Workbook
Name aquimsj1: 'Soja SS'!$E$30
Name aquimsj1: Camelina!$E$30
Name labsj1: NA()
Name semsj1: 'Soja SS'!$E$36
Name semsj1: Camelina!$E$37

Sheet Cotizaciones
A1: PROYECCIÓN ALEA SIEMBRA: COTIZACIONES
A4: MONEDAS | D4: LABORES (U$/Ha) // FLETES (U$/TON) | H4: AGROQUÍMICOS/FERTILIZANTES (U$/Unid) | L4: PRODUCTO (U$/Ton)
A5: Dólar | B5: 10 | D5: Análisis | E5: 13 | H5: 2,4-D | I5: 4.6 | J5: Lt | L5: 43132 | M5: 19.97
A6: Euro | B6: 6 | D6: Aplicación Cebo | E6: - | F6: 5 | H6: Aceite Vegetal | I6: 3 | J6: Lt | L6: 43160 | M6: 20.285
D7: Cultivador | E7: 170 | H7: Acetoclor | I7: 7.2 | J7: Lt | L7: 43191 | M7: 20.679
A8: PRODUCTO (U$/Ton) | C8: Px bruto | D8: Disco, Rastra y Rolo | E8: 600 | H8: Allegro | I8: 20 | J8: Lt | L8: 43221 | M8: 20.97
A9: Cebada Cervera | B9: 245 | D9: Escardillo | E9: 180 | H9: Arrancador Azufrado | I9: 770 | J9: Ton | L9: 43252 | M9: 21.28
A10: Cebada Forrajera | B10: 220 | D10: Fertilización Urea | E10: =180*1.15 -> 207 | H10: Atrazina granulada | I10: 5.7 | J10: kg | L10: 43282 | M10: 21.61
A11: Colza | D11: Fertilización UAN | E11: =80*1.15 -> 92 | H11: Axial | I11: 39 | J11: Lt | L11: 43313 | M11: 21.92 | N11: rofex
A12: Girasol | B12: 450 | D12: Limpieza, Curada e Inoculada | E12: =420*1.15 -> 483 | H12: Bellis | I12: 39 | J12: Lt | L12: 43344 | M12: 22.2
A13: Maíz | B13: 200 | D13: Medición Satelital | E13: - | H13: Caramba | I13: 16.7 | J13: Lt | L13: 43374 | M13: 22.52
A14: Soja | B14: 355 | D14: Monitoreo B y BB. | E14: - | F14: 5 | H14: Cebo | I14: 7 | J14: Lt | L14: 43405 | M14: 22.81
A15: Trigo | B15: 230 | C15: =+'Trigo SP'!E73 -> 201.04308 | D15: Muestreo de Suelos | E15: - | F15: 1 | H15: lambda 25% | I15: 20 | J15: Lt | L15: 43435 | M15: 22.95
D16: Pulverización Aerea | F16: 13 | H16: Clearsol | I16: 170 | J16: 12 | L16: 43466 | M16: 23.25
D17: Pulverización Terrestre | F17: 5 | H17: Clearsol Plus | I17: 20 | L17: 43497 | M17: 23.553922
D18: Rolo Picador | F18: 17 | H18: Clorimuron | I18: =21*1.05 -> 22.05 | J18: Kg | L18: 43525 | M18: 23.861816
D19: Siembra Conv. Fina | H19: Clorpirifos | I19: 7 | J19: Lt | L19: 43556 | M19: 24.173735
D20: Siembra Conv. Gruesa | H20: Coadyudante (Acampo max N)18 | I20: 20 | J20: Lt | L20: 43586 | M20: 24.489732
D21: Siembra Directa Fina | F21: 42 | H21: Coadyugante Extremo | I21: 12 | J21: Lt
D22: Siembra Directa Gruesa | F22: 42 | H22: Curasemillas Fina (sist) | I22: 80 | J22: tn
H23: Dicamba | I23: 7 | J23: Lt
D24: Extracción Embolsado | F24: 3.3 | H24: Fluorucloridona | I24: 11.8 | J24: Lt
D25: Flete Cereal 110 kms | F25: 20 | H25: Fosforo (MAP / DAP) | I25: 990 | J25: Ton | K25: Aproximado
D26: Flete Semilla 110 kms | F26: 35 | H26: Orquesta | I26: 28 | J26: Lt
D27: Secada Cebada Cervecera | F27: 3 | H27: Cletodyn | I27: 6 | J27: Lt
D28: Secada Cebada Forrajera | F28: 3 | H28: Glifosato | I28: 4.5 | J28: Lt | K28: 0.54
D29: Secada Colza | F29: 3 | H29: Inoculante (Combi full action) | I29: 250 | J29: pack (3 ton)
D30: Secada Maíz | F30: 3 | H30: coragen | I30: 100 | J30: Lt
D31: Secada Girasol | F31: 3 | H31: lambda 25% | I31: 20 | J31: Lt
H32: MCPA 75 % | I32: 11
D33: Secada Soja | F33: 3 | H33: Lontrel | I33: 35 | J33: Lt
D34: Secada Trigo | F34: 3 | H34: Nitrogeno (Urea) | I34: 610 | J34: Ton | K34: Aproximado
D35: Paritaria | F35: 5 | H35: Nitrogeno Líquido 32% (Solmix) | I35: 440 | J35: Ton
D36: Traspile | F36: 6.5 | H36: Picloran | I36: 7 | J36: l
H37: Metsulfuron | I37: 35 | J37: Kg
H38: Peack Pack | I38: 125 | J38: Pack
D39: SEMILLA (U$/Ton) | H39: Pibot | I39: 8 | J39: Lt
D40: Semilla Cebada Curada | E40: 0.52 | F40: Ton | H40: Silobolsa Fina | I40: 380 | J40: 220 tn
D41: Semilla Colza | E41: 300 | F41: bolsa 20 Kg | H41: Silobolsa Gruesa | I41: 410 | J41: 210 tons
D42: Semilla Girasol | E42: 300 | F42: 150mil Sem | H42: Sulfato de Amonio | I42: 1.1 | J42: lts
D43: Semilla Girasol Oleico | E43: 330 | F43: 180mil Sem | H43: sulfosato | I43: =+I28 -> 4.5 | J43: Lts
D44: Semilla Maíz | E44: 180 | F44: 80mil sem | H44: Acuron Pack | I44: 400 | J44: pack 10 has
D45: Semilla Soja | E45: 35 | F45: Bolsa 40kg | H45: PARAQUAT | I45: 2.6 | J45: Lts
D46: Semilla Soja propia | E46: =+B14 -> 355 | F46: Ton | H46: carfentrazone | I46: 80 | J46: l
D47: Semilla Trigo | E47: 0.525 | F47: Ton | H47: spider | I47: 200
H48: Starane | I48: 37
H49: texaro | I49: 390
H50: yamato top | I50: 80
H51: fomesafen | I51: 7.2
H52: Sulfentrazone | I52: 19
B53: =+'Cebada SP'!B3 -> 0 | E53: =+'Trigo SP'!B3 -> 0 | H53: convey | I53: 200 | L53: =+'Girasol SP'!B3 -> 0
A54: Agroquímicos | B54: cebada | D54: Agroquimicos | E54: Trigo | H54: =+D54 -> Agroquimicos | I54: Maiz | K54: Agroquímicos | L54: Girasol
A55: Curasemillas | B55: 0.25 | C55: =+B55*C70 -> 0 | D55: Curasemillas | E55: 0.25 | F55: =+E55*$E$53 -> 0 | H55: Coadyuvante | I55: 0.2 | J55: =+I55*$I$53 -> 40 | K55: Coadyuvante | L55: 0.2 | M55: =+L55*$L$53 -> 0
A56: Coadyugante (Lecitina) | B56: 0.15 | C56: =+B56*$B$53 -> 0 | D56: Coadyugante (Lecitina) | E56: 0.15 | F56: =+E56*$E$53 -> 0 | H56: Inoculante | I56: 0 | J56: =+I56*$I$53 -> 0 | K56: Glifosato | L56: 4.5 | M56: =+L56*$L$53 -> 0
A57: Aceite Vegetal | B57: 1 | C57: =+B57*$B$53 -> 0 | D57: Aceite vegetal | E57: 1 | F57: =+E57*$E$53 -> 0 | H57: Sulfosato | I57: 6 | J57: =+I57*$I$53 -> 1200 | K57: 2,4-D | L57: 1.2 | M57: =+L57*$L$53 -> 0
A58: Sulfosato | B58: 2.2 | C58: =+B58*$B$53 -> 0 | D58: Sulfosato | E58: 2.2 | F58: =+E58*$E$53 -> 0 | H58: 2,4-D | I58: 1.2 | J58: =+I58*$I$53 -> 240 | K58: Lontrel | L58: 0.2 | M58: =+L58*$L$53 -> 0
A59: 2,4-D | B59: 1 | C59: =+B59*$B$53 -> 0 | D59: 2,4-D | E59: 0.8 | F59: =+E59*$E$53 -> 0 | H59: Picloran | I59: 0.15 | J59: =+I59*$I$53 -> 30 | K59: Dicamba | L59: 0.2 | M59: =+L59*$L$53 -> 0
A60: Picloran | B60: 0.12 | C60: =+B60*$B$53 -> 0 | D60: Picloran | E60: 0.08 | F60: =+E60*$E$53 -> 0 | H60: Lontrel | I60: 0.2 | J60: =+I60*$I$53 -> 40 | K60: Clearsol CP | L60: 2 | M60: =+L60*$L$53 -> 0
A61: Axial | B61: 0.3 | C61: =+B61*$B$53 -> 0 | D61: Axial | E61: 0.3 | F61: =+E61*$E$53 -> 0 | H61: Atrazina | I61: 3 | J61: =+I61*$I$53 -> 600 | K61: Karate Zeon | L61: 0.015 | M61: =+L61*$L$53 -> 0
A62: Fungicida (Orquesta) | B62: 1.5 | C62: =+B62*$B$53 -> 0 | D62: Fungicida (Opera) | E62: 0.8 | F62: =+E62*$E$53 -> 0 | H62: Dicamba | I62: 0.2 | J62: =+I62*$I$53 -> 40 | K62: Clorpirifos | L62: 0.8 | M62: =+L62*$L$53 -> 0
A63: Soprano | B63: 0 | C63: =+B63*$B$53 -> 0 | D63: Metsulfurón | E63: 0.008 | F63: =+E63*$E$53 -> 0 | H63: Cebo | I63: 2 | J63: =+I63*$I$53 -> 400 | K63: Starane | L63: 0.2 | M63: =+L63*$L$53 -> 0
A64: Peack Pack | B64: 0 | C64: =+B64*$B$53 -> 0 | D64: Dicamba | E64: 0.2 | F64: =+E64*$E$53 -> 0 | H64: Ferti | I64: 0.08 | J64: =+I64*$I$53 -> 16 | K64: cebo | L64: 3 | M64: =+L64*$L$53 -> 0
A65: Dicamba | B65: 0.2 | C65: =+B65*$B$53 -> 0 | D65: Peack Pack | E65: 0 | F65: =+E65*$E$53 -> 0 | H65: urea | I65: 0.16 | J65: =+I65*$I$53 -> 32 | K65: ferti | L65: 0.04 | M65: =+L65*$L$53 -> 0
A66: Clorpirifos | B66: 0.4 | C66: =+B66*$B$53 -> 0 | D66: Clorpirifos | E66: 0.4 | F66: =+E66*$E$53 -> 0 | H66: semilla | I66: 0.65 | J66: =+I66*$I$53 -> 130 | K66: urea | L66: 0.03 | M66: =+L66*$L$53 -> 0
A67: Metsulfuron | B67: 0.01 | C67: =+B67*$B$53 -> 0 | D67: Fertilizantes | E67: 0.08 | F67: =+E67*$E$53 -> 0 | H67: Graminicida | I67: 0.7 | J67: =+I67*$I$53*0.1 -> 14 | K67: semilla | L67: 0.38 | M67: =+L67*$L$53 -> 0
A68: Fertilizantes | B68: 0.08 | C68: =+B68*$B$53 -> 0 | D68: Urea | E68: 0.2 | F68: =+E68*$E$53 -> 0 | K68: Graminicida | L68: 0.7 | M68: =+L68*$L$53*0.1 -> 0
A69: Urea | B69: 0.18 | C69: =+B69*$B$53 -> 0 | D69: semilla | E69: 0.14 | F69: =+E69*$E$53*0.2 -> 0
A70: semilla | B70: 0.14 | C70: =+B70*$B$53 -> 0 | D70: Graminicida | E70: 0.7 | F70: =+E70*$E$53*0.1 -> 0
A71: Graminicida | B71: 0.7 | C71: =+B71*$B$53*0.1 -> 0
A72: curasemilla sistiva
A73: coadyudante | B73: =+C56+F56+J55+M55 -> 40 | C73: =+I21 -> 12
A74: Aceite | B74: =+C57+F57 -> 0 | C74: =+I6 -> 3
A75: Sulfosato | B75: =+C58+F58+J57+M56 -> 1200 | C75: =+I43 -> 4.5
A76: 24d | B76: =+C59+F59+J58+M57 -> 240 | C76: =+I5 -> 4.6
A77: Picloran | B77: =+C60+F60+J59 -> 30 | C77: =+I36 -> 7
A78: Axial | B78: =+C61 -> 0 | C78: =+I11 -> 39
A79: Fungicida (Orquesta) | B79: =+C62 -> 0 | C79: +
A80: Fungicida Opera | B80: =+F62 -> 0
A81: =+A65 -> Dicamba | B81: =+C65+F64+J62+M59 -> 40
A82: clorpirifos | B82: =+C66+F66 -> 0
A83: =+A67 -> Metsulfuron | B83: =+C67 -> 0
A84: =+A68 -> Fertilizantes | B84: =+C68+F67+J64+M65 -> 16
A85: Urea | B85: =+C69+F68+J65+M66 -> 32
A86: Semilla cebada
A87: semilla Trigo
A88: Semilla Maiz
A89: Semilla Girasol

Sheet Resumen Proy
A1: Proyeccion General 2526
Q3: SUELOS PROFUNDOS | AC3: doble cultivo
B4: Has | C4: Rinde | D4: Arrend. | E4: Precio | F4: Ingreso Bruto | G4: Costo | H4: Px dolor | I4: R. Indif | J4: Resultado | K4: Inversión Real | L4: costo prod/tn | M4: costo tn/Px | N4: Retorno | O4: Retorno | Q4: Administración | AC4: Retorno | AD4: Retorno
C5: Tons / Ha | D5: U$ / Ha | E5: U$ / Ton | F5: U$ / Ha | G5: U$ / Ha | I5: Tons / Ha | J5: U$ / Ha | K5: U$ / Ha | N5: Inversion | O5: costos | Q5: u$ / Ton | R5: U$ | S5: $ | AC5: costos | AD5: Inversion
A6: Trigo / SOJA 2DA | B6: ='Trigo SP'!B3 -> 0 | C6: ='Trigo SP'!B75 -> 5.7 | D6: =+C57 -> 426 | E6: =Cotizaciones!B15 -> 230 | F6: =+'Trigo SP'!B79 -> 1123.0267 | G6: ='Trigo SP'!B77 -> 1026.77 | H6: =+('Trigo SP'!B77+'Trigo SP'!E70)/'Trigo SP'!B75 -> 209.09201 | I6: ='Trigo SP'!B82 -> 5.1072138 | J6: ='Trigo SP'!B80 -> 96.256658 | K6: ='Trigo SP'!B83 -> 921.77 | L6: =+G6/C6 -> 180.13509 | M6: =+L6/E6 -> 0.78319603 | N6: =+'Trigo SP'!B84 -> 0.1044259 | O6: =+'Trigo SP'!B81 -> 0.09374705 | P6: =G6*B6 -> 0 | Q6: ='[1]Trigo SP'!E30 -> 50.35 | R6: =Q6*B6 -> 0 | S6: =R6*[1]Cotizaciones!$B$5 -> 0 | T6: Trigo / Soja 2da | AA6: =(J6+G6)*B6 -> 0 | AC6: =+'Trigo SP'!H81 -> Ha | AD6: =+'Trigo SP'!H84 -> 0
B7: =+'Soja 2da. T'!B3 -> 0 | C7: ='Soja 2da. T'!B73 -> 1.3 | D7: 0 | E7: =+Cotizaciones!B14 -> 355 | F7: =+'Soja 2da. T'!B76 -> 414.33491 | G7: =+'Soja 2da. T'!B75 -> 404.65 | H7: =+('Soja 2da. T'!B75+'Soja 2da. T'!E67)/'Soja 2da. T'!B73 -> 347.55007 | I7: =+'Soja 2da. T'!B79 -> 1.269613 | J7: =+'Soja 2da. T'!B77 -> 9.6849149 | K7: =+'Soja 2da. T'!B80 -> 296.65 | L7: =+G7/C7 -> 311.26923 | M7: =+L7/E7 -> 0.87681473 | N7: =+'Soja 2da. T'!B81 -> 0.032647615 | O7: =+'Soja 2da. T'!B78 -> 0.023934054 | P7: =G7*B7 -> 0 | Q7: ='[1]Soja 2da. C'!E28 -> 22.4 | R7: =Q7*B7 -> 0 | S7: =R7*[1]Cotizaciones!$B$5 -> 0 | AA7: =(J7+G7)*B7 -> 0
A8: Cebada / Soja 2da | B8: =+'Cebada SP'!B3 -> 0 | C8: ='Cebada SP'!B80 -> 5.7 | D8: =+'Cebada SP'!D26 -> 426 | E8: =+Cotizaciones!B9 -> 245 | F8: ='Cebada SP'!B84 -> 1152.7368 | G8: ='Cebada SP'!B82 -> 1044.71 | H8: =+('Cebada SP'!B82+'Cebada SP'!E73)/'Cebada SP'!B80 -> 209.67069 | I8: ='Cebada SP'!B87 -> 5.0625172 | J8: =+'Cebada SP'!B85 -> 108.02684 | K8: ='Cebada SP'!B88 -> 939.71 | L8: =+G8/C8 -> 183.28246 | M8: =+L8/E8 -> 0.74809166 | N8: =+'Cebada SP'!B89 -> 0.11495764 | O8: =+'Cebada SP'!B86 -> 0.10340367 | P8: =G8*B8 -> 0 | Q8: ='[1]Cebada SP'!E30 -> 52.5 | R8: =Q8*B8 -> 0 | S8: =R8*[1]Cotizaciones!$B$5 -> 0 | T8: Cebada / Soja 2da | AA8: =(J8+G8)*B8 -> 0 | AC8: =+'Soja 2da. C'!D79 -> 0.12567587 | AD8: =+'Cebada SP'!E87 -> 0.14623846 | AF8: =+B8*C8 -> 0
B9: =+'Soja 2da. C'!B3 -> 0 | C9: ='Soja 2da. C'!B74 -> 1.5 | D9: 0 | E9: =Cotizaciones!B14 -> 355 | F9: ='Soja 2da. C'!B77 -> 472.41267 | G9: ='Soja 2da. C'!B76 -> 399 | H9: =+('Soja 2da. C'!B76+'Soja 2da. C'!E68)/'Soja 2da. C'!B74 -> 299.63083 | I9: ='Soja 2da. C'!B80 -> 1.2415628 | J9: =+'Soja 2da. C'!B78 -> 73.412673 | K9: ='Soja 2da. C'!B81 -> 301 | L9: =+G9/C9 -> 266 | M9: =+L9/E9 -> 0.74929577 | N9: =+'Soja 2da. C'!B82 -> 0.24389592 | O9: =+'Soja 2da. C'!B79 -> 0.18399166 | P9: =G9*B9 -> 0 | Q9: ='[1]Soja 2da. C'!E28 -> 22.4 | R9: =Q9*B9 -> 0 | S9: =R9*[1]Cotizaciones!$B$5 -> 0 | AA9: =(J9+G9)*B9 -> 0 | AF9: =+B9*C9 -> 0
A10: Maiz 2da | B10: 0 | C10: =+'Maiz 2da'!B76 -> 4.5 | D10: 0 | E10: =+Cotizaciones!B13 -> 200 | F10: =+'Maiz 2da'!B79 -> 719.72853 | G10: =+'Maiz 2da'!E69 -> 654.65 | I10: =+'Maiz 2da'!B82 -> 4.0112437 | J10: =+F10-G10 -> 65.078528 | K10: =+'Maiz 2da'!B83 -> 536.61 | L10: =+G10/C10 -> 145.47778 | M10: =+L10/E10 -> 0.72738889 | N10: =+'Maiz 2da'!B84 -> 0.12127714 | O10: =+'Maiz 2da'!B81 -> 0.099409651 | P10: =G10*B10 -> 0 | R10: =Q10*B10 -> 0 | S10: =R10*[1]Cotizaciones!$B$5 -> 0 | T10: Colza / Soja 2da | AA10: =(J10+G10)*B10 -> 0 | AC10: =+'Maiz 2da'!D81 -> 0.10186504
A11: Girasol | B11: =+'Girasol SP'!B3 -> 0 | C11: =+'Girasol SP'!B83 -> 2.6 | D11: =+'Girasol SP'!E28 -> 426 | E11: =+Cotizaciones!B12 -> 450 | F11: ='Girasol SP'!B89 -> 971.77383 | G11: ='Girasol SP'!B88 -> 972.71 | H11: =+('Girasol SP'!B88+'Girasol SP'!E77)/'Girasol SP'!B83-'Girasol SP'!B85 -> 358.36007 | I11: =+'Girasol SP'!B92 -> 2.6025047 | J11: =+F11-G11 -> -0.93617029 | K11: =+'Girasol SP'!B93 -> 872.71 | L11: =+G11/C11 -> 374.11923 | M11: =+L11/E11 -> 0.83137607 | N11: =+'Girasol SP'!B94 -> -0.0010727164 | O11: =+'Girasol SP'!B91 -> -0.00096243514 | P11: =G11*B11 -> 0 | Q11: ='[1]Soja 2da. C'!E28 -> 22.4 | R11: =Q11*B11 -> 0 | S11: =R11*[1]Cotizaciones!$B$5 -> 0 | AA11: =(J11+G11)*B11 -> 0 | AC11: =+'Girasol 2da'!D75 -> 0 | AF11: =+B11*C11 -> 0
A12: Maíz | B12: ='Maiz SP'!B3 -> 0 | C12: ='Maiz SP'!B76 -> 8.5 | D12: =+'Maiz SP'!D27 -> 426 | E12: =Cotizaciones!B13 -> 200 | F12: ='Maiz SP'!B79 -> 1346.5629 | G12: ='Maiz SP'!B78 -> 1152.01 | H12: =+('Maiz SP'!B78+'Maiz SP'!E71)/'Maiz SP'!B76 -> 177.11142 | I12: ='Maiz SP'!B82 -> 7.2719106 | J12: =+'Maiz SP'!B80 -> 194.5529 | K12: ='Maiz SP'!B83 -> 1017.01 | L12: =+G12/C12 -> 135.53059 | M12: =+L12/E12 -> 0.67765294 | N12: ='Maiz SP'!B84 -> 0.19129891 | O12: ='Maiz SP'!B81 -> 0.16888126 | P12: =G12*B12 -> 0 | R12: =Q12*B12 -> 0 | S12: =R12*[1]Cotizaciones!$B$5 -> 0 | T12: Maíz | AA12: =(J12+G12)*B12 -> 0 | AF12: =+B12*C12 -> 0
A13: Girasol Oleico | B13: ='Girasol O SP'!B3 -> 0 | C13: ='Girasol O SP'!B80 -> 2.6 | D13: =+'Girasol O SP'!D27 -> 426 | E13: ='Girasol O SP'!B85 -> 380.21917 | F13: ='Girasol O SP'!B87 -> 968.79843 | G13: ='Girasol O SP'!B86 -> 975.72667 | H13: =+('Girasol O SP'!B86+'Girasol O SP'!E73)/'Girasol O SP'!B80-'Girasol O SP'!B82 -> 355.06032 | I13: ='Girasol O SP'!B90 -> 2.5662217 | J13: =+'Girasol O SP'!B88 -> -6.9282335 | K13: ='Girasol O SP'!B91 -> 875.72667 | L13: =+G13/C13 -> 375.27949 | M13: =+L13/E13 -> 0.98700834 | N13: ='Girasol O SP'!B92 -> -0.007911411 | O13: ='Girasol O SP'!B89 -> -0.0071005885 | P13: =G13*B13 -> 0 | R13: =Q13*B13 -> 0 | AA13: =(J13+G13)*B13 -> 0
A14: Girasol | B14: 0 | C14: ='Girasol SP'!B83 -> 2.6 | D14: =+'Girasol SP'!D28 -> 426 | E14: ='Girasol SP'!B87 -> 373.75917 | F14: ='Girasol SP'!B89 -> 971.77383 | G14: ='Girasol SP'!B88 -> 972.71 | I14: ='Girasol SP'!B92 -> 2.6025047 | J14: =+'Girasol SP'!B90 -> -0.93617029 | K14: ='Girasol SP'!B93 -> 872.71 | L14: =+G14/C14 -> 374.11923 | M14: =+L14/E14 -> 1.0009634 | N14: ='Girasol SP'!B94 -> -0.0010727164 | O14: ='Girasol SP'!B91 -> -0.00096243514 | P14: =G14*B14 -> 0 | R14: =Q14*B14 -> 0 | S14: =R14*[1]Cotizaciones!$B$5 -> 0 | T14: Girasol | AA14: =(J14+G14)*B14 -> 0
A15: Soja | B15: =Camelina!B3 -> 0 | C15: =Camelina!B82 -> 1 | D15: =+C57 -> 426 | E15: =Cotizaciones!B14 -> 355 | F15: =Camelina!B85 -> 416.45 | G15: =Camelina!B84 -> 399.5 | I15: =Camelina!B88 -> 0.95929884 | J15: =+Camelina!B86 -> 16.95 | K15: =Camelina!B89 -> 304.5 | L15: =+G15/C15 -> 399.5 | M15: =+L15/E15 -> 1.1253521 | N15: =Camelina!B90 -> 0.055665025 | O15: =Camelina!B87 -> 0.042428035 | P15: =G15*B15 -> 0 | R15: =Q15*B15 -> 0 | S15: =R15*[1]Cotizaciones!$B$5 -> 0 | T15: Soja | AA15: =(J15+G15)*B15 -> 0
A16: TOTAL / HA | B16: =+B12+B8+B14+B6+B15+B13 -> 0 | C16: =((C6*B6)+(C7*B7)+(C8*B8)+(C9*B9)+(C10*B10)+(C11*B11)+(C12*B12)+(C13*B13)+(C14*B14)+(C15*B15))/(B16+B11+B9+B7) -> #DIV/0! | D16: =((D6*B6)+(D7*B7)+(D8*B8)+(D9*B9)+(D10*B10)+(D11*B11)+(D12*B12)+(D13*B13)+(D14*B14)+(D15*B15))/B16 -> #DIV/0! | E16: =((E6*B6)+(E7*B7)+(E8*B8)+(E9*B9)+(E10*B10)+(E11*B11)+(E12*B12)+(E13*B13)+(E14*B14)+(E15*B15))/(B16+B7+B9+B11) -> #DIV/0! | F16: =((F6*B6)+(F7*B7)+(F8*B8)+(F9*B9)+(F10*B10)+(F11*B11)+(F12*B12)+(F13*B13)+(F14*B14)+(F15*B15))/(B16) -> #DIV/0! | G16: =((G6*B6)+(G7*B7)+(G8*B8)+(G9*B9)+(G10*B10)+(G11*B11)+(G12*B12)+(G13*B13)+(G14*B14)+(G15*B15))/(B16) -> #DIV/0! | I16: =((I6*B6)+(I7*B7)+(I8*B8)+(I9*B9)+(I10*B10)+(I11*B11)+(I12*B12)+(I13*B13)+(I14*B14)+(I15*B15))/(B16+B7+B9+B11) -> #DIV/0! | J16: =J17/B16 -> #DIV/0! | K16: =((K6*B6)+(K7*B7)+(K8*B8)+(K9*B9)+(K10*B10)+(K11*B11)+(K12*B12)+(K13*B13)+(K14*B14)+(K15*B15))/(B16+B7+B9+B11) -> #DIV/0! | N16: RI | O16: =J16/K16 -> #DIV/0! | P16: =SUM(P6:P15) -> 0 | Q16: =SUM(Q6:Q15) -> 170.05 | R16: =SUM(R6:R15) -> 0 | S16: =SUM(S6:S15) -> 0 | T16: =SUM(T6:T15) -> 0 | U16: =SUM(U6:U15) -> 0 | V16: =SUM(V6:V15) -> 0 | W16: =SUM(W6:W15) -> 0 | ... AA16: =SUM(AA6:AA15) -> 0
A17: TOTAL | D17: =+'[2]Alquileres por campo'!$S$64 -> 0 | F17: =((F6*B6)+(F7*B7)+(F8*B8)+(F9*B9)+(F10*B10)+(F11*B11)+(F12*B12)+(F13*B13)+(F14*B14)+(F15*B15)) -> 0 | G17: =((G6*B6)+(G7*B7)+(G8*B8)+(G9*B9)+(G10*B10)+(G11*B11)+(G12*B12)+(G13*B13)+(G14*B14)+(G15*B15)) -> 0 | J17: =((J6*B6)+(J7*B7)+(J8*B8)+(J9*B9)+(J10*B10)+(J11*B11)+(J12*B12)+(J13*B13)+(J14*B14)+(J15*B15)) -> 0 | K17: =((K6*B6)+(K7*B7)+(K8*B8)+(K9*B9)+(K10*B10)+(K11*B11)+(K12*B12)+(K13*B13)+(K14*B14)+(K15*B15)) -> 0 | N17: RC | O17: =J16/G16 -> #DIV/0!
B19: SUELOS SOMEROS
B20: Has | C20: Rinde | D20: Arrend. | E20: Precio | F20: Ingreso Bruto | G20: Costo | I20: Rinde Indif | J20: Resultado | K20: Inversión Real | N20: Retorno | O20: Retorno
C21: Tons / Ha | D21: U$ / Ha | E21: U$ / Ton | F21: U$ / Ha | G21: U$ / Ha | I21: Tons / Ha | J21: u$ / Ton | K21: U$ / ha | N21: Real | O21: Nominal
A22: Trigo / Soja 2da | B22: 0 | C22: ='Trigo SS'!B71 -> 4 | D22: 224 | E22: =E6 -> 230 | F22: ='Trigo SS'!B74 -> 920 | G22: ='Trigo SS'!B73 -> 722.52875 | I22: ='Trigo SS'!B77 -> 3.0386015 | J22: ='Trigo SS'!B75 -> 197.47125 | K22: ='Trigo SS'!B78 -> 497.25 | N22: ='Trigo SS'!B79 -> 0.3971267 | O22: ='Trigo SS'!H79 -> 0.26093483 | P22: =G22*B22 -> 0 | Q22: ='[1]Trigo SP'!E46 -> 78.845 | R22: =Q22*B22 -> 0 | S22: =R22*[1]Cotizaciones!$B$5 -> 0 | T22: Trigo / Soja 2da | AA22: =(J22+G22)*B22 -> 0
B23: 0 | C23: =C7 -> 1.3 | D23: 56 | E23: =E7 -> 355 | F23: ='Soja 2da. T'!B76 -> 414.33491 | G23: =G7 -> 404.65 | I23: =I7 -> 1.269613 | J23: =J7 -> 9.6849149 | K23: =K7 -> 296.65 | N23: =N7 -> 0.032647615 | P23: =G23*B23 -> 0 | Q23: ='[1]Soja 2da. C'!E44 -> 5.118 | R23: =Q23*B23 -> 0 | S23: =R23*[1]Cotizaciones!$B$5 -> 0 | AA23: =(J23+G23)*B23 -> 0
A24: Cebada / Soja 2da | B24: 0 | C24: ='Cebada SS '!B73 -> 5 | D24: 224 | E24: =E8 -> 245 | F24: ='Cebada SS '!B76 -> 1225 | G24: =+'Cebada SS '!E70 -> 832.447 | I24: ='Cebada SS '!B79 -> 3.2189065 | J24: ='Cebada SS '!B77 -> 392.553 | K24: ='Cebada SS '!B80 -> 569.865 | N24: ='Cebada SS '!B81 -> 0.68885262 | O24: ='Cebada SS '!B78 -> 0.47156516 | P24: =G24*B24 -> 0 | Q24: ='[1]Cebada SP'!E46 -> 0 | R24: =Q24*B24 -> 0 | S24: =R24*[1]Cotizaciones!$B$5 -> 0 | T24: Cebada / Soja 2da | AA24: =(J24+G24)*B24 -> 0
B25: 0 | C25: ='Soja 2da. C'!B74 -> 1.5 | D25: 56 | E25: =E9 -> 355 | F25: ='Soja 2da. C'!B77 -> 472.41267 | G25: ='Soja 2da. C'!B76 -> 399 | I25: ='Soja 2da. C'!B80 -> 1.2415628 | J25: ='Soja 2da. C'!B78 -> 73.412673 | K25: ='Soja 2da. C'!B81 -> 301 | P25: =G25*B25 -> 0 | Q25: ='[1]Soja 2da. C'!E44 -> 5.118 | R25: =Q25*B25 -> 0 | S25: =R25*[1]Cotizaciones!$B$5 -> 0 | AA25: =(J25+G25)*B25 -> 0
A26: Colza / Soja 2da | B26: 0 | C26: ='Girasol 2da'!B69 -> 1.3 | D26: 224 | E26: =E10 -> 200 | F26: ='Girasol 2da'!B73 -> 522.91365 | G26: ='Girasol 2da'!B72 -> 507.33333 | I26: ='Girasol 2da'!B76 -> 1.1236735 | J26: ='Girasol 2da'!B74 -> 15.580321 | K26: ='Girasol 2da'!B77 -> 411.29333 | N26: ='Girasol 2da'!B78 -> 0.037881288 | O26: ='Girasol 2da'!H78 -> 0 | P26: =G26*B26 -> 0 | R26: =Q26*B26 -> 0 | S26: =R26*[1]Cotizaciones!$B$5 -> 0 | T26: Colza / Soja 2da | AA26: =(J26+G26)*B26 -> 0
B27: 0 | C27: ='Soja 2da. Co'!B71 -> 1.5 | D27: 56 | E27: =E11 -> 450 | F27: ='Soja 2da. Co'!B74 -> 532.5 | G27: =G11 -> 972.71 | I27: =I11 -> 2.6025047 | J27: =J11 -> -0.93617029 | K27: =K11 -> 872.71 | N27: =N11 -> -0.0010727164 | P27: =G27*B27 -> 0 | Q27: ='[1]Soja 2da. C'!E44 -> 5.118 | R27: =Q27*B27 -> 0 | S27: =R27*[1]Cotizaciones!$B$5 -> 0 | AA27: =(J27+G27)*B27 -> 0
A28: Maíz | B28: 0 | C28: 5.5 | D28: 0 | E28: 0 | F28: 0 | G28: 0 | I28: 0 | J28: 0 | K28: 0 | N28: 0 | P28: =G28*B28 -> 0 | R28: =Q28*B28 -> 0 | S28: =R28*[1]Cotizaciones!$B$5 -> 0 | T28: Maíz | AA28: =(J28+G28)*B28 -> 0
A29: Girasol | B29: 0 | C29: 2 | D29: 280 | E29: =E14 -> 373.75917 | F29: ='Girasol SS'!B82 -> 1166.4 | G29: ='Girasol SS'!B81 -> 745.87253 | I29: ='Girasol SS'!B85 -> 1.4863064 | J29: ='Girasol SS'!B83 -> 420.52747 | K29: ='Girasol SS'!B86 -> 550.93333 | N29: ='Girasol SS'!B87 -> 0.7633001 | P29: =G29*B29 -> 0 | R29: =Q29*B29 -> 0 | AA29: =(J29+G29)*B29 -> 0
A30: Girasol Oleico | B30: 0 | C30: ='Girasol O SS'!B74 -> 2 | D30: 280 | E30: =E13 -> 380.21917 | F30: =E30*C30 -> 760.43833 | G30: ='Girasol O SS'!B80 -> 740.01536 | I30: ='Girasol O SS'!B84 -> 1.3690907 | J30: ='Girasol O SS'!B82 -> 311.98464 | K30: ='Girasol O SS'!B85 -> 546.08 | N30: ='Girasol O SS'!B86 -> 0.57131673 | O30: ='Girasol O SS'!B83 -> 0.42159211 | P30: =G30*B30 -> 0 | R30: =Q30*B30 -> 0 | S30: =R30*[1]Cotizaciones!$B$5 -> 0 | T30: Girasol | AA30: =(J30+G30)*B30 -> 0
A31: Soja | B31: 0 | C31: ='Soja SS'!B81 -> 2.8 | D31: 280 | E31: =E15 -> 355 | F31: ='Soja SS'!B84 -> 994 | G31: ='Soja SS'!E73 -> 934.2697 | I31: ='Soja SS'!B87 -> 2.6185868 | J31: ='Soja SS'!B85 -> 59.7303 | K31: ='Soja SS'!B88 -> 653.15 | N31: ='Soja SS'!B89 -> 0.09144959 | O31: ='Soja SS'!B86 -> 0.069279053 | P31: =G31*B31 -> 0 | R31: =Q31*B31 -> 0 | S31: =R31*[1]Cotizaciones!$B$5 -> 0 | T31: Soja | AA31: =(J31+G31)*B31 -> 0
A32: TOTAL / HA | B32: =SUM(B22:B31)-B23-B25-B27 -> 0 | C32: =((C22*B22)+(C23*B23)+(C24*B24)+(C25*B25)+(C26*B26)+(C27*B27)+(C28*B28)+(C29*B29)+(C30*B30)+(C31*B31))/(B32+B27+B25+B23) -> #DIV/0! | D32: =((D22*B22)+(D23*B23)+(D24*B24)+(D25*B25)+(D26*B26)+(D27*B27)+(D28*B28)+(D29*B29)+(D30*B30)+(D31*B31))/B32 -> #DIV/0! | E32: =((E22*B22)+(E23*B23)+(E24*B24)+(E25*B25)+(E26*B26)+(E27*B27)+(E28*B28)+(E29*B29)+(E30*B30)+(E31*B31))/(B32+B23+B25+B27) -> #DIV/0! | F32: =((F22*B22)+(F23*B23)+(F24*B24)+(F25*B25)+(F26*B26)+(F27*B27)+(F28*B28)+(F29*B29)+(F30*B30)+(F31*B31))/(B32+B25) -> #DIV/0! | G32: =((G22*B22)+(G23*B23)+(G24*B24)+(G25*B25)+(G26*B26)+(G27*B27)+(G28*B28)+(G29*B29)+(G30*B30)+(G31*B31))/(B32+B25) -> #DIV/0! | I32: =((I22*B22)+(I23*B23)+(I24*B24)+(I25*B25)+(I26*B26)+(I27*B27)+(I28*B28)+(I29*B29)+(I30*B30)+(I31*B31))/(B32+B23+B25+B27) -> #DIV/0! | J32: =((J22*B22)+(J23*B23)+(J24*B24)+(J25*B25)+(J26*B26)+(J27*B27)+(J28*B28)+(J29*B29)+(J30*B30)+(J31*B31))/(B32+B25) -> #DIV/0! | K32: =((K22*B22)+(K23*B23)+(K24*B24)+(K25*B25)+(K26*B26)+(K27*B27)+(K28*B28)+(K29*B29)+(B30*K30)+(K31*B31))/(B32+B25) -> #DIV/0! | N32: RR | O32: =J32/K32 -> #DIV/0! | P32: =SUM(P22:P31) -> 0 | Q32: =SUM(Q22:Q31) -> 94.199 | R32: =SUM(R22:R31) -> 0 | S32: =SUM(S22:S31) -> 0 | T32: =SUM(T22:T31) -> 0 | U32: =SUM(U22:U31) -> 0 | V32: =SUM(V22:V31) -> 0 | W32: =SUM(W22:W31) -> 0 | ... AA32: =SUM(AA22:AA31) -> 0
A33: TOTAL | D33: =((D22*B22)+(D23*B23)+(D24*B24)+(D25*B25)+(D26*B26)+(D27*B27)+(D28*B28)+(D29*B29)+(D30*B30)+(D31*B31)) -> 0 | F33: =((F22*B22)+(F23*B23)+(F24*B24)+(F25*B25)+(F26*B26)+(F27*B27)+(F28*B28)+(F29*B29)+(F30*B30)+(F31*B31)) -> 0 | G33: =((G22*B22)+(G23*B23)+(G24*B24)+(G25*B25)+(G26*B26)+(G27*B27)+(G28*B28)+(G29*B29)+(G30*B30)+(G31*B31)) -> 0 | J33: =((J22*B22)+(J23*B23)+(J24*B24)+(J25*B25)+(J26*B26)+(J27*B27)+(J28*B28)+(J29*B29)+(J30*B30)+(J31*B31)) -> 0 | K33: =((K22*B22)+(K23*B23)+(K24*B24)+(K25*B25)+(K26*B26)+(K27*B27)+(K28*B28)+(K29*B29)+(B30*K30)+(K31*B31)) -> 0 | N33: RN | O33: =J32/G32 -> #DIV/0!
B35: PROYECTO GENERAL
B36: Has | C36: Rinde | D36: Arrend. | E36: Precio | F36: Ingreso Bruto | G36: Costo | I36: Rinde Indif | J36: Resultado | K36: Inversión Real | N36: Retorno | O36: Retorno
C37: Tons / Ha | D37: U$ / Ha | E37: U$ / Ton | F37: U$ / Ha | G37: U$ / Ha | I37: Tons / Ha | J37: u$ / Ton | K37: U$ / Ton | N37: Real | O37: Nominal
A38: Trigo / Soja 2da | B38: =B22+B6 -> 0 | C38: =((B6*C6)+(B22*C22))/B38 -> #DIV/0! | D38: =((D6*B6)+(D22*B22))/B38 -> #DIV/0! | E38: =E6 -> 230 | F38: =((F6*B6)+(F22*B22))/B38 -> #DIV/0! | G38: =((G6*B6)+(G22*B22))/B38 -> #DIV/0! | I38: =((I6*B6)+(I22*B22))/B38 -> #DIV/0! | J38: =((J6*B6)+(J22*B22))/B38 -> #DIV/0! | K38: =((K6*B6)+(K22*B22))/B38 -> #DIV/0! | N38: =(J38+J39)/(K38+K39) -> #DIV/0! | O38: =(J38+J39)/(G38+G39) -> #DIV/0! | P38: =G38*B38 -> #DIV/0! | Q38: ='[1]Trigo SP'!E62 -> 11.034707 | R38: =Q38*B38 -> 0 | S38: =R38*[1]Cotizaciones!$B$5 -> 0 | T38: Trigo / Soja 2da | AA38: =(J38+G38)*B38 -> #DIV/0!
B39: =B23+B7 -> 0 | C39: =((B7*C7)+(B23*C23))/B39 -> #DIV/0! | D39: =((D7*B7)+(D23*B23))/B39 -> #DIV/0! | E39: =E7 -> 355 | F39: =((F7*B7)+(F23*B23))/B39 -> #DIV/0! | G39: =((G7*B7)+(G23*B23))/B39 -> #DIV/0! | I39: =((I7*B7)+(I23*B23))/B39 -> #DIV/0! | J39: =((J7*B7)+(J23*B23))/B39 -> #DIV/0! | K39: =((K7*B7)+(K23*B23))/B39 -> #DIV/0! | P39: =G39*B39 -> #DIV/0! | Q39: ='[1]Soja 2da. C'!E60 -> #REF! | R39: =Q39*B39 -> #REF! | S39: =R39*[1]Cotizaciones!$B$5 -> #REF! | AA39: =(J39+G39)*B39 -> #DIV/0!
A40: Cebada / Soja 2da | B40: =B24+B8 -> 0 | C40: =((B8*C8)+(B24*C24))/B40 -> #DIV/0! | D40: =((D8*B8)+(D24*B24))/B40 -> #DIV/0! | E40: =E8 -> 245 | F40: =((F8*B8)+(F24*B24))/B40 -> #DIV/0! | G40: =((G8*B8)+(G24*B24))/B40 -> #DIV/0! | I40: =((I8*B8)+(I24*B24))/B40 -> #DIV/0! | J40: =((J8*B8)+(J24*B24))/B40 -> #DIV/0! | K40: =((K8*B8)+(K24*B24))/B40 -> #DIV/0! | N40: =(J40+J41)/(K40+K41) -> #DIV/0! | O40: =(J40+J41)/(G40+G41) -> #DIV/0! | P40: =G40*B40 -> #DIV/0! | Q40: ='[1]Cebada SP'!E62 -> 131.13585 | R40: =Q40*B40 -> 0 | S40: =R40*[1]Cotizaciones!$B$5 -> 0 | T40: Cebada / Soja 2da | AA40: =(J40+G40)*B40 -> #DIV/0!
B41: =B25+B9 -> 0 | C41: =((B9*C9)+(B25*C25))/B41 -> #DIV/0! | D41: =((D9*B9)+(D25*B25))/B41 -> #DIV/0! | E41: =E9 -> 355 | F41: =((F9*B9)+(F25*B25))/B41 -> #DIV/0! | G41: =((G9*B9)+(G25*B25))/B41 -> #DIV/0! | I41: =((I9*B9)+(I25*B25))/B41 -> #DIV/0! | J41: =((J9*B9)+(J25*B25))/B41 -> #DIV/0! | K41: =((K9*B9)+(K25*B25))/B41 -> #DIV/0! | P41: =G41*B41 -> #DIV/0! | Q41: ='[1]Soja 2da. C'!E60 -> #REF! | R41: =Q41*B41 -> #REF! | S41: =R41*[1]Cotizaciones!$B$5 -> #REF! | AA41: =(J41+G41)*B41 -> #DIV/0!
A42: Colza / Soja 2da | B42: =B26+B10 -> 0 | C42: =((B10*C10)+(B26*C26))/B42 -> #DIV/0! | D42: =((D10*B10)+(D26*B26))/B42 -> #DIV/0! | E42: =E10 -> 200 | F42: =((F10*B10)+(F26*B26))/B42 -> #DIV/0! | G42: =((G10*B10)+(G26*B26))/B42 -> #DIV/0! | I42: =((I10*B10)+(I26*B26))/B42 -> #DIV/0! | J42: =((J10*B10)+(J26*B26))/B42 -> #DIV/0! | K42: =((K10*B10)+(K26*B26))/B42 -> #DIV/0! | N42: =(J42+J43)/(K42+K43) -> #DIV/0! | O42: =(J42+J43)/(G42+G43) -> #DIV/0! | P42: =G42*B42 -> #DIV/0! | R42: =Q42*B42 -> 0 | S42: =R42*[1]Cotizaciones!$B$5 -> 0 | T42: Colza / Soja 2da | AA42: =(J42+G42)*B42 -> #DIV/0!
B43: =B27+B11 -> 0 | C43: =((B11*C11)+(B27*C27))/B43 -> #DIV/0! | D43: =((D11*B11)+(D27*B27))/B43 -> #DIV/0! | E43: =E11 -> 450 | F43: =((F11*B11)+(F27*B27))/B43 -> #DIV/0! | G43: =((G11*B11)+(G27*B27))/B43 -> #DIV/0! | I43: =((I11*B11)+(I27*B27))/B43 -> #DIV/0! | J43: =((J11*B11)+(J27*B27))/B43 -> #DIV/0! | K43: =((K11*B11)+(K27*B27))/B43 -> #DIV/0! | P43: =G43*B43 -> #DIV/0! | Q43: ='[1]Soja 2da. C'!E60 -> #REF! | R43: =Q43*B43 -> #REF! | S43: =R43*[1]Cotizaciones!$B$5 -> #REF! | AA43: =(J43+G43)*B43 -> #DIV/0!
A44: Maíz | B44: =B28+B12 -> 0 | C44: =((B12*C12)+(B28*C28))/B44 -> #DIV/0! | D44: =((D12*B12)+(D28*B28))/B44 -> #DIV/0! | E44: =E12 -> 200 | F44: =((F12*B12)+(F28*B28))/B44 -> #DIV/0! | G44: =((G12*B12)+(G28*B28))/B44 -> #DIV/0! | I44: =((I12*B12)+(I28*B28))/B44 -> #DIV/0! | J44: =((J12*B12)+(J28*B28))/B44 -> #DIV/0! | K44: =((K12*B12)+(K28*B28))/B44 -> #DIV/0! | N44: =J44/K44 -> #DIV/0! | O44: =J44/G44 -> #DIV/0! | P44: =G44*B44 -> #DIV/0! | R44: =Q44*B44 -> 0 | S44: =R44*[1]Cotizaciones!$B$5 -> 0 | T44: Maíz | AA44: =(J44+G44)*B44 -> #DIV/0!
A45: Girasol | B45: =B29+B14 -> 0 | C45: =((B14*C14)+(B29*C29))/B45 -> #DIV/0! | D45: =((D14*B14)+(D29*B29))/B45 -> #DIV/0! | E45: =E14 -> 373.75917 | F45: =((F14*B14)+(F29*B29))/B45 -> #DIV/0! | G45: =((G14*B14)+(G29*B29))/B45 -> #DIV/0! | I45: =((I14*B14)+(I29*B29))/B45 -> #DIV/0! | J45: =((J14*B14)+(J29*B29))/B45 -> #DIV/0! | K45: =((K14*B14)+(K29*B29))/B45 -> #DIV/0! | N45: =J45/K45 -> #DIV/0! | O45: =J45/G45 -> #DIV/0! | P45: =G45*B45 -> #DIV/0! | R45: =Q45*B45 -> 0 | AA45: =(J45+G45)*B45 -> #DIV/0!
A46: Girasol Oleico | B46: =B30+B13 -> 0 | C46: =((B13*C13)+(B30*C30))/B46 -> #DIV/0! | D46: =((D13*B13)+(D30*B30))/B46 -> #DIV/0! | E46: =E30 -> 380.21917 | F46: =E46*C46 -> #DIV/0! | G46: =((G13*B13)+(G30*B30))/B46 -> #DIV/0! | I46: =((I13*B13)+(I30*B30))/B46 -> #DIV/0! | J46: =((J13*B13)+(B30*J30))/B46 -> #DIV/0! | K46: =((K13*B13)+(K30*B30))/B46 -> #DIV/0! | N46: =J46/K46 -> #DIV/0! | O46: =J46/G46 -> #DIV/0! | P46: =G46*B46 -> #DIV/0! | R46: =Q46*B46 -> 0 | S46: =R46*[1]Cotizaciones!$B$5 -> 0 | T46: Girasol | AA46: =(J46+G46)*B46 -> #DIV/0!
A47: Soja | B47: =B31+B15 -> 0 | C47: =((B15*C15)+(B31*C31))/B47 -> #DIV/0! | D47: =((D15*B15)+(D31*B31))/B47 -> #DIV/0! | E47: =E15 -> 355 | F47: =((F15*B15)+(F31*B31))/B47 -> #DIV/0! | G47: =((G15*B15)+(G31*B31))/B47 -> #DIV/0! | I47: =((I14*B14)+(I30*B30))/B47 -> #DIV/0! | J47: =((J15*B15)+(J31*B31))/B47 -> #DIV/0! | K47: =((K15*B15)+(K31*B31))/B47 -> #DIV/0! | N47: =J47/K47 -> #DIV/0! | O47: =J47/G47 -> #DIV/0! | P47: =G47*B47 -> #DIV/0! | R47: =Q47*B47 -> 0 | S47: =R47*[1]Cotizaciones!$B$5 -> 0 | T47: Soja | AA47: =(J47+G47)*B47 -> #DIV/0!
B48: =SUM(B38:B47)-B39-B41-B43 -> 0 | D48: =((D38*B38)+(D39*B39)+(D40*B40)+(D41*B41)+(D42*B42)+(D43*B43)+(D44*B44)+(D45*B45)+(B46*D46)+(D47*B47))/B48 -> #DIV/0! | E48: =((E6*B6)+(E7*B7)+(E8*B8)+(E9*B9)+(E10*B10)+(E11*B11)+(E12*B12)+(E13*B13)+(E14*B14)+(E15*B15))/(B16+B7+B9+B11) -> #DIV/0! | F48: =((F38*B38)+(F39*B39)+(F40*B40)+(F41*B41)+(F42*B42)+(F43*B43)+(F44*B44)+(F45*B45)+(B46*F46)+(F47*B47))/(B48+B39+B41+B43) -> #DIV/0! | G48: =((B38*G38)+(G39*B39)+(B40*G40)+(B41*G41)+(G42*B42)+(B43*G43)+(G44*B44)+(B45*G45)+(G46*B46)+(B47*G47))/(B48+B41+B43+B39) -> #DIV/0! | J48: =((J38*B38)+(J39*B39)+(J40*B40)+(J41*B41)+(J42*B42)+(J43*B43)+(J44*B44)+(J45*B45)+(B46*J46)+(J47*B47))/(B48+B39+B41+B43) -> #DIV/0! | K48: =((K38*B38)+(K39*B39)+(K40*B40)+(K41*B41)+(K42*B42)+(K43*B43)+(K44*B44)+(K45*B45)+(K46*B46)+(K47*B47))/(B48+B39+B41+B43) -> #DIV/0! | N48: RR | O48: =J48/K48 -> #DIV/0! | P48: =SUM(P38:P47) -> #DIV/0! | Q48: =SUM(Q38:Q47) -> #REF! | R48: =SUM(R38:R47) -> #REF! | S48: =SUM(S38:S47) -> #REF! | T48: =SUM(T38:T47) -> 0 | U48: =SUM(U38:U47) -> 0 | V48: =SUM(V38:V47) -> 0 | W48: =SUM(W38:W47) -> 0 | ... AA48: =SUM(AA38:AA47) -> #DIV/0!
D49: =B48*D48 -> #DIV/0! | F49: =F48*(B48+B39+B41+B43) -> #DIV/0! | G49: =G48*(B48+B43+B41+B39) -> #DIV/0! | J49: =J48*(B48+B43+B41+B39) -> #DIV/0! | K49: =+K48*(B48+B43+B41+B39) -> #DIV/0! | N49: RN | O49: =J48/G48 -> #DIV/0!
A56: Arrendamiento en qq | B56: =+(B57/10)*12 -> 426 | D56: =+D17/G17 -> #DIV/0!
A57: Matba | B57: =+Cotizaciones!B14 -> 355 | C57: =+B56 -> 426 | E57: =190/210 -> 0.9047619 | G57: Mayo | I57: Diciembre | J57: Mayo | K57: Total
A58: 80 % primer cultivo | C58: =C57*0.8 -> 340.8 | G58: =+I58 -> 0 | I58: =+J58 -> 0 | J58: =+K58/3 -> 0 | K58: =+B16*B56 -> 0
A59: 20 % segundo cutivo | C59: =C57-C58 -> 85.2
A60: Rotacion | B60: has | C60: % | D60: cultivos | E60: has | F60: %
A61: Fina | B61: =+B8 -> 0 | C61: =+B61/B16 -> #DIV/0! | D61: Cebda | E61: =+B8 -> 0 | F61: =+E61/B16 -> #DIV/0!
A62: Gruesa | B62: =+B12+B13 -> 0 | C62: =+B62/B16 -> #DIV/0! | D62: Maiz | E62: =+B12 -> 0 | F62: =+E62/B16 -> #DIV/0! | M62: Alea | N62: Socio | O62: Total/ha
D63: Girasol | E63: =+B13 -> 0 | F63: =+E63/B16 -> #DIV/0! | L63: Labores | N63: =+'Trigo SP'!L63 -> 0 | O63: =+M63+N63 -> 0
L64: Semilla | M64: =+'Trigo SP'!J64 -> 0 | N64: =+'Soja 2da. T'!J73+'Maiz SP'!K78+'Girasol O SP'!K81 -> 0 | O64: =+M64+N64 -> 0
L65: Arrendamiento | M65: =+'Trigo SP'!J65+'Soja 2da. T'!H74+'Maiz SP'!I79+'Girasol O SP'!I82 -> 0 | O65: =+M65+N65 -> 0
L66: Gerenciamiento | M66: =+'Trigo SP'!J66+'Soja 2da. T'!H75+'Maiz SP'!I80+'Girasol O SP'!I83 -> 0 | O66: =+M66+N66 -> 0
L67: Fertilizantes | M67: =+'Trigo SP'!J67+'Maiz SP'!I81+'Girasol O SP'!I84 -> 0 | O67: =+M67+N67 -> 0
L68: Agroquímicos | N68: =+'Trigo SP'!L68+'Soja 2da. T'!J77+'Maiz SP'!K82+'Girasol O SP'!K85 -> 0 | O68: =+M68+N68 -> 0
L69: Total | M69: =SUM(M63:M68) -> 0 | N69: =SUM(N63:N68) -> 0 | O69: =+M69+N69 -> 0
M70: =+M69/O69 -> #DIV/0! | N70: =+N69/O69 -> #DIV/0!

Sheet CASH FLOW
A1: PROYECCIÓN ALEA SIEMBRA: CASH FLOW SIEMBRAS PROPIAS
B3: 42856 | C3: 42887 | D3: 42917 | E3: 42948 | F3: 42979 | G3: 43009 | H3: 43040 | I3: 43070 | J3: 43101 | K3: 43132 | L3: 43160 | M3: 43191 | N3: 43221 | O3: 43252 | P3: TOTAL Con IVA
A4: TOTAL MENSUAL | B4: =+B36-B38+B90-B92+B118-B120+B132-B134 -> 0 | C4: =+C36-C38+C90-C92+C118-C120+C132-C134 -> 0 | D4: =+D36-D38+D90-D92+D118-D120+D132-D134 -> 0 | E4: =+E36-E38+E90-E92+E118-E120+E132-E134 -> 0 | F4: =+F36-F38+F90-F92+F118-F120+F132-F134 -> 0 | G4: =+G36-G38+G90-G92+G118-G120+G132-G134 -> 0 | H4: =+H36-H38+H90-H92+H118-H120+H132-H134 -> 0 | I4: =+I36-I38+I90-I92+I118-I120+I132-I134 -> 0 | J4: =+J36-J38+J90-J92+J118-J120+J132-J134+J50-J52 -> 0 | K4: =+K36-K38+K90-K92+K118-K120+K132-K134+K50-K52 -> 0 | L4: =+L36-L38+L90-L92+L118-L120+L132-L134+L50-L52 -> 0 | M4: =+M36-M38+M90-M92+M118-M120+M132-M134+M50-M52 -> 0 | N4: =+N36-N38+N90-N92+N118-N120+N132-N134+N50-N52 -> 0 | O4: =+O36-O38+O90-O92+O118-O120+O132-O134+O50-O52 -> 0 | P4: =SUM(B4:O4) -> 0 | Q4: c/iva
A5: TOTAL ACUMULADO | B5: =B4 -> 0 | C5: =B5+C4 -> 0 | D5: =C5+D4 -> 0 | E5: =D5+E4 -> 0 | F5: =E5+F4 -> 0 | G5: =F5+G4 -> 0 | H5: =G5+H4 -> 0 | I5: =H5+I4 -> 0 | J5: =I5+J4 -> 0 | ... O5: =N5+O4 -> 0
A7: TRIGO | B7: =B9-B11 -> 0 | C7: =C9-C11 -> 0 | D7: =D9-D11 -> -1950.165 | E7: =E9-E11 -> -1950.165 | F7: =F9-F11 -> -1950.165 | G7: =G9-G11 -> -1950.165 | H7: =H9-H11 -> -1950.165 | I7: =I9-I11 -> -1950.165 | ... O7: =O9-O11 -> 0 | P7: =SUM(B7:O7) -> -19501.65
B8: =B7 -> 0 | C8: =B8+C7 -> 0 | D8: =C8+D7 -> -1950.165 | E8: =D8+E7 -> -3900.33 | F8: =E8+F7 -> -5850.495 | G8: =F8+G7 -> -7800.66 | H8: =G8+H7 -> -9750.825 | I8: =H8+I7 -> -11700.99 | J8: =I8+J7 -> -13651.155 | ... O8: =N8+O7 -> -19501.65
A9: INGRESOS | B9: =B10 -> 0 | C9: =C10 -> 0 | D9: =D10 -> 0 | E9: =E10 -> 0 | F9: =F10 -> 0 | G9: =G10 -> 0 | H9: =H10 -> 0 | I9: =I10 -> 0 | ... O9: =O10 -> 0 | P9: =SUM(B9:O9) -> 0
A10: Ventas | J10: =('Trigo SP'!B79*'Trigo SP'!B3)*0.52 -> 0 | O10: =+('Trigo SP'!B79*'Trigo SP'!B3)*0.48 -> 0 | P10: =SUM(B10:O10) -> 0
A11: EGRESOS | B11: =SUM(B12:B19) -> 0 | C11: =SUM(C12:C19) -> 0 | D11: =SUM(D12:D19) -> 1950.165 | E11: =SUM(E12:E19) -> 1950.165 | F11: =SUM(F12:F19) -> 1950.165 | G11: =SUM(G12:G19) -> 1950.165 | H11: =SUM(H12:H19) -> 1950.165 | I11: =SUM(I12:I19) -> 1950.165 | ... O11: =SUM(O12:O19) -> 0 | P11: =SUM(B11:O11) -> 19501.65
A12: Arrendamiento | B12: =+'[2]Alquileres por campo'!$D$56+'[2]Alquileres por campo'!$E$56 -> 0 | C12: =+'[2]Alquileres por campo'!F56 -> 0 | D12: =+'[2]Alquileres por campo'!G56 -> 1950.165 | E12: =+'[2]Alquileres por campo'!H56 -> 1950.165 | F12: =+'[2]Alquileres por campo'!I56 -> 1950.165 | G12: =+'[2]Alquileres por campo'!J56 -> 1950.165 | H12: =+'[2]Alquileres por campo'!K56 -> 1950.165 | I12: =+'[2]Alquileres por campo'!L56 -> 1950.165 | J12: =+'[2]Alquileres por campo'!M56 -> 1950.165 | ... O12: =+'[2]Alquileres por campo'!R56 -> 0 | P12: =SUM(B12:O12) -> 19501.65
A13: Labores | B13: =((SUMIF('Trigo SP'!J8:J19,"MAYO",'Trigo SP'!E8:E19)*'Trigo SP'!B3)+(SUMIF('Trigo SS'!J8:J19,"MAYO",'Trigo SS'!E8:E19)*'Trigo SS'!B3))/9*'Tipo de Cambio Proyectado'!B2 -> 0 | C13: =((SUMIF('Trigo SP'!J8:J19,"JUNIO",'Trigo SP'!E8:E19)*'Trigo SP'!B3)+(SUMIF('Trigo SS'!J8:J19,"JUNIO",'Trigo SS'!E8:E19)*'Trigo SS'!B3))/9*'Tipo de Cambio Proyectado'!B3 -> 0 | D13: =(SUMIF('Trigo SP'!J8:J19,"JULIO",'Trigo SP'!E8:E19)*'Trigo SP'!B3)+(SUMIF('Trigo SS'!J8:J19,"JULIO",'Trigo SS'!E8:E19)*'Trigo SS'!B3)+(SUMIF('Trigo SS'!J8:J19,"JULIO/SEPTIEMBRE",'Trigo SS'!E8:E19)*'Trigo SS'!B3*0.5)+(SUMIF('Trigo SP'!J8:J19,"JULIO/SEPTIEMBRE",'Trigo SP'!E8:E19)*'Trigo SP'!B3*0.5) -> 0 | E13: =(SUMIF('Trigo SP'!J8:J19,"AGOSTO",'Trigo SP'!E8:E19)*'Trigo SP'!B3)+(SUMIF('Trigo SS'!J8:J19,"AGOSTO",'Trigo SS'!E8:E19)*'Trigo SS'!B3) -> 0 | F13: =(SUMIF('Trigo SP'!K8:K19,"SEPTIEMBRE",'Trigo SP'!F8:F19)*'Trigo SP'!B3)+(SUMIF('Trigo SS'!K8:K19,"SEPTIEMBRE",'Trigo SS'!F8:F19)*'Trigo SS'!B3)+(SUMIF('Trigo SS'!J8:J19,"JULIO/SEPTIEMBRE",'Trigo SS'!E8:E19)*'Trigo SS'!B3*0.5)+(SUMIF('Trigo SP'!J8:J19,"JULIO/SEPTIEMBRE",'Trigo SP'!E8:E19)*'Trigo SP'!B3*0.5) -> 0 | G13: =(SUMIF('Trigo SP'!K8:K19,"OCTUBRE",'Trigo SP'!F8:F19)*'Trigo SP'!B3)+(SUMIF('Trigo SS'!K8:K19,"OCTUBRE",'Trigo SS'!F8:F19)*'Trigo SS'!B3) -> 0 | H13: =(SUMIF('Trigo SP'!K8:K19,"NOVIEMBRE",'Trigo SP'!F8:F19)*'Trigo SP'!B3)+(SUMIF('Trigo SS'!K8:K19,"NOVIEMBRE",'Trigo SS'!F8:F19)*'Trigo SS'!B3) -> 0 | I13: =(SUMIF('Trigo SP'!J8:J18,"DICIEMBRE",'Trigo SP'!E8:E19)*'Trigo SP'!B3)+(SUMIF('Trigo SS'!K8:K19,"DICIEMBRE",'Trigo SS'!F8:F19)*'Trigo SS'!C3) -> 0 | J13: =(SUMIF('Trigo SP'!K8:K19,"ENERO",'Trigo SP'!F8:F19)*'Trigo SP'!C3)+(SUMIF('Trigo SS'!K8:K19,"ENERO",'Trigo SS'!F8:F19)*'Trigo SS'!C3) -> 0 | K13: =(SUMIF('Trigo SP'!K8:K19,"FEBRERO",'Trigo SP'!F8:F19)*'Trigo SP'!C3)+(SUMIF('Trigo SS'!K8:K19,"FEBRERO",'Trigo SS'!F8:F19)*'Trigo SS'!C3) -> 0 | L13: =(SUMIF('Trigo SP'!K8:K19,"MARZO",'Trigo SP'!F8:F19)*'Trigo SP'!C3)+(SUMIF('Trigo SS'!K8:K19,"MARZO",'Trigo SS'!F8:F19)*'Trigo SS'!C3) -> 0 | P13: =SUM(B13:O13) -> 0
A14: Insumos | B14: =(SUMIF('Trigo SP'!J38:J49,"MAYO",'Trigo SP'!E38:E49)*'Trigo SP'!B3)+(SUMIF('Trigo SS'!J37:J45,"MAYO",'Trigo SS'!E37:E45)*'Trigo SS'!B3) -> 0 | C14: =(SUMIF('Trigo SP'!J38:J49,"JUNIO",'Trigo SP'!E38:E49)*'Trigo SP'!B3)+(SUMIF('Trigo SS'!J37:J45,"JUNIO",'Trigo SS'!E37:E45)*'Trigo SS'!B3) -> 0 | D14: =(SUMIF('Trigo SP'!J38:J49,"JULIO",'Trigo SP'!E38:E49)*'Trigo SP'!B3)+(SUMIF('Trigo SS'!J37:J45,"JULIO",'Trigo SS'!E37:E45)*'Trigo SS'!B3) -> 0 | E14: =(SUMIF('Trigo SP'!J38:J49,"AGOSTO",'Trigo SP'!E38:E49)*'Trigo SP'!B3)+(SUMIF('Trigo SS'!J37:J45,"AGOSTO",'Trigo SS'!E37:E45)*'Trigo SS'!B3) -> 0 | F14: =(SUMIF('Trigo SP'!J38:J49,"SEPTIEMBRE",'Trigo SP'!E38:E49)*'Trigo SP'!B3)+(SUMIF('Trigo SS'!J37:J45,"SEPTIEMBRE",'Trigo SS'!E37:E45)*'Trigo SS'!B3) -> 0 | G14: =(SUMIF('Trigo SP'!J38:J49,"OCTUBRE",'Trigo SP'!E38:E49)*'Trigo SP'!B3)+(SUMIF('Trigo SS'!J37:J45,"OCTUBRE",'Trigo SS'!E37:E45)*'Trigo SS'!B3) -> 0 | H14: =(SUMIF('Trigo SP'!J38:J49,"NOVIEMBRE",'Trigo SP'!E38:E49)*'Trigo SP'!B3)+(SUMIF('Trigo SS'!J37:J45,"NOVIEMBRE",'Trigo SS'!E37:E45)*'Trigo SS'!B3) -> 0 | I14: =(SUMIF('Trigo SP'!J38:J49,"DICIEMBRE",'Trigo SP'!E38:E49)*'Trigo SP'!B3)+(SUMIF('Trigo SS'!J37:J45,"DICIEMBRE",'Trigo SS'!E37:E45)*'Trigo SS'!B3) -> 0 | J14: =(SUMIF('Trigo SP'!J38:J49,"ENERO",'Trigo SP'!E38:E49)*'Trigo SP'!B3)+(SUMIF('Trigo SS'!J37:J45,"ENERO",'Trigo SS'!E37:E45)*'Trigo SS'!B3) -> 0 | K14: =(SUMIF('Trigo SP'!J38:J49,"FEBRERO",'Trigo SP'!E38:E49)*'Trigo SP'!B3)+(SUMIF('Trigo SS'!J37:J45,"FEBRERO",'Trigo SS'!E37:E45)*'Trigo SS'!B3) -> 0 | L14: =(SUMIF('Trigo SP'!J38:J49,"MARZO",'Trigo SP'!E38:E49)*'Trigo SP'!B3)+(SUMIF('Trigo SS'!J37:J45,"MARZO",'Trigo SS'!E37:E45)*'Trigo SS'!B3) -> 0 | P14: =SUM(B14:O14) -> 0
A15: Fertilizante | B15: =('Trigo SP'!B3*SUMIF('Trigo SP'!J33:J34,"MAYO",'Trigo SP'!E33:E34))+('Trigo SS'!B3*SUMIF('Trigo SS'!J33:J34,"MAYO",'Trigo SS'!E33:E34)) -> 0 | C15: =('Trigo SP'!B3*SUMIF('Trigo SP'!J33:J34,"JUNIO",'Trigo SP'!E33:E34))+('Trigo SS'!B3*SUMIF('Trigo SS'!J33:J34,"JUNIO",'Trigo SS'!E33:E34)) -> 0 | D15: =('Trigo SP'!B3*SUMIF('Trigo SP'!J33:J34,"JULIO",'Trigo SP'!E33:E34))+('Trigo SS'!B3*SUMIF('Trigo SS'!J33:J34,"JULIO",'Trigo SS'!E33:E34)) -> 0 | I15: =+'Trigo SP'!I33 -> 0 | J15: =+'Trigo SP'!I34 -> 0 | P15: =SUM(B15:O15) -> 0
A16: Semilla | J16: ='Trigo SP'!B3*'Trigo SP'!E22+'Trigo SS'!B3*'Trigo SS'!E23 -> 0 | P16: =SUM(B16:O16) -> 0
A17: Cosecha// Comerc | J17: =('Trigo SP'!B3*('Trigo SP'!E53+'Trigo SP'!E70))+('Trigo SS'!B3*('Trigo SS'!D48+'Trigo SS'!E59)) -> 0 | P17: =SUM(B17:O17) -> 0
A18: Gerenciamiento | B18: =(('Trigo SP'!D29*'Trigo SP'!B3)+('Trigo SS'!D29*'Trigo SS'!B3))*0.1 -> 0 | C18: =(('Trigo SP'!D29*'Trigo SP'!B3)+('Trigo SS'!D29*'Trigo SS'!B3))*0.1 -> 0 | D18: =(('Trigo SP'!D29*'Trigo SP'!B3)+('Trigo SS'!D29*'Trigo SS'!B3))*0.1 -> 0 | E18: =(('Trigo SP'!D29*'Trigo SP'!B3)+('Trigo SS'!D29*'Trigo SS'!B3))*0.1 -> 0 | F18: =(('Trigo SP'!D29*'Trigo SP'!B3)+('Trigo SS'!D29*'Trigo SS'!B3))*0.1 -> 0 | G18: =(('Trigo SP'!D29*'Trigo SP'!B3)+('Trigo SS'!D29*'Trigo SS'!B3))*0.1 -> 0 | H18: =(('Trigo SP'!D29*'Trigo SP'!B3)+('Trigo SS'!D29*'Trigo SS'!B3))*0.1 -> 0 | I18: =(('Trigo SP'!D29*'Trigo SP'!B3)+('Trigo SS'!D29*'Trigo SS'!B3))*0.1 -> 0 | J18: =(('Trigo SP'!D29*'Trigo SP'!B3)+('Trigo SS'!D29*'Trigo SS'!B3))*0.1 -> 0 | K18: =(('Trigo SP'!D29*'Trigo SP'!B3)+('Trigo SS'!D29*'Trigo SS'!B3))*0.1 -> 0 | P18: =SUM(B18:O18) -> 0
A19: Seguro | K19: =('Trigo SP'!B3*'Trigo SP'!D54)+('Trigo SS'!D61*'Trigo SS'!B3) -> 0 | P19: =SUM(B19:O19) -> 0
A21: SOJA 2DA TRIGO | B21: =B23-B25 -> 0 | C21: =C23-C25 -> 0 | D21: =D23-D25 -> 0 | E21: =E23-E25 -> 0 | F21: =F23-F25 -> 0 | G21: =G23-G25 -> 0 | H21: =H23-H25 -> 0 | I21: =I23-I25 -> 0 | ... K21: =K23-K25 -> 0 | L21: 0 | M21: =M23-M25 -> 0 | N21: =N23-N25 -> 0 | O21: =O23-O25 -> 0 | P21: =SUM(B21:O21) -> 0
B22: =B21 -> 0 | C22: =B22+C21 -> 0 | D22: =C22+D21 -> 0 | E22: =D22+E21 -> 0 | F22: =E22+F21 -> 0 | G22: =F22+G21 -> 0 | H22: =G22+H21 -> 0 | I22: =H22+I21 -> 0 | J22: =I22+J21 -> 0 | K22: =J22+K21 -> 0 | L22: 0 | M22: 0 | N22: =M22+N21 -> 0 | O22: =N22+O21 -> 0
A23: INGRESOS | B23: =B24 -> 0 | C23: =C24 -> 0 | D23: =D24 -> 0 | E23: =E24 -> 0 | F23: =F24 -> 0 | G23: =G24 -> 0 | H23: =H24 -> 0 | I23: =I24 -> 0 | ... O23: =O24 -> 0 | P23: =SUM(B23:O23) -> 0
A24: Ventas | O24: ='Soja 2da. T'!B76*'Soja 2da. T'!B3 -> 0 | P24: =SUM(B24:O24) -> 0
A25: EGRESOS | B25: =SUM(B26:B32) -> 0 | C25: =SUM(C26:C32) -> 0 | D25: =SUM(D26:D32) -> 0 | E25: =SUM(E26:E32) -> 0 | F25: =SUM(F26:F32) -> 0 | G25: =SUM(G26:G32) -> 0 | H25: =SUM(H26:H32) -> 0 | I25: =SUM(I26:I32) -> 0 | ... O25: =SUM(O26:O32) -> 0 | P25: =SUM(B25:O25) -> 0
A26: Arrendamiento | P26: =SUM(B26:O26) -> 0
A27: Labores | D27: =(SUMIF('Soja 2da. T'!J7:J17,"JULIO",'Soja 2da. T'!E7:E17))*'Soja 2da. T'!B3 -> 0 | E27: =(SUMIF('Soja 2da. T'!J7:J17,"AGOSTO",'Soja 2da. T'!E7:E17))*'Soja 2da. T'!B3 -> 0 | F27: =(SUMIF('Soja 2da. T'!J7:J17,"SEPTIEMBRE",'Soja 2da. T'!E7:E17))*'Soja 2da. T'!B3 -> 0 | G27: =(SUMIF('Soja 2da. T'!J7:J17,"OCTUBREL",'Soja 2da. T'!E7:E17))*'Soja 2da. T'!B3 -> 0 | H27: =(SUMIF('Soja 2da. T'!J7:J17,"NOVIEMBRE",'Soja 2da. T'!E7:E17))*'Soja 2da. T'!B3 -> 0 | I27: =(SUMIF('Soja 2da. T'!J7:J17,"DICIEMBRE",'Soja 2da. T'!E7:E17))*'Soja 2da. T'!B3 -> 0 | J27: =(SUMIF('Soja 2da. T'!J7:J17,"ENERO",'Soja 2da. T'!E7:E17))*'Soja 2da. T'!B3 -> 0 | K27: =(SUMIF('Soja 2da. T'!J7:J17,"FEBRERO",'Soja 2da. T'!E7:E17))*'Soja 2da. T'!B3 -> 0 | L27: =(SUMIF('Soja 2da. T'!J7:J17,"MARZO",'Soja 2da. T'!E7:E17))*'Soja 2da. T'!B3 -> 0 | M27: =(SUMIF('Soja 2da. T'!J7:J17,"ABRIL",'Soja 2da. T'!E7:E17))*'Soja 2da. T'!B3 -> 0 | N27: =(SUMIF('Soja 2da. T'!J7:J17,"MAYO",'Soja 2da. T'!E7:E17))*'Soja 2da. T'!B3 -> 0 | O27: =(SUMIF('Soja 2da. T'!J7:J17,"JUNIO",'Soja 2da. T'!E7:E17))*'Soja 2da. T'!B3 -> 0 | P27: =SUM(B27:O27) -> 0
A28: Insumos | D28: =(SUMIF('Soja 2da. T'!J35:J44,"JULIO",'Soja 2da. T'!E35:E44)*'Soja 2da. T'!B3) -> 0 | E28: =(SUMIF('Soja 2da. T'!J35:J44,"AGOSTO",'Soja 2da. T'!E35:E44)*'Soja 2da. T'!B3) -> 0 | F28: =(SUMIF('Soja 2da. T'!J35:J44,"SEPTIEMBRE",'Soja 2da. T'!E35:E44)*'Soja 2da. T'!B3) -> 0 | G28: =(SUMIF('Soja 2da. T'!J35:J44,"OCTUBRE",'Soja 2da. T'!E35:E44)*'Soja 2da. T'!B3) -> 0 | H28: =(SUMIF('Soja 2da. T'!J35:J44,"NOVIEMBRE",'Soja 2da. T'!E35:E44)*'Soja 2da. T'!B3) -> 0 | I28: =(SUMIF('Soja 2da. T'!J35:J44,"DICIEMBRE",'Soja 2da. T'!E35:E44)*'Soja 2da. T'!B3) -> 0 | J28: =(SUMIF('Soja 2da. T'!J35:J44,"ENERO",'Soja 2da. T'!E35:E44)*'Soja 2da. T'!B3)+('Soja 2da. T'!B3*SUMIF('Soja 2da. T'!J35:J44,"ENERO/MARZO",'Soja 2da. T'!E35:E44)*0.5) -> 0 | K28: =(SUMIF('Soja 2da. T'!J35:J44,"FEBRERO",'Soja 2da. T'!E35:E44)*'Soja 2da. T'!B3) -> 0 | L28: =(SUMIF('Soja 2da. T'!J35:J44,"MARZO",'Soja 2da. T'!E35:E44)*'Soja 2da. T'!B3)+('Soja 2da. T'!B3*SUMIF('Soja 2da. T'!J35:J44,"ENERO/MARZO",'Soja 2da. T'!E35:E44)*0.5) -> 0 | M28: =(SUMIF('Soja 2da. T'!J35:J44,"ABRIL",'Soja 2da. T'!E35:E44)*'Soja 2da. T'!B3) -> 0 | N28: =(SUMIF('Soja 2da. T'!J35:J44,"MAYO",'Soja 2da. T'!E35:E44)*'Soja 2da. T'!B3) -> 0 | O28: =(SUMIF('Soja 2da. T'!J35:J44,"JUNIO",'Soja 2da. T'!E35:E44)*'Soja 2da. T'!B3) -> 0 | P28: =SUM(B28:O28) -> 0
A29: Semilla | J29: ='Soja 2da. T'!B3*'Soja 2da. T'!E21 -> 0 | P29: =SUM(B29:O29) -> 0
A30: Cosecha// Comerc | O30: ='Soja 2da. T'!B3*('Soja 2da. T'!E48+'Soja 2da. T'!E67) -> 0 | P30: =SUM(B30:O30) -> 0
A31: Gerenciamiento | F31: =('Soja 2da. T'!D27*'Soja 2da. T'!B3)*0.1 -> 0 | G31: =('Soja 2da. T'!D27*'Soja 2da. T'!B3)*0.1 -> 0 | H31: =('Soja 2da. T'!D27*'Soja 2da. T'!B3)*0.1 -> 0 | I31: =('Soja 2da. T'!D27*'Soja 2da. T'!B3)*0.1 -> 0 | J31: =('Soja 2da. T'!D27*'Soja 2da. T'!B3)*0.1 -> 0 | K31: =('Soja 2da. T'!D27*'Soja 2da. T'!B3)*0.1 -> 0 | L31: =('Soja 2da. T'!D27*'Soja 2da. T'!B3)*0.1 -> 0 | M31: =('Soja 2da. T'!D27*'Soja 2da. T'!B3)*0.1 -> 0 | N31: =('Soja 2da. T'!D27*'Soja 2da. T'!B3)*0.1 -> 0 | O31: =('Soja 2da. T'!D27*'Soja 2da. T'!B3)*0.1 -> 0 | P31: =SUM(B31:O31) -> 0
A32: Seguro | O32: ='Soja 2da. T'!E51*'Soja 2da. T'!B3 -> 0 | P32: =SUM(B32:O32) -> 0
A34: CEBADA | B34: =B36-B38 -> 0 | C34: =C36-C38 -> 0 | D34: =D36-D38 -> 0 | E34: =E36-E38 -> 0 | F34: =F36-F38 -> 0 | G34: =G36-G38 -> 0 | H34: =H36-H38 -> 0 | I34: =I36-I38 -> 0 | ... O34: =O36-O38 -> 0 | P34: =SUM(B34:O34) -> 0
B35: =B34 -> 0 | C35: =B35+C34 -> 0 | D35: =C35+D34 -> 0 | E35: =D35+E34 -> 0 | F35: =E35+F34 -> 0 | G35: =F35+G34 -> 0 | H35: =G35+H34 -> 0 | I35: =H35+I34 -> 0 | J35: =I35+J34 -> 0 | ... O35: =N35+O34 -> 0
A36: INGRESOS | B36: =B37 -> 0 | C36: =C37 -> 0 | D36: =D37 -> 0 | E36: =E37 -> 0 | F36: =F37 -> 0 | G36: =G37 -> 0 | H36: =H37 -> 0 | I36: =I37 -> 0 | ... O36: =O37 -> 0 | P36: =SUM(B36:O36) -> 0
A37: Ventas | J37: =+('Cebada SP'!B84*'Cebada SP'!B3)*0.165 -> 0 | K37: =+('Cebada SP'!B3*'Cebada SP'!B84)*0.172 -> 0 | L37: =+('Cebada SP'!B84*'Cebada SP'!B3)*0.663 -> 0 | P37: =SUM(B37:O37) -> 0
A38: EGRESOS | B38: =SUM(B39:B46) -> 0 | C38: =SUM(C39:C46) -> 0 | D38: =SUM(D39:D46) -> 0 | E38: =SUM(E39:E46) -> 0 | F38: =SUM(F39:F46) -> 0 | G38: =SUM(G39:G46) -> 0 | H38: =SUM(H39:H46) -> 0 | I38: =SUM(I39:I46) -> 0 | ... O38: =SUM(O39:O46) -> 0 | P38: =SUM(B38:O38) -> 0
A39: Arrendamiento | B39: =+'[2]Alquileres por campo'!$D$58+'[2]Alquileres por campo'!$E$58 -> 0 | C39: =+'[2]Alquileres por campo'!F58 -> 0 | D39: =+'[2]Alquileres por campo'!G58 -> 0 | E39: =+'[2]Alquileres por campo'!H58 -> 0 | F39: =+'[2]Alquileres por campo'!I58 -> 0 | G39: =+'[2]Alquileres por campo'!J58 -> 0 | H39: =+'[2]Alquileres por campo'!K58 -> 0 | I39: =+'[2]Alquileres por campo'!L58 -> 0 | J39: =+'[2]Alquileres por campo'!M58 -> 0 | ... O39: =+'[2]Alquileres por campo'!R58 -> 0 | P39: =SUM(B39:O39) -> 0
A40: Labores | B40: =((SUMIF('Cebada SP'!J8:J20,"MAYO",'Cebada SP'!E8:E20)*'Cebada SP'!B3)+(SUMIF('Cebada SS '!J8:J19,"MAYO",'Cebada SS '!E8:E19)*'Cebada SS '!B3))/9*'Tipo de Cambio Proyectado'!B2 -> 0 | C40: =(SUMIF('Cebada SP'!J8:J20,"JUNIO",'Cebada SP'!E8:E20)*'Cebada SP'!B3)+(SUMIF('Cebada SS '!J8:J19,"JUNIO",'Cebada SS '!E8:E19)*'Cebada SS '!B3) -> 0 | D40: =((SUMIF('Cebada SP'!J8:J20,"JULIO",'Cebada SP'!E8:E20)*'Cebada SP'!B3)+(SUMIF('Cebada SS '!J8:J19,"JULIO",'Cebada SS '!E8:E19)*'Cebada SS '!B3))/9*'Tipo de Cambio Proyectado'!B4 -> 0 | E40: =((SUMIF('Cebada SP'!J8:J20,"AGOSTO",'Cebada SP'!E8:E20)*'Cebada SP'!B3)+(SUMIF('Cebada SS '!J8:J19,"AGOSTO",'Cebada SS '!E8:E19)*'Cebada SS '!B3))/9*'Tipo de Cambio Proyectado'!B5 -> 0 | F40: =(SUMIF('Cebada SP'!J8:J20,"SEPTIEMBRE",'Cebada SP'!E8:E20)*'Cebada SP'!B3)+(SUMIF('Cebada SS '!J8:J19,"SEPTIEMBRE",'Cebada SS '!E8:E19)*'Cebada SS '!B3) -> 0 | G40: =(SUMIF('Cebada SP'!J8:J20,"OCTUBRE",'Cebada SP'!E8:E20)*'Cebada SP'!B3)+(SUMIF('Cebada SS '!J8:J19,"OCTUBRE",'Cebada SS '!E8:E19)*'Cebada SS '!B3) -> 0 | H40: =((SUMIF('Cebada SP'!J8:J20,"NOVIEMBRE",'Cebada SP'!E8:E20)*'Cebada SP'!B3)+(SUMIF('Cebada SS '!J8:J19,"NOVIEMBRE",'Cebada SS '!E8:E19)*'Cebada SS '!B3))/9*'Tipo de Cambio Proyectado'!B8 -> 0 | I40: =(SUMIF('Cebada SP'!J8:J20,"DICIEMBRE",'Cebada SP'!E8:E20)*'Cebada SP'!B3)+(SUMIF('Cebada SS '!J8:J19,"DICIEMBRE",'Cebada SS '!E8:E19)*'Cebada SS '!B3) -> 0 | J40: =(SUMIF('Cebada SP'!J8:J20,"ENERO",'Cebada SP'!E8:E20)*'Cebada SP'!B3)+(SUMIF('Cebada SS '!J8:J19,"ENERO",'Cebada SS '!E8:E19)*'Cebada SS '!B3) -> 0 | K40: =(SUMIF('Cebada SP'!J8:J20,"FEBRERO",'Cebada SP'!E8:E20)*'Cebada SP'!B3)+(SUMIF('Cebada SS '!J8:J19,"FEBRERO",'Cebada SS '!E8:E19)*'Cebada SS '!B3) -> 0 | L40: =(SUMIF('Cebada SP'!J8:J20,"MARZO",'Cebada SP'!E8:E20)*'Cebada SP'!B3)+(SUMIF('Cebada SS '!J8:J19,"MARZO",'Cebada SS '!E8:E19)*'Cebada SS '!B3) -> 0 | M40: =(SUMIF('Cebada SP'!J8:J20,"ABRIL",'Cebada SP'!E8:E20)*'Cebada SP'!B3)+(SUMIF('Cebada SS '!J8:J19,"ABRIL",'Cebada SS '!E8:E19)*'Cebada SS '!B3) -> 0 | P40: =SUM(B40:O40) -> 0
A41: Insumos | B41: =('Cebada SP'!B3*(SUMIF('Cebada SP'!J38:J50,"MAYO",'Cebada SP'!E38:E50)))+('Cebada SS '!B3*(SUMIF('Cebada SS '!J37:J48,"MAYO",'Cebada SS '!E37:E48))) -> 0 | C41: =('Cebada SP'!B3*(SUMIF('Cebada SP'!J38:J50,"JUNIO",'Cebada SP'!E38:E50)))+('Cebada SS '!B3*(SUMIF('Cebada SS '!J37:J48,"JUNIO",'Cebada SS '!E37:E48))) -> 0 | D41: =('Cebada SP'!B3*(SUMIF('Cebada SP'!J38:J50,"JULIO",'Cebada SP'!E38:E50)))+('Cebada SS '!B3*(SUMIF('Cebada SS '!J37:J48,"JULIO",'Cebada SS '!E37:E48))) -> 0 | E41: =('Cebada SP'!B3*(SUMIF('Cebada SP'!J38:J50,"AGOSTO",'Cebada SP'!E38:E50)))+('Cebada SS '!B3*(SUMIF('Cebada SS '!J37:J48,"AGOSTO",'Cebada SS '!E37:E48))) -> 0 | F41: =('Cebada SP'!B3*(SUMIF('Cebada SP'!J38:J50,"SEPTIEMBRE",'Cebada SP'!E38:E50)))+('Cebada SS '!B3*(SUMIF('Cebada SS '!J37:J48,"SEPTIEMBRE",'Cebada SS '!E37:E48))) -> 0 | G41: =('Cebada SP'!B3*(SUMIF('Cebada SP'!J38:J50,"OCTUBRE",'Cebada SP'!E38:E50)))+('Cebada SS '!B3*(SUMIF('Cebada SS '!J37:J48,"OCTUBRE",'Cebada SS '!E37:E48))) -> 0 | H41: =('Cebada SP'!B3*(SUMIF('Cebada SP'!J38:J50,"NOVIEMBRE",'Cebada SP'!E38:E50)))+('Cebada SS '!B3*(SUMIF('Cebada SS '!J37:J48,"NOVIEMBRE",'Cebada SS '!E37:E48))) -> 0 | I41: =('Cebada SP'!B3*(SUMIF('Cebada SP'!J38:J50,"DICIEMBRE",'Cebada SP'!E38:E50)))+('Cebada SS '!B3*(SUMIF('Cebada SS '!J37:J48,"DICIEMBRE",'Cebada SS '!E37:E48))) -> 0 | J41: =('Cebada SP'!B3*(SUMIF('Cebada SP'!J38:J50,"ENERO",'Cebada SP'!E38:E50)))+('Cebada SS '!B3*(SUMIF('Cebada SS '!J37:J48,"ENERO",'Cebada SS '!E37:E48))) -> 0 | K41: =('Cebada SP'!B3*(SUMIF('Cebada SP'!J38:J50,"FEBRERO",'Cebada SP'!E38:E50)))+('Cebada SS '!B3*(SUMIF('Cebada SS '!J37:J48,"FEBRERO",'Cebada SS '!E37:E48))) -> 0 | L41: =('Cebada SP'!B3*(SUMIF('Cebada SP'!J38:J50,"MARZO",'Cebada SP'!E38:E50)))+('Cebada SS '!B3*(SUMIF('Cebada SS '!J37:J48,"MARZO",'Cebada SS '!E37:E48))) -> 0 | P41: =SUM(B41:O41) -> 0
A42: Fertilizante | I42: =+'Cebada SP'!H33 -> 0 | J42: =+'Cebada SP'!H34 -> 0 | P42: =SUM(B42:O42) -> 0
A43: Semilla | J43: =('Cebada SP'!B3*'Cebada SP'!E23)+('Cebada SS '!E22*'Cebada SS '!B3) -> 0 | P43: =SUM(B43:O43) -> 0
A44: Cosecha// Comerc | J44: ='Cebada SP'!D53*'Cebada SP'!B3+'Cebada SP'!E73*'Cebada SP'!B3 -> 0 | P44: =SUM(B44:O44) -> 0
A45: Gerenciamiento | P45: =SUM(B45:O45) -> 0
A46: Seguro | K46: =('Cebada SP'!B3*'Cebada SP'!E57)+('Cebada SS '!B3*'Cebada SS '!E65) -> 0 | P46: =SUM(B46:O46) -> 0
A48: SOJA 2DA CEBADA | B48: =B50-B52 -> 0 | C48: =C50-C52 -> 0 | D48: =D50-D52 -> 0 | E48: =E50-E52 -> 0 | F48: =F50-F52 -> 0 | G48: =G50-G52 -> 0 | H48: =H50-H52 -> 0 | I48: =I50-I52 -> 0 | ... O48: =O50-O52 -> 0 | P48: =SUM(B48:O48) -> 0
B49: =B48 -> 0 | C49: =B49+C48 -> 0 | D49: =C49+D48 -> 0 | E49: =D49+E48 -> 0 | F49: =E49+F48 -> 0 | G49: =F49+G48 -> 0 | H49: =G49+H48 -> 0 | I49: =H49+I48 -> 0 | J49: =I49+J48 -> 0 | ... O49: =N49+O48 -> 0
A50: INGRESOS | B50: =B51 -> 0 | C50: =C51 -> 0 | D50: =D51 -> 0 | E50: =E51 -> 0 | F50: =F51 -> 0 | G50: =G51 -> 0 | H50: =H51 -> 0 | I50: =I51 -> 0 | ... O50: =O51 -> 0 | P50: =SUM(B50:O50) -> 0
A51: Ventas | O51: ='Soja 2da. C'!B77*'Soja 2da. C'!B3 -> 0 | P51: =SUM(B51:O51) -> 0
A52: EGRESOS | B52: =SUM(B53:B59) -> 0 | C52: =SUM(C53:C59) -> 0 | D52: =SUM(D53:D59) -> 0 | E52: =SUM(E53:E59) -> 0 | F52: =SUM(F53:F59) -> 0 | G52: =SUM(G53:G59) -> 0 | H52: =SUM(H53:H59) -> 0 | I52: =SUM(I53:I59) -> 0 | ... O52: =SUM(O53:O59) -> 0 | P52: =SUM(B52:O52) -> 0
A53: Arrendamiento | B53: ='Resumen Proy'!C59*'Resumen Proy'!B9*'Resumen Proy'!G56*0 -> 0 | J53: ='Resumen Proy'!B8*'Resumen Proy'!C59*'Resumen Proy'!I56*0 -> 0 | L53: ='Resumen Proy'!B8*'Resumen Proy'!C59*'Resumen Proy'!J56*0 -> 0 | N53: ='Resumen Proy'!B8*'Resumen Proy'!C59*'Resumen Proy'!K56*0 -> 0 | P53: =SUM(B53:O53) -> 0
A54: Labores | D54: =(SUMIF('Soja 2da. C'!J7:J17,"JULIO",'Soja 2da. C'!E7:E17))*'Soja 2da. C'!B3 -> 0 | E54: =(SUMIF('Soja 2da. C'!J7:J17,"AGOSTO",'Soja 2da. C'!E7:E17))*'Soja 2da. C'!B3 -> 0 | F54: =(SUMIF('Soja 2da. C'!J7:J17,"SEPTIEMBRE",'Soja 2da. C'!E7:E17))*'Soja 2da. C'!B3 -> 0 | G54: =(SUMIF('Soja 2da. C'!J7:J17,"OCTUBRE",'Soja 2da. C'!E7:E17))*'Soja 2da. C'!B3 -> 0 | H54: =(SUMIF('Soja 2da. C'!J7:J17,"NOVIEMBRE",'Soja 2da. C'!E7:E17))*'Soja 2da. C'!B3 -> 0 | I54: =(SUMIF('Soja 2da. C'!J7:J17,"DICIEMBRE",'Soja 2da. C'!E7:E17))*'Soja 2da. C'!B3 -> 0 | J54: =((SUMIF('Soja 2da. C'!J7:J17,"ENERO",'Soja 2da. C'!E7:E17))*'Soja 2da. C'!B3) -> 0 | K54: =(SUMIF('Soja 2da. C'!J7:J17,"FEBRERO",'Soja 2da. C'!E7:E17))*'Soja 2da. C'!B3 -> 0 | L54: =((SUMIF('Soja 2da. C'!J7:J17,"MARZO",'Soja 2da. C'!E7:E17))*'Soja 2da. C'!B3) -> 0 | M54: =(SUMIF('Soja 2da. C'!J7:J17,"ABRIL",'Soja 2da. C'!E7:E17))*'Soja 2da. C'!B3 -> 0 | N54: =(SUMIF('Soja 2da. C'!J7:J17,"MAYO",'Soja 2da. C'!E7:E17))*'Soja 2da. C'!B3 -> 0 | O54: =(SUMIF('Soja 2da. C'!J7:J17,"JUNIO",'Soja 2da. C'!E7:E17))*'Soja 2da. C'!B3 -> 0 | P54: =SUM(B54:O54) -> 0
A55: Insumos | D55: =(SUMIF('Soja 2da. C'!J36:J45,"JULIO",'Soja 2da. C'!E36:E45)*'Soja 2da. C'!B3) -> 0 | E55: =(SUMIF('Soja 2da. C'!J36:J45,"AGOSTO",'Soja 2da. C'!E36:E45)*'Soja 2da. C'!B3) -> 0 | F55: =(SUMIF('Soja 2da. C'!J36:J45,"SEPTIEMBRE",'Soja 2da. C'!E36:E45)*'Soja 2da. C'!B3) -> 0 | G55: =(SUMIF('Soja 2da. C'!J36:J45,"OCTUBRE",'Soja 2da. C'!E36:E45)*'Soja 2da. C'!B3) -> 0 | H55: =(SUMIF('Soja 2da. C'!J36:J45,"NOVIEMBRE",'Soja 2da. C'!E36:E45)*'Soja 2da. C'!B3) -> 0 | I55: =(SUMIF('Soja 2da. C'!J36:J45,"DICIEMBRE",'Soja 2da. C'!E36:E45)*'Soja 2da. C'!B3) -> 0 | J55: =(SUMIF('Soja 2da. C'!J36:J45,"ENERO",'Soja 2da. C'!E36:E45)*'Soja 2da. C'!B3)+('Soja 2da. C'!B3*SUMIF('Soja 2da. C'!J36:J45,"ENERO/MARZO",'Soja 2da. C'!E36:E45)*0.5) -> 0 | K55: =(SUMIF('Soja 2da. C'!J36:J45,"FEBRERO",'Soja 2da. C'!E36:E45)*'Soja 2da. C'!B3) -> 0 | L55: =(SUMIF('Soja 2da. C'!J36:J45,"MARZO",'Soja 2da. C'!E36:E45)*'Soja 2da. C'!B3)+('Soja 2da. C'!B3*SUMIF('Soja 2da. C'!J36:J45,"ENERO/MARZO",'Soja 2da. C'!E36:E45)*0.5) -> 0 | M55: =(SUMIF('Soja 2da. C'!J36:J45,"ABRIL",'Soja 2da. C'!E36:E45)*'Soja 2da. C'!B3) -> 0 | N55: =(SUMIF('Soja 2da. C'!J36:J45,"MAYO",'Soja 2da. C'!E36:E45)*'Soja 2da. C'!B3) -> 0 | O55: =(SUMIF('Soja 2da. C'!J36:J45,"JUNIO",'Soja 2da. C'!E36:E45)*'Soja 2da. C'!B3) -> 0 | P55: =SUM(B55:O55) -> 0
A56: Semilla | J56: ='Soja 2da. C'!E22*'Soja 2da. C'!B3 -> 0 | P56: =SUM(B56:O56) -> 0
A57: Cosecha// Comerc | O57: ='Soja 2da. C'!B3*'Soja 2da. C'!D48+'Soja 2da. C'!B3*'Soja 2da. C'!E68 -> 0 | P57: =SUM(B57:O57) -> 0
A58: Gerenciamiento | P58: =SUM(B58:O58) -> 0
A59: Seguro | O59: ='Soja 2da. C'!E52*'Soja 2da. C'!B3 -> 0 | P59: =SUM(B59:O59) -> 0
A61: MAIZ 2DA | B61: =B63-B65 -> 0 | C61: =C63-C65 -> 0 | D61: =D63-D65 -> 0 | E61: =E63-E65 -> 0 | F61: =F63-F65 -> 0 | G61: =G63-G65 -> 0 | H61: =H63-H65 -> 0 | I61: =I63-I65 -> 0 | ... O61: =O63-O65 -> 0 | P61: =SUM(B61:O61) -> 0
B62: =B61 -> 0 | C62: =B62+C61 -> 0 | D62: =C62+D61 -> 0 | E62: =D62+E61 -> 0 | F62: =E62+F61 -> 0 | G62: =F62+G61 -> 0 | H62: =G62+H61 -> 0 | I62: =H62+I61 -> 0 | J62: =I62+J61 -> 0 | ... O62: =N62+O61 -> 0 | P62: =SUM(B62:O62) -> 0
A63: INGRESOS | B63: =B64 -> 0 | C63: =C64 -> 0 | D63: =D64 -> 0 | E63: =E64 -> 0 | F63: =F64 -> 0 | G63: =G64 -> 0 | H63: =H64 -> 0 | I63: =I64 -> 0 | ... O63: =O64 -> 0 | P63: =SUM(B63:O63) -> 0
A64: Ventas | I64: =(('Maiz 2da'!B61*'Maiz 2da'!B3)+('Girasol 2da'!B3*'Girasol 2da'!B73)) -> 0 | P64: =SUM(B64:O64) -> 0
A65: EGRESOS | B65: =SUM(B66:B73) -> 0 | C65: =SUM(C66:C73) -> 0 | D65: =SUM(D66:D73) -> 0 | E65: =SUM(E66:E73) -> 0 | F65: =SUM(F66:F73) -> 0 | G65: =SUM(G66:G73) -> 0 | H65: =SUM(H66:H73) -> 0 | I65: =SUM(I66:I73) -> 0 | ... O65: =SUM(O66:O73) -> 0 | P65: =SUM(B65:O65) -> 0
A66: Arrendamiento | P66: =SUM(B66:O66) -> 0
A67: Labores | B67: 0 | C67: 0 | D67: =('Maiz 2da'!B3*SUMIF('Maiz 2da'!J8:J12,"JULIO",'Maiz 2da'!E8:E12))+('Girasol 2da'!B3*SUMIF('Girasol 2da'!J8:J15,"JULIO",'Girasol 2da'!E8:E15)) -> 0 | E67: 0 | F67: =('Maiz 2da'!B3*SUMIF('Maiz 2da'!J8:J12,"SEPTIEMBRE",'Maiz 2da'!E8:E12))+('Girasol 2da'!B3*SUMIF('Girasol 2da'!J8:J15,"SEPTIEMBRE",'Girasol 2da'!E8:E15)) -> 0 | G67: =('Maiz 2da'!B3*SUMIF('Maiz 2da'!J8:J12,"OCTUBRE",'Maiz 2da'!E8:E12))+('Girasol 2da'!B3*SUMIF('Girasol 2da'!J8:J15,"OCTUBRE",'Girasol 2da'!E8:E15)) -> 0 | H67: =('Maiz 2da'!B3*SUMIF('Maiz 2da'!J8:J12,"NOVIEMBRE",'Maiz 2da'!E8:E12))+('Girasol 2da'!B3*SUMIF('Girasol 2da'!J8:J15,"NOVIEMBRE",'Girasol 2da'!E8:E15)) -> 0 | I67: =('Maiz 2da'!B3*SUMIF('Maiz 2da'!J8:J12,"DICIEMBRE",'Maiz 2da'!E8:E12))+('Girasol 2da'!B3*SUMIF('Girasol 2da'!J8:J15,"DICIEMBRE",'Girasol 2da'!E8:E15)) -> 0 | J67: =('Maiz 2da'!B3*SUMIF('Maiz 2da'!J8:J12,"ENERO",'Maiz 2da'!E8:E12))+('Girasol 2da'!B3*SUMIF('Girasol 2da'!J8:J15,"ENERO",'Girasol 2da'!E8:E15)) -> 0 | K67: =('Maiz 2da'!B3*SUMIF('Maiz 2da'!J8:J12,"FEBRERO",'Maiz 2da'!E8:E12))+('Girasol 2da'!B3*SUMIF('Girasol 2da'!J8:J15,"FEBRERO",'Girasol 2da'!E8:E15)) -> 0 | P67: =SUM(B67:O67) -> 0
A68: Insumos | B68: =('Maiz 2da'!B3*(SUMIF('Maiz 2da'!J30:J32,"MAYO",'Maiz 2da'!E30:E32)))+('Girasol 2da'!B3*(SUMIF('Girasol 2da'!J33:J38,"MAYO",'Girasol 2da'!E33:E38))) -> 0 | C68: =('Maiz 2da'!B3*(SUMIF('Maiz 2da'!J30:J32,"JUNIO",'Maiz 2da'!E30:E32)))+('Girasol 2da'!B3*(SUMIF('Girasol 2da'!J33:J38,"JUNIO",'Girasol 2da'!E33:E38))) -> 0 | D68: =('Maiz 2da'!B3*(SUMIF('Maiz 2da'!J30:J32,"JULIO",'Maiz 2da'!E30:E32)))+('Girasol 2da'!B3*(SUMIF('Girasol 2da'!J33:J38,"JULIO",'Girasol 2da'!E33:E38))) -> 0 | E68: =('Maiz 2da'!B3*(SUMIF('Maiz 2da'!J30:J32,"AGOSTO",'Maiz 2da'!E30:E32)))+('Girasol 2da'!B3*(SUMIF('Girasol 2da'!J33:J38,"AGOSTO",'Girasol 2da'!E33:E38))) -> 0 | F68: =('Maiz 2da'!B3*(SUMIF('Maiz 2da'!J30:J32,"SEPTIEMBRE",'Maiz 2da'!E30:E32)))+('Girasol 2da'!B3*(SUMIF('Girasol 2da'!J33:J38,"SEPTIEMBRE",'Girasol 2da'!E33:E38))) -> 0 | G68: =('Maiz 2da'!B3*(SUMIF('Maiz 2da'!J30:J32,"OCTUBRE",'Maiz 2da'!E30:E32)))+('Girasol 2da'!B3*(SUMIF('Girasol 2da'!J33:J38,"OCTUBRE",'Girasol 2da'!E33:E38))) -> 0 | H68: =('Maiz 2da'!B3*(SUMIF('Maiz 2da'!J30:J32,"NOVIEMBRE",'Maiz 2da'!E30:E32)))+('Girasol 2da'!B3*(SUMIF('Girasol 2da'!J33:J38,"NOVIEMBRE",'Girasol 2da'!E33:E38))) -> 0 | I68: =('Maiz 2da'!B3*(SUMIF('Maiz 2da'!J30:J32,"DICIEMBRE",'Maiz 2da'!E30:E32)))+('Girasol 2da'!B3*(SUMIF('Girasol 2da'!J33:J38,"DICIEMBRE",'Girasol 2da'!E33:E38))) -> 0 | J68: =('Maiz 2da'!B3*(SUMIF('Maiz 2da'!J30:J32,"ENERO",'Maiz 2da'!E30:E32)))+('Girasol 2da'!B3*(SUMIF('Girasol 2da'!J33:J38,"ENERO",'Girasol 2da'!E33:E38))) -> 0 | K68: =('Maiz 2da'!B3*(SUMIF('Maiz 2da'!J30:J32,"FEBRERO",'Maiz 2da'!E30:E32)))+('Girasol 2da'!B3*(SUMIF('Girasol 2da'!J33:J38,"FEBRERO",'Girasol 2da'!E33:E38))) -> 0 | L68: =('Maiz 2da'!B3*(SUMIF('Maiz 2da'!J30:J32,"MARZO",'Maiz 2da'!E30:E32)))+('Girasol 2da'!B3*(SUMIF('Girasol 2da'!J33:J38,"MARZO",'Girasol 2da'!E33:E38))) -> 0 | M68: =('Maiz 2da'!B3*(SUMIF('Maiz 2da'!J30:J32,"ABRIL",'Maiz 2da'!E30:E32)))+('Girasol 2da'!B3*(SUMIF('Girasol 2da'!J33:J38,"ABRIL",'Girasol 2da'!E33:E38))) -> 0 | P68: =SUM(B68:O68) -> 0
A69: Fertilizante | B69: =('Maiz 2da'!B3*SUMIF('Maiz 2da'!J26:J27,"MAYO",'Maiz 2da'!E26:E27))+('Girasol 2da'!B3*SUMIF('Girasol 2da'!J29:J30,"MAYO",'Girasol 2da'!E29:E30)) -> 0 | C69: =('Maiz 2da'!B3*SUMIF('Maiz 2da'!J26:J27,"JUNIO",'Maiz 2da'!E26:E27))+('Girasol 2da'!B3*SUMIF('Girasol 2da'!J29:J30,"JUNIO",'Girasol 2da'!E29:E30)) -> 0 | D69: =('Maiz 2da'!B3*SUMIF('Maiz 2da'!J26:J27,"JULIO",'Maiz 2da'!E26:E27))+('Girasol 2da'!B3*SUMIF('Girasol 2da'!J29:J30,"JULIO",'Girasol 2da'!E29:E30)) -> 0 | E69: =('Maiz 2da'!B3*SUMIF('Maiz 2da'!J26:J27,"AGOSTO",'Maiz 2da'!E26:E27))+('Girasol 2da'!B3*SUMIF('Girasol 2da'!J29:J30,"AGOSTO",'Girasol 2da'!E29:E30)) -> 0 | J69: =+'Maiz 2da'!I27 -> 0 | P69: =SUM(B69:O69) -> 0
A70: Semilla | B70: ='Maiz 2da'!B3*'Maiz 2da'!E16 -> 0 | P70: =SUM(B70:O70) -> 0
A71: Cosecha// Comerc | I71: =('Maiz 2da'!B3*('Maiz 2da'!E36+'Maiz 2da'!E46))+('Girasol 2da'!B3*('Girasol 2da'!E42+'Girasol 2da'!E52)) -> 0 | P71: =SUM(B71:O71) -> 0
A72: Gerenciamiento | B72: =(('Maiz 2da'!E23*'Maiz 2da'!B3)+('Girasol 2da'!B3*'Girasol 2da'!F26))*0.1 -> 0 | C72: =(('Maiz 2da'!E23*'Maiz 2da'!B3)+('Girasol 2da'!B3*'Girasol 2da'!F26))*0.1 -> 0 | D72: =(('Maiz 2da'!E23*'Maiz 2da'!B3)+('Girasol 2da'!B3*'Girasol 2da'!F26))*0.1 -> 0 | E72: =(('Maiz 2da'!E23*'Maiz 2da'!B3)+('Girasol 2da'!B3*'Girasol 2da'!F26))*0.1 -> 0 | F72: =(('Maiz 2da'!E23*'Maiz 2da'!B3)+('Girasol 2da'!B3*'Girasol 2da'!F26))*0.1 -> 0 | G72: =(('Maiz 2da'!E23*'Maiz 2da'!B3)+('Girasol 2da'!B3*'Girasol 2da'!F26))*0.1 -> 0 | H72: =(('Maiz 2da'!E23*'Maiz 2da'!B3)+('Girasol 2da'!B3*'Girasol 2da'!F26))*0.1 -> 0 | I72: =(('Maiz 2da'!E23*'Maiz 2da'!B3)+('Girasol 2da'!B3*'Girasol 2da'!F26))*0.1 -> 0 | J72: =(('Maiz 2da'!E23*'Maiz 2da'!B3)+('Girasol 2da'!B3*'Girasol 2da'!F26))*0.1 -> 0 | K72: =(('Maiz 2da'!E23*'Maiz 2da'!B3)+('Girasol 2da'!B3*'Girasol 2da'!F26))*0.1 -> 0 | P72: =SUM(B72:O72) -> 0
A73: Seguro | J73: =('Maiz 2da'!E49*'Maiz 2da'!B3)+('Girasol 2da'!E55*'Girasol 2da'!B3) -> 0 | P73: =SUM(B73:O73) -> 0
P74: =SUM(B74:O74) -> 0
A75: SOJA 2DA COLZA | B75: =B77-B79 -> 0 | C75: =C77-C79 -> 0 | D75: =D77-D79 -> 0 | E75: =E77-E79 -> 0 | F75: =F77-F79 -> 0 | G75: =G77-G79 -> 0 | H75: =H77-H79 -> 0 | I75: =I77-I79 -> 0 | ... O75: =O77-O79 -> 0 | P75: =SUM(B75:O75) -> 0
B76: =B75 -> 0 | C76: =B76+C75 -> 0 | D76: =C76+D75 -> 0 | E76: =D76+E75 -> 0 | F76: =E76+F75 -> 0 | G76: =F76+G75 -> 0 | H76: =G76+H75 -> 0 | I76: =H76+I75 -> 0 | J76: =I76+J75 -> 0 | ... O76: =N76+O75 -> 0 | P76: =SUM(B76:O76) -> 0
A77: INGRESOS | B77: =B78 -> 0 | C77: =C78 -> 0 | D77: =D78 -> 0 | E77: =E78 -> 0 | F77: =F78 -> 0 | G77: =G78 -> 0 | H77: =H78 -> 0 | I77: =I78 -> 0 | ... O77: =O78 -> 0 | P77: =SUM(B77:O77) -> 0
A78: Ventas | N78: =('Soja 2da. Co'!B74*'Soja 2da. Co'!B3)*0.4 -> 0 | O78: =('Soja 2da. Co'!B74*'Soja 2da. Co'!B3)*0.6 -> 0 | P78: =SUM(B78:O78) -> 0
A79: EGRESOS | B79: =SUM(B80:B86) -> 0 | C79: =SUM(C80:C86) -> 0 | D79: =SUM(D80:D86) -> 0 | E79: =SUM(E80:E86) -> 0 | F79: =SUM(F80:F86) -> 0 | G79: =SUM(G80:G86) -> 0 | H79: =SUM(H80:H86) -> 0 | I79: =SUM(I80:I86) -> 0 | ... O79: =SUM(O80:O86) -> 0 | P79: =SUM(B79:O79) -> 0
A80: Arrendamiento | P80: =SUM(B80:O80) -> 0
A81: Labores | D81: =(SUMIF('Soja 2da. Co'!J7:J17,"JULIO",'Soja 2da. Co'!E7:E17))*'Soja 2da. C'!B3 -> 0 | E81: =(SUMIF('Soja 2da. Co'!J7:J17,"AGOSTO",'Soja 2da. Co'!E7:E17))*'Soja 2da. Co'!B3 -> 0 | F81: =(SUMIF('Soja 2da. Co'!J7:J17,"SEPTIEMBRE",'Soja 2da. Co'!E7:E17))*'Soja 2da. Co'!B3 -> 0 | G81: =(SUMIF('Soja 2da. Co'!J7:J17,"OCTUBRE",'Soja 2da. Co'!E7:E17))*'Soja 2da. Co'!B3 -> 0 | H81: =(SUMIF('Soja 2da. Co'!J7:J17,"NOVIEMBRE",'Soja 2da. Co'!E7:E17))*'Soja 2da. Co'!B3 -> 0 | I81: =(SUMIF('Soja 2da. Co'!J7:J17,"DICIEMBRE",'Soja 2da. Co'!E7:E17))*'Soja 2da. Co'!B3 -> 0 | J81: =(SUMIF('Soja 2da. Co'!J7:J17,"ENERO",'Soja 2da. Co'!E7:E17))*'Soja 2da. Co'!B3 -> 0 | K81: =(SUMIF('Soja 2da. Co'!J7:J17,"FEBRERO",'Soja 2da. Co'!E7:E17))*'Soja 2da. Co'!B3 -> 0 | L81: =(SUMIF('Soja 2da. Co'!J7:J17,"MARZO",'Soja 2da. Co'!E7:E17))*'Soja 2da. Co'!B3 -> 0 | M81: =(SUMIF('Soja 2da. Co'!J7:J17,"ABRIL",'Soja 2da. Co'!E7:E17))*'Soja 2da. Co'!B3 -> 0 | N81: =(SUMIF('Soja 2da. Co'!J7:J17,"MAYO",'Soja 2da. Co'!E7:E17))*'Soja 2da. Co'!B3 -> 0 | O81: =(SUMIF('Soja 2da. Co'!J7:J17,"JUNIO",'Soja 2da. Co'!E7:E17))*'Soja 2da. Co'!B3 -> 0 | P81: =SUM(B81:O81) -> 0
A82: Insumos | D82: =(SUMIF('Soja 2da. Co'!J35:J44,"JULIO",'Soja 2da. Co'!E35:E44)*'Soja 2da. Co'!B3) -> 0 | E82: =(SUMIF('Soja 2da. Co'!J35:J44,"AGOSTO",'Soja 2da. Co'!E35:E44)*'Soja 2da. Co'!B3) -> 0 | F82: =(SUMIF('Soja 2da. Co'!J35:J44,"SEPTIEMBRE}",'Soja 2da. Co'!E35:E44)*'Soja 2da. Co'!B3) -> 0 | G82: =(SUMIF('Soja 2da. Co'!J35:J44,"OCTUBRE",'Soja 2da. Co'!E35:E44)*'Soja 2da. Co'!B3) -> 0 | H82: =(SUMIF('Soja 2da. Co'!J35:J44,"NOVIEMBRE",'Soja 2da. Co'!E35:E44)*'Soja 2da. Co'!B3) -> 0 | I82: =(SUMIF('Soja 2da. Co'!J35:J44,"DICIEMBRE",'Soja 2da. Co'!E35:E44)*'Soja 2da. Co'!B3) -> 0 | J82: =(SUMIF('Soja 2da. Co'!J35:J44,"ENERO",'Soja 2da. Co'!E35:E44)*'Soja 2da. Co'!B3)+('Soja 2da. Co'!B3*SUMIF('Soja 2da. Co'!J35:J44,"ENERO/MARZO",'Soja 2da. Co'!E35:E44)*0.5) -> 0 | K82: =(SUMIF('Soja 2da. Co'!J35:J44,"FEBRERO",'Soja 2da. Co'!E35:E44)*'Soja 2da. Co'!B3) -> 0 | L82: =(SUMIF('Soja 2da. Co'!J35:J44,"MARZO",'Soja 2da. Co'!E35:E44)*'Soja 2da. Co'!B3)+('Soja 2da. Co'!B3*SUMIF('Soja 2da. Co'!J35:J44,"ENERO/MARZO",'Soja 2da. Co'!E35:E44)*0.5) -> 0 | M82: =(SUMIF('Soja 2da. Co'!J35:J44,"ABRIL",'Soja 2da. Co'!E35:E44)*'Soja 2da. Co'!B3) -> 0 | N82: =(SUMIF('Soja 2da. Co'!J35:J44,"MAYO",'Soja 2da. Co'!E35:E44)*'Soja 2da. Co'!B3) -> 0 | O82: =(SUMIF('Soja 2da. Co'!J35:J44,"JUNIO",'Soja 2da. Co'!E35:E44)*'Soja 2da. Co'!B3) -> 0 | P82: =SUM(B82:O82) -> 0
A83: Semilla | J83: ='Soja 2da. Co'!B3*'Soja 2da. Co'!E22 -> 0 | P83: =SUM(B83:O83) -> 0
A84: Cosecha// Comerc | O84: ='Soja 2da. Co'!B3*('Soja 2da. Co'!E48+'Soja 2da. Co'!E58) -> 0 | P84: =SUM(B84:O84) -> 0
A85: Gerenciamiento | F85: ='Soja 2da. Co'!E28*'Soja 2da. Co'!B3*0.1 -> 0 | G85: ='Soja 2da. Co'!E28*'Soja 2da. Co'!B3*0.1 -> 0 | H85: ='Soja 2da. Co'!E28*'Soja 2da. Co'!B3*0.1 -> 0 | I85: ='Soja 2da. Co'!E28*'Soja 2da. Co'!B3*0.1 -> 0 | J85: ='Soja 2da. Co'!E28*'Soja 2da. Co'!B3*0.1 -> 0 | K85: ='Soja 2da. Co'!E28*'Soja 2da. Co'!B3*0.1 -> 0 | L85: ='Soja 2da. Co'!E28*'Soja 2da. Co'!B3*0.1 -> 0 | M85: ='Soja 2da. Co'!E28*'Soja 2da. Co'!B3*0.1 -> 0 | N85: ='Soja 2da. Co'!E28*'Soja 2da. Co'!B3*0.1 -> 0 | O85: ='Soja 2da. Co'!E28*'Soja 2da. Co'!B3*0.1 -> 0 | P85: =SUM(B85:O85) -> 0
A86: Seguro | O86: ='Soja 2da. Co'!E62*'Soja 2da. Co'!B3 -> 0 | P86: =SUM(B86:O86) -> 0
A88: MAÍZ | B88: =B90-B92 -> 0 | C88: =C90-C92 -> 0 | D88: =D90-D92 -> 0 | E88: =E90-E92 -> 0 | F88: =F90-F92 -> 0 | G88: =G90-G92 -> 0 | H88: =H90-H92 -> 0 | I88: =I90-I92 -> 0 | ... O88: =O90-O92 -> 0 | P88: =SUM(B88:O88) -> 0
B89: =B88 -> 0 | C89: =B89+C88 -> 0 | D89: =C89+D88 -> 0 | E89: =D89+E88 -> 0 | F89: =E89+F88 -> 0 | G89: =F89+G88 -> 0 | H89: =G89+H88 -> 0 | I89: =H89+I88 -> 0 | J89: =I89+J88 -> 0 | ... O89: =N89+O88 -> 0 | P89: =SUM(B89:O89) -> 0
A90: INGRESOS | B90: =B91 -> 0 | C90: =C91 -> 0 | D90: =D91 -> 0 | E90: =E91 -> 0 | F90: =F91 -> 0 | G90: =G91 -> 0 | H90: =H91 -> 0 | I90: =I91 -> 0 | ... O90: =O91 -> 0 | P90: =SUM(B90:O90) -> 0
A91: Ventas | N91: ='Maiz SP'!B79*'Maiz SP'!B3*0.15 -> 0 | O91: ='Maiz SP'!B79*'Maiz SP'!B3*0.85 -> 0 | P91: =SUM(B91:O91) -> 0
A92: EGRESOS | B92: =SUM(B93:B100) -> 0 | C92: =SUM(C93:C100) -> 0 | D92: =SUM(D93:D100) -> 0 | E92: =SUM(E93:E100) -> 0 | F92: =SUM(F93:F100) -> 0 | G92: =SUM(G93:G100) -> 0 | H92: =SUM(H93:H100) -> 0 | I92: =SUM(I93:I100) -> 0 | ... O92: =SUM(O93:O100) -> 0 | P92: =SUM(B92:O92) -> 0
A93: Arrendamiento | B93: =+'[2]Alquileres por campo'!$D$62+'[2]Alquileres por campo'!$E$62 -> 0 | C93: =+'[2]Alquileres por campo'!F62 -> 0 | D93: =+'[2]Alquileres por campo'!G62 -> 0 | E93: =+'[2]Alquileres por campo'!H62 -> 0 | F93: =+'[2]Alquileres por campo'!I62 -> 0 | G93: =+'[2]Alquileres por campo'!J62 -> 0 | H93: =+'[2]Alquileres por campo'!K62 -> 0 | I93: =+'[2]Alquileres por campo'!L62 -> 0 | J93: =+'[2]Alquileres por campo'!M62 -> 0 | ... O93: =+'[2]Alquileres por campo'!R62 -> 0 | P93: =SUM(B93:O93) -> 0
A94: Labores | D94: ='Maiz SP'!B3*(SUMIF('Maiz SP'!J6:J20,"JULIO",'Maiz SP'!E6:E20)) -> 0 | E94: ='Maiz SP'!B3*(SUMIF('Maiz SP'!J6:J20,"AGOSTO",'Maiz SP'!E6:E20)) -> 0 | F94: ='Maiz SP'!B3*(SUMIF('Maiz SP'!J6:J20,"SEPTIEMBRE",'Maiz SP'!E6:E20)) -> 0 | G94: ='Maiz SP'!B3*(SUMIF('Maiz SP'!J6:J20,"OCTUBRE",'Maiz SP'!E6:E20)) -> 0 | H94: ='Maiz SP'!B3*(SUMIF('Maiz SP'!J6:J20,"NOVIEMBRE",'Maiz SP'!E6:E20)) -> 0 | I94: ='Maiz SP'!B3*(SUMIF('Maiz SP'!J6:J20,"DICIEMBRE",'Maiz SP'!E6:E20)) -> 0 | J94: ='Maiz SP'!B3*(SUMIF('Maiz SP'!J6:J20,"ENERO",'Maiz SP'!E6:E20)) -> 0 | K94: ='Maiz SP'!B3*(SUMIF('Maiz SP'!J6:J20,"FEBRERO",'Maiz SP'!E6:E20)) -> 0 | L94: ='Maiz SP'!B3*(SUMIF('Maiz SP'!J6:J20,"MARZO",'Maiz SP'!E6:E20)) -> 0 | M94: ='Maiz SP'!B3*(SUMIF('Maiz SP'!J6:J20,"ABRIL",'Maiz SP'!E6:E20)) -> 0 | N94: ='Maiz SP'!B3*(SUMIF('Maiz SP'!J6:J20,"MAYO",'Maiz SP'!E6:E20)) -> 0 | O94: ='Maiz SP'!B3*(SUMIF('Maiz SP'!J6:J20,"JUNIO",'Maiz SP'!E6:E20)) -> 0 | P94: =SUM(B94:O94) -> 0
A95: Insumos | D95: ='Maiz SP'!B3*(SUMIF('Maiz SP'!J38:J47,"JULIO",'Maiz SP'!E38:E47)) -> 0 | E95: ='Maiz SP'!B3*(SUMIF('Maiz SP'!J38:J47,"AGOSTO",'Maiz SP'!E38:E47)) -> 0 | F95: ='Maiz SP'!B3*(SUMIF('Maiz SP'!J38:J47,"SEPTIEMBRE",'Maiz SP'!E38:E47)) -> 0 | G95: ='Maiz SP'!B3*(SUMIF('Maiz SP'!J38:J47,"OCTUBRE",'Maiz SP'!E38:E47)) -> 0 | H95: ='Maiz SP'!B3*(SUMIF('Maiz SP'!J38:J47,"NOVIEMBRE",'Maiz SP'!E38:E47)) -> 0 | I95: ='Maiz SP'!B3*(SUMIF('Maiz SP'!J38:J47,"DICIEMBRE",'Maiz SP'!E38:E47)) -> 0 | J95: ='Maiz SP'!B3*(SUMIF('Maiz SP'!J38:J47,"ENERO",'Maiz SP'!E38:E47)) -> 0 | K95: ='Maiz SP'!B3*(SUMIF('Maiz SP'!J38:J47,"FEBRERO",'Maiz SP'!E38:E47)) -> 0 | L95: ='Maiz SP'!B3*(SUMIF('Maiz SP'!J38:J47,"MARZO",'Maiz SP'!E38:E47)) -> 0 | M95: ='Maiz SP'!B3*(SUMIF('Maiz SP'!J38:J47,"ABRIL",'Maiz SP'!E38:E47)) -> 0 | N95: ='Maiz SP'!B3*(SUMIF('Maiz SP'!J38:J47,"MAYO",'Maiz SP'!E38:E47)) -> 0 | O95: ='Maiz SP'!B3*(SUMIF('Maiz SP'!J38:J47,"JUNIO",'Maiz SP'!E38:E47)) -> 0 | P95: =SUM(B95:O95) -> 0
A96: Semilla | J96: ='Maiz SP'!E24*'Maiz SP'!B3 -> 0 | P96: =SUM(B96:O96) -> 0
A97: Fertilizante | I97: =+'Maiz SP'!I33 -> 0 | J97: =+'Maiz SP'!I35 -> 0 | P97: =SUM(B97:O97) -> 0
A98: Cosecha// Comerc | O98: ='Maiz SP'!B3*('Maiz SP'!E51+'Maiz SP'!E71) -> 0 | P98: =SUM(B98:O98) -> 0
A99: Gerenciamiento | P99: =SUM(B99:O99) -> 0
A100: Seguro | O100: ='Maiz SP'!B3*'Maiz SP'!E54 -> 0 | P100: =SUM(B100:O100) -> 0
A102: SOJA | B102: =B104-B106 -> 0 | C102: =C104-C106 -> 0 | D102: =D104-D106 -> 0 | E102: =E104-E106 -> 0 | F102: =F104-F106 -> 0 | G102: =G104-G106 -> 0 | H102: =H104-H106 -> 0 | I102: =I104-I106 -> 0 | ... O102: =O104-O106 -> 0 | P102: =SUM(B102:O102) -> 0
B103: =B102 -> 0 | C103: =B103+C102 -> 0 | D103: =C103+D102 -> 0 | E103: =D103+E102 -> 0 | F103: =E103+F102 -> 0 | G103: =F103+G102 -> 0 | H103: =G103+H102 -> 0 | I103: =H103+I102 -> 0 | J103: =I103+J102 -> 0 | ... O103: =N103+O102 -> 0 | P103: =SUM(B103:O103) -> 0
A104: INGRESOS | B104: =B105 -> 0 | C104: =C105 -> 0 | D104: =D105 -> 0 | E104: =E105 -> 0 | F104: =F105 -> 0 | G104: =G105 -> 0 | H104: =H105 -> 0 | I104: =I105 -> 0 | ... O104: =O105 -> 0 | P104: =SUM(B104:O104) -> 0
A105: Ventas | N105: =0.3*(Camelina!B85*Camelina!B3) -> 0 | O105: =0.7*(Camelina!B85*Camelina!B3) -> 0 | P105: =SUM(B105:O105) -> 0
A106: EGRESOS | B106: =SUM(B107:B114) -> 0 | C106: =SUM(C107:C114) -> 0 | D106: =SUM(D107:D114) -> 0 | E106: =SUM(E107:E114) -> 0 | F106: =SUM(F107:F114) -> 0 | G106: =SUM(G107:G114) -> 0 | H106: =SUM(H107:H114) -> 0 | I106: =SUM(I107:I114) -> 0 | ... O106: =SUM(O107:O114) -> 0 | P106: =SUM(B106:O106) -> 0
A107: Arrendamiento | B107: ='Resumen Proy'!B15*'Resumen Proy'!C57*'Resumen Proy'!G56 -> 0 | J107: ='Resumen Proy'!B15*'Resumen Proy'!I56*'Resumen Proy'!C57 -> 0 | L107: ='Resumen Proy'!B15*'Resumen Proy'!J56*'Resumen Proy'!C57 -> 0 | N107: ='Resumen Proy'!B15*'Resumen Proy'!C57*'Resumen Proy'!K56 -> 0 | P107: =SUM(B107:O107) -> 0 | U107: =Camelina!B3*((SUMIF(Camelina!J8:J19,"MAYO",Camelina!E8:E18))+(SUMIF('Soja SS'!J8:J19,"MAYO",'Soja SS'!E8:E19))) -> 0
A108: Labores | D108: =Camelina!B3*((SUMIF(Camelina!J8:J19,"JULIO",Camelina!E8:E18))+(SUMIF('Soja SS'!J8:J19,"JULIO",'Soja SS'!E8:E19))) -> 0 | J108: =+C108 -> 0 | L108: =+J108 -> 0 | M108: =Camelina!B3*((SUMIF(Camelina!J8:J19,"ABRIL",Camelina!E8:E18))+(SUMIF('Soja SS'!J8:J19,"ABRIL",'Soja SS'!E8:E19))) -> 0 | P108: =SUM(B108:O108) -> 0
...

Sheet Cebada SP
A1: Proyección Cebada
A3: HECTAREAS | B3: 0
B5: CANTIDAD | C5: UNIDAD | D5: PRECIO | E5: TOTAL / HA | F5: % Costo | G5: Inv Real | H5: Mes | J5: MES CASH FLOW
D6: UNITARIO
A7: Labores
A8: Disco,rastra y rolo | B8: 0 | C8: Uni | D8: =+Cotizaciones!E8/Cotizaciones!M7 -> 29.014943 | E8: =B8*D8 -> 0 | H8: Abril | J8: MAYO
A9: Rolo picador | B9: 1 | C9: Uni | D9: 24 | E9: =B9*D9 -> 24 | H9: Abril | J9: MAYO
A10: Barbecho Quimico | B10: 2 | C10: Uni | D10: 6.5 | E10: =B10*D10 -> 13 | H10: 41030 | J10: MAYO
A11: Siembra | B11: 1 | C11: Uni | D11: 55 | E11: =B11*D11 -> 55 | H11: 41061 | J11: JULIO
A12: Pulverizacion Post-emergente | B12: 1 | C12: Uni | D12: 6.5 | E12: =B12*D12 -> 6.5 | F12: =42*105 -> 4410 | H12: 1/2 Julio | J12: AGOSTO
A13: Pulverización graminicidas | B13: 0 | C13: Uni | D13: 6.5 | E13: =B13*D13 -> 0 | H13: 1/2 Julio | J13: AGOSTO
A14: Aplicación Urea | B14: 1 | C14: Uni | D14: 11 | E14: =B14*D14 -> 11 | H14: 41091 | I14: 41122 | J14: JULIO
A15: Aplicación Urea | B15: 1 | C15: Uni | D15: 11 | E15: =B15*D15 -> 11 | J15: AGOSTO
A16: Aplicacion Fungicida Terrestre | B16: 2 | C16: Uni | D16: 6.5 | E16: =B16*D16 -> 13 | H16: 1/2 octubre | J16: NOVIEMBRE
A17: Muestreo de suelos | B17: 1 | C17: Uni | D17: 1 | E17: =B17*D17 -> 1 | H17: 41030 | J17: MAYO
A18: Analisis de suelos | B18: 0 | C18: Uni | D18: 1 | E18: =B18*D18 -> 0 | H18: 41030 | J18: MAYO
A19: Medicion satelital GPS | B19: 0 | C19: Uni | D19: 0 | E19: =B19*D19 -> 0 | J19: MAYO
A20: Limpieza, Curada e Inoculada | B20: 0 | C20: Uni | D20: 0 | E20: =B20*D20 -> 0 | J20: MAYO
C21: Total Labores | E21: =SUM(E8:E20) -> 134.5 | F21: =E21/E62 -> 0.12874386 | H21: =E21*$B$3 -> 0
A22: Semilla
A23: Semilla Cebada | B23: 140 | C23: Ton | D23: =+Cotizaciones!E40 -> 0.52 | E23: =B23*D23 -> 72.8 | H23: Canje | J23: ENERO
A24: Flete | D24: =+Cotizaciones!F26/1000 -> 0.035 | E24: =+D24*B23 -> 4.9 | H24: =E25*$B$3 -> 0
C25: Total Semilla | E25: =SUM(E23:E24) -> 77.7 | F25: =E25/E62 -> 0.074374707
A26: Arrendamiento | B26: 0.8 | C26: Uni | D26: =+'Resumen Proy'!C57 -> 426 | E26: =B26*D26 -> 340.8
C27: Total Arrendamiento | E27: =E26 -> 340.8 | F27: =E27/E62 -> 0.32621493 | H27: =+'[2]Alquileres por campo'!$S$58 -> 0
A29: Gerenciamiento | B29: 40 | C29: USD / Ha | D29: =+B29 -> 40 | E29: =D29 -> 40
C30: Total Gerenciamiento | E30: =E29 -> 40 | F30: =E30/E62 -> 0.038288137 | H30: =E30*$B$3 -> 0
A32: Fertilizantes
A33: Fosforados (en campo) | B33: 0.08 | C33: Ton. | D33: =+Cotizaciones!I25 -> 990 | E33: =B33*D33 -> 79.2 | H33: =+B3*E33 -> 0 | J33: DICIEMBRE
A34: Nitrogenados (en campo) | B34: 0.24 | C34: Ton. | D34: =+Cotizaciones!I34 -> 610 | E34: =B34*D34 -> 146.4 | H34: =+E34*B3 -> 0 | J34: ABRIL | K34: 200 tn se paga en marzo 100 tn en junio
A35: Flete | B35: =+B34+B33 -> 0.32 | C35: Ton. | D35: =+Cotizaciones!F26 -> 35 | E35: =+D35*B35 -> 11.2
C36: Total Fertilizantes | E36: =+E35+E34+E33 -> 236.8 | F36: =E36/E62 -> 0.22666577 | H36: =E36*$B$3 -> 0
A37: Agroquímicos
H38: siembra | J38: MAYO
A39: Paraquat | B39: 2 | C39: Lts. | D39: =+Cotizaciones!I45 -> 2.6 | E39: =B39*D39 -> 5.2 | H39: =A10 -> Barbecho Quimico | J39: MAYO
A40: yamato top | B40: 0.12 | C40: Lts. | D40: =+Cotizaciones!I50 -> 80 | E40: =B40*D40 -> 9.6 | H40: Fungicida | J40: MAYO
A41: Sulfosato | B41: 2 | C41: Lts. | D41: =+Cotizaciones!I28 -> 4.5 | E41: =B41*D41 -> 9 | H41: =A10 -> Barbecho Quimico | J41: MAYO
A42: 2,4-D | B42: 1.2 | C42: Lts. | D42: =+Cotizaciones!I5 -> 4.6 | E42: =B42*D42 -> 5.52 | H42: =A10 -> Barbecho Quimico | J42: MAYO
A43: MCPA | B43: 0.03 | C43: Lts. | D43: =+Cotizaciones!I32 -> 11 | E43: =B43*D43 -> 0.33 | H43: Barbecho Quimico | J43: MAYO
A44: Axial | B44: 0 | C44: Lts. | D44: =Cotizaciones!I11 -> 39 | E44: =B44*D44 -> 0 | H44: =+A13 -> Pulverización graminicidas | J44: ENERO
A45: Fungicida (Orquesta) | B45: 2 | C45: Lts. | D45: =Cotizaciones!I26 -> 28 | E45: =B45*D45 -> 56 | H45: =A16 -> Aplicacion Fungicida Terrestre | J45: NOVIEMBRE
A46: Affinity | B46: 0.08 | C46: Lts. | D46: =Cotizaciones!I46 -> 80 | E46: =B46*D46 -> 6.4 | J46: SEPTIEMBRE
A47: Cletodyn | B47: 0.8 | C47: Lts. | D47: =+Cotizaciones!I27 -> 6 | E47: =B47*D47 -> 4.8 | H47: =A12 -> Pulverizacion Post-emergente | J47: ENERO
A48: Dicamba | B48: 0.15 | C48: Lts. | D48: =Cotizaciones!I23 -> 7 | E48: =B48*D48 -> 1.05 | J48: AGOSTO
A49: Flurocloridona | B49: 1 | C49: Lts. | D49: =+Cotizaciones!I24 -> 11.8 | E49: =B49*D49 -> 11.8 | H49: =H45 -> Aplicacion Fungicida Terrestre | J49: NOVIEMBRE
A50: Metsulfuron | B50: 0.006 | C50: Kgs | D50: =Cotizaciones!I37 -> 35 | E50: =B50*D50 -> 0.21 | H50: =H41 -> Barbecho Quimico | J50: MAYO
C51: Total Agroquimicos | E51: =+SUM(E38:E50) -> 109.91 | F51: =E51/E62 -> 0.10520623 | H51: =E51*$B$3 -> 0
A53: Cosecha | B53: 1 | C53: Hás. | D53: 85 | E53: =+D53*B53 -> 85 | H53: 41245 | J53: ENERO
C54: Total Cosecha | E54: =+E53 -> 85 | F54: =E54/E62 -> 0.081362292 | H54: =E54*$B$3 -> 0
A56: Seguro (Granizo) | B56: 2 | C56: % Costo | D56: 20 | E56: =D56 -> 20 | H56: 40909
C57: Total Seguro | E57: =E56 -> 20 | F57: =E57/E62 -> 0.019144069 | H57: =E57*$B$3 -> 0
A59: Costos Financiero | B59: 0 | C59: % | D59: +
C60: Total Costo Financ. | H60: =E60*$B$3 -> 0
C62: Costo Total/ha | E62: =+E51+E36+E30+E27+E25+E21+E54+E57 -> 1044.71 | F62: =+E62*B3 -> 0 | H62: Alea | I62: Socio
G63: =+A7 -> Labores
A64: Comercialización | G64: =+A22 -> Semilla
A65: Extraccion/Embolsado | B65: 1.4 | C65: U$ / ton | D65: =+Cotizaciones!F24 -> 3.3 | E65: =D65*B65*B80 -> 26.334 | G65: =+A26 -> Arrendamiento
A66: Silobolsa | B66: 0.7 | C66: 180 Tons | D66: =Cotizaciones!I40/220 -> 1.7272727 | E66: =D66*B66*B80 -> 6.8918182 | G66: =+A29 -> Gerenciamiento
A67: Secada | B67: 0 | C67: U$ / ton | E67: =+D67*B67*B80 -> 0
A68: Paritaria | B68: 0 | C68: U$ / ton | D68: =Cotizaciones!F35 -> 5 | E68: =+D68*B68*B80 -> 0 | J68: =60*0.24*246 -> 3542.4
A69: Traspile | B69: 0 | C69: U$ / ton | D69: =+Cotizaciones!F36 -> 6.5 | E69: =+D69*B69*B80 -> 0 | J69: =229*246 -> 56334
A70: Analisis | B70: 1 | C70: U$ / ton | D70: =+Cotizaciones!E5/Cotizaciones!M16 -> 0.55913978 | E70: =+D70*B70*$B$80 -> 3.1870968
A71: Flete | B71: 1 | C71: U$ / ton | D71: =+Cotizaciones!F25 -> 20 | E71: =B71*D71*B80 -> 114 | J71: =1.5*246 -> 369
A72: Comisión | J72: =+J71*E76 -> 76147.493
C73: Total Comercialización | E73: =SUM(E65:E72) -> 150.41291 | K73: =86*296 -> 25456
A74: Precio bruto Factor 95 | E74: =+Cotizaciones!B9*0.95 -> 232.75 | K74: =K73/12 -> 2121.3333
A75: Gastos Comerciales/tn | E75: =+E73/B80 -> 26.388231 | F75: =+E75/E74 -> 0.11337586
A76: Precio Neto Estimado | E76: =+E74-E75 -> 206.36177
A77: TRIGO SUELO PROFUNDO
A79: Resultado Estimado Cebada | D79: Cervecera + Soja 2da
A80: Rendimiento Estimado | B80: 5.7 | C80: Ton/Ha. | H80: El silencio | I80: Alea
A81: Precio Neto Estimado | B81: =+E76 -> 206.36177 | C81: Ton | D81: Costo Total | E81: =B82+'Soja 2da. C'!B76 -> 1443.71 | F81: Ha | G81: labores | H81: =+E21+'Soja 2da. C'!E18 -> 209 | I81: 0
A82: Costo Total | B82: =E62 -> 1044.71 | C82: Ha | D82: Ingreso Bruto | E82: =B84+'Soja 2da. C'!B77 -> 1625.1495 | F82: Ha | G82: Alquiler | I82: =+E27+'Soja 2da. C'!E25 -> 426
A83: Costo/tn | B83: =+E62/B80 -> 183.28246 | D83: Margen | E83: =E82-E81 -> 181.43952 | F83: Ha | G83: semilla | H83: =+E25+'Soja 2da. C'!E22 -> 159.6
A84: Ingreso Bruto (2% IB) | B84: =+B81*B80*0.98 -> 1152.7368 | C84: Ha | D84: Retorno | E84: =E83/E81 -> 0.12567587 | G84: fertis | I84: =+E36 -> 236.8
A85: Margen | B85: =+B84-B82 -> 108.02684 | C85: Ha | G85: agroquimicos | H85: =+E51+'Soja 2da. C'!E46 -> 159.31
A86: Retorno | B86: =B85/E62 -> 0.10340367 | D86: Inversión Real | E86: =B88+'Soja 2da. C'!B81 -> 1240.71 | F86: Ha | G86: Gerenciamiento | I86: 50
A87: Rendimiento de Indiferencia | B87: =+E62/E76 -> 5.0625172 | D87: Retorno Real | E87: =E83/E86 -> 0.14623846 | H87: =SUM(H81:H86) -> 527.91 | I87: =SUM(I81:I86) -> 712.8 | J87: =+I87+H87 -> 1240.71
A88: Inversión Real | B88: =+E21+E25+E27+E30+E36+E51 -> 939.71 | C88: Ha | H88: =+H87/J87 -> 0.42549024 | I88: =+I87/J87 -> 0.57450976
A89: Retorno Real | B89: =B85/B88 -> 0.11495764
A90: Rinde Indiferencia | B90: =+E62/B81 -> 5.0625172 | C90: =+B90/B80 -> 0.88816091
A91: Costo Total Sementera | C91: =E62 -> 1044.71
A92: Cebada Cervecera
A93: % Retorno
A94: Px/Rinde | B94: =E94-1.5 -> 4.2 | C94: =E94-1 -> 4.7 | D94: =E94-0.5 -> 5.2 | E94: =B80 -> 5.7 | F94: =E94+0.5 -> 6.2 | G94: =E94+0.8 -> 6.5 | H94: =E94+1.2 -> 6.9
A95: =A96-10 -> 176.36177 | B95: =B104/C91*100 -> -29.098082 | C95: =C104/C91*100 -> -20.657377 | D95: =D104/C91*100 -> -12.216673 | E95: =E104/C91*100 -> -3.775968 | F95: =F104/C91*100 -> 4.6647366 | G95: =G104/C91*100 -> 9.7291593 | H95: =H104/C91*100 -> 16.481723
A96: =A97-10 -> 186.36177 | B96: =B105/C91*100 -> -25.077827 | C96: =C105/C91*100 -> -16.158521 | D96: =D105/C91*100 -> -7.2392147 | E96: =E105/C91*100 -> 1.6800916 | F96: =F105/C91*100 -> 10.599398 | G96: =G105/C91*100 -> 15.950982 | H96: =H105/C91*100 -> 23.086427
A97: =A98-10 -> 196.36177 | B97: =B106/C91*100 -> -21.057573 | C97: =C106/C91*100 -> -11.659665 | D97: =D106/C91*100 -> -2.2617568 | E97: =E106/C91*100 -> 7.1361512 | F97: =F106/C91*100 -> 16.534059 | G97: =G106/C91*100 -> 22.172804 | H97: =H106/C91*100 -> 29.69113
A98: =B81 -> 206.36177 | B98: =B107/C91*100 -> -17.037318 | C98: =C107/C91*100 -> -7.1608087 | D98: =D107/C91*100 -> 2.715701 | E98: =E107/C91*100 -> 12.592211 | F98: =F107/C91*100 -> 22.46872 | G98: =G107/C91*100 -> 28.394626 | H98: =H107/C91*100 -> 36.295834
A99: =A98+10 -> 216.36177 | B99: =B108/C91*100 -> -13.017064 | C99: =C108/C91*100 -> -2.6619525 | D99: =D108/C91*100 -> 7.6931589 | E99: =E108/C91*100 -> 18.04827 | F99: =F108/C91*100 -> 28.403382 | G99: =G108/C91*100 -> 34.616449 | H99: =H108/C91*100 -> 42.900538
A100: =A99+10 -> 226.36177 | B100: =B109/C91*100 -> -8.9968095 | C100: =C109/C91*100 -> 1.8369036 | D100: =D109/C91*100 -> 12.670617 | E100: =E109/C91*100 -> 23.50433 | F100: =F109/C91*100 -> 34.338043 | G100: =G109/C91*100 -> 40.838271 | H100: =H109/C91*100 -> 49.505241
A101: =A100+10 -> 236.36177 | B101: =B110/C91*100 -> -4.9765551 | C101: =C110/C91*100 -> 6.3357598 | D101: =D110/C91*100 -> 17.648075 | E101: =E110/C91*100 -> 28.960389 | F101: =F110/C91*100 -> 40.272704 | G101: =G110/C91*100 -> 47.060093 | H101: =H110/C91*100 -> 56.109945
A102: MB CEBADA SUELOS PROFUNDOS (USD/TON) (s/IB)
A103: Px/Rinde | B103: =E103-1.5 -> 4.2 | C103: =E103-1 -> 4.7 | D103: =E103-0.5 -> 5.2 | E103: =B80 -> 5.7 | F103: =E103+0.5 -> 6.2 | G103: =E103+0.8 -> 6.5 | H103: =E103+1.2 -> 6.9
A104: =A105-10 -> 176.36177 | B104: =(B103*A104)-C91 -> -303.99057 | C104: =(C103*A104)-C91 -> -215.80968 | D104: =(D103*A104)-C91 -> -127.6288 | E104: =(E103*A104)-C91 -> -39.447915 | F104: =(F103*A104)-C91 -> 48.73297 | G104: =(G103*A104)-C91 -> 101.6415 | H104: =(H103*A104)-C91 -> 172.18621
A105: =A106-10 -> 186.36177 | B105: =(B103*A105)-C91 -> -261.99057 | C105: =(C103*A105)-C91 -> -168.80968 | D105: =(D103*A105)-C91 -> -75.6288 | E105: =(E103*A105)-C91 -> 17.552085 | F105: =(F103*A105)-C91 -> 110.73297 | G105: =(G103*A105)-C91 -> 166.6415 | H105: =(H103*A105)-C91 -> 241.18621
A106: =A107-10 -> 196.36177 | B106: =(A106*B103)-C91 -> -219.99057 | C106: =(C103*A106)-C91 -> -121.80968 | D106: =(D103*A106)-C91 -> -23.6288 | E106: =(E103*A106)-C91 -> 74.552085 | F106: =(F103*A106)-C91 -> 172.73297 | G106: =(G103*A106)-C91 -> 231.6415 | H106: =(H103*A106)-C91 -> 310.18621
A107: =B81 -> 206.36177 | B107: =(A107*B103)-C91 -> -177.99057 | C107: =(A107*C103)-C91 -> -74.809684 | D107: =(D103*A107)-C91 -> 28.3712 | E107: =(A107*E103)-C91 -> 131.55209 | F107: =(A107*F103)-C91 -> 234.73297 | G107: =(G103*A107)-C91 -> 296.6415 | H107: =(H103*A107)-C91 -> 379.18621
A108: =A107+10 -> 216.36177 | B108: =(A108*B103)-C91 -> -135.99057 | C108: =(C103*A108)-C91 -> -27.809684 | D108: =(D103*A108)-C91 -> 80.3712 | E108: =(E103*A108)-C91 -> 188.55209 | F108: =(F103*A108)-C91 -> 296.73297 | G108: =(G103*A108)-C91 -> 361.6415 | H108: =(H103*A108)-C91 -> 448.18621
A109: =A108+10 -> 226.36177 | B109: =(A109*B103)-C91 -> -93.990569 | C109: =(C103*A109)-C91 -> 19.190316 | D109: =(D103*A109)-C91 -> 132.3712 | E109: =(E103*A109)-C91 -> 245.55209 | F109: =(F103*A109)-C91 -> 358.73297 | G109: =(G103*A109)-C91 -> 426.6415 | H109: =(H103*A109)-C91 -> 517.18621
...

Sheet Cebada SS 
A1: Proyección Cebada Suelos Someros
A3: HECTAREAS | B3: ='Resumen Proy'!B24 -> 0
B5: CANTIDAD | C5: UNIDAD | D5: PRECIO | E5: TOTAL / HA | F5: % Costo | G5: Inv Real | H5: Mes | J5: MES CASH FLOW
D6: UNITARIO
A7: Labores
A8: Disco,rastra y rolo | B8: 0 | C8: Uni | D8: =Cotizaciones!F8 -> 0 | E8: =B8*D8 -> 0 | H8: Abril | J8: MAYO
A9: Rolo picador | B9: 0 | C9: Uni | D9: =Cotizaciones!F18 -> 17 | E9: =B9*D9 -> 0 | H9: Abril | J9: MAYO
A10: Barbecho Quimico | B10: 1 | C10: Uni | D10: =Cotizaciones!F17 -> 5 | E10: =B10*D10 -> 5 | H10: 41030 | J10: MAYO
A11: Siembra | B11: 1 | C11: Uni | D11: =Cotizaciones!F21 -> 42 | E11: =B11*D11 -> 42 | H11: 41061 | J11: JULIO
A12: Pulverizacion Post-emergente | B12: 1 | C12: Uni | D12: =Cotizaciones!F17 -> 5 | E12: =B12*D12 -> 5 | H12: 1/2 Julio | J12: AGOSTO
A13: Pulverización graminicidas | B13: 0.5 | C13: Uni | D13: =Cotizaciones!F17 -> 5 | E13: =B13*D13 -> 2.5 | H13: 1/2 Julio | J13: AGOSTO
A14: Aplicación Urea | B14: 1 | C14: Uni | D14: =Cotizaciones!F10 -> 0 | E14: =B14*D14 -> 0 | H14: 41091 | I14: 41122 | J14: JULIO
A15: Aplicación Fungicida | B15: 1 | C15: Uni | D15: =Cotizaciones!F17 -> 5 | E15: =B15*D15 -> 5 | H15: 1/2 octubre | J15: NOVIEMBRE
A16: Muestreo de suelos | B16: 0 | C16: Uni | D16: 1 | E16: =B16*D16 -> 0 | H16: 41030 | J16: MAYO
A17: Analisis de suelos | B17: 0 | C17: Uni | D17: 1 | E17: =B17*D17 -> 0 | H17: 41030 | J17: MAYO
A18: Medicion satelital GPS | B18: 0 | C18: Uni | D18: 1 | E18: =B18*D18 -> 0
A19: Limpieza, Curada e Inoculada | B19: 0 | C19: Uni | D19: =Cotizaciones!F12 -> 0 | E19: =B19*D19 -> 0
C20: Total Labores | E20: =SUM(E8:E19) -> 59.5 | F20: =E20/E70 -> 0.071476022 | H20: =E20*$B$3 -> 0
A21: Semilla
A22: Semilla Cebada Curada | B22: 0.12 | C22: Ton | D22: =Cotizaciones!E40 -> 0.52 | E22: =B22*D22 -> 0.0624 | H22: Canje | J22: ENERO
C23: Total Semilla | E23: =SUM(E22:E22) -> 0.0624 | F23: =E23/E70 -> 7.4959727e-05 | H23: =E23*$B$3 -> 0
A25: Arrendamiento | B25: 1 | C25: Uni | D25: =260*0.8 -> 208 | E25: =B25*D25 -> 208
C26: Total Arrendamiento | E26: =E25 -> 208 | F26: =E26/E70 -> 0.24986576 | H26: =E26*$B$3 -> 0
A28: Gerenciamiento | B28: 1 | C28: USD / Ha | D28: =B76*5% -> 61.25 | E28: =D28 -> 61.25
C29: Total Gerenciamiento | E29: =E28 -> 61.25 | F29: =E29/E70 -> 0.073578258 | H29: =E29*$B$3 -> 0
A31: Fertilizantes
A32: Fosforados (en campo) | B32: 0.07 | C32: Ton. | D32: =Cotizaciones!I25+Cotizaciones!F26 -> 1025 | E32: =B32*D32 -> 71.75 | J32: JUNIO
A33: Nitrogenados (en campo) | B33: 0.15 | C33: Ton. | D33: =Cotizaciones!I34+Cotizaciones!F26 -> 645 | E33: =B33*D33 -> 96.75 | J33: JUNIO
C35: Total Fertilizantes | E35: =SUM(E32:E33) -> 168.5 | F35: =E35/E70 -> 0.20241529 | H35: =E35*$B$3 -> 0
A36: Agroquímicos
A37: Curasemillas | B37: 0 | C37: Lts. | D37: =Cotizaciones!I22 -> 80 | E37: =B37*D37 -> 0 | H37: siembra | J37: MAYO
A38: Coadyugante (Lecitina) | B38: 0.3 | C38: Lts. | D38: =Cotizaciones!I21 -> 12 | E38: =B38*D38 -> 3.6 | H38: =A10 -> Barbecho Quimico | J38: MAYO | M38: =+A13 -> Pulverización graminicidas
A39: Aceite Vegetal | B39: 1 | C39: Lts. | D39: =Cotizaciones!I6 -> 3 | E39: =B39*D39 -> 3 | H39: Aplicación Fungicida | J39: MAYO
A40: Glifosato | B40: 3 | C40: Lts. | D40: =Cotizaciones!I28 -> 4.5 | E40: =B40*D40 -> 13.5 | H40: =A10 -> Barbecho Quimico | J40: MAYO
A41: 2,4-D | B41: 0.5 | C41: Lts. | D41: =Cotizaciones!I5 -> 4.6 | E41: =B41*D41 -> 2.3 | H41: =A10 -> Barbecho Quimico | J41: AGOSTO
A42: Axial | B42: 0.3 | C42: Lts. | D42: =Cotizaciones!I11 -> 39 | E42: =B42*D42 -> 11.7 | H42: =+A13 -> Pulverización graminicidas | J42: NOVIEMBRE
A43: Fungicida (orquesta) | B43: 1 | C43: Lts. | D43: =Cotizaciones!I26 -> 28 | E43: =B43*D43 -> 28 | H43: =A15 -> Aplicación Fungicida | J43: AGOSTO
A44: Soprano | B44: 0.6 | C44: Lts. | D44: =Cotizaciones!I46 -> 80 | E44: =B44*D44 -> 48
A45: Peack Pack | B45: 0.05 | C45: Dosis | D45: =Cotizaciones!I38 -> 125 | E45: =B45*D45 -> 6.25 | H45: =A12 -> Pulverizacion Post-emergente | J45: AGOSTO
A46: Dicamba | B46: 0.15 | C46: Lts. | D46: =Cotizaciones!I23 -> 7 | E46: =B46*D46 -> 1.05 | J46: NOVIEMBRE
A47: Clorpirifos | B47: 0.4 | C47: Lts. | D47: =Cotizaciones!I19 -> 7 | E47: =B47*D47 -> 2.8 | H47: =H43 -> Aplicación Fungicida | J47: MAYO
A48: Metsulfuron | B48: 0.004 | C48: Kgs | D48: =Cotizaciones!I37 -> 35 | E48: =B48*D48 -> 0.14 | H48: =H40 -> Barbecho Quimico | J48: MAYO
C49: Total Agroquimicos | E49: =+SUM(E37:E48) -> 120.34 | F49: =E49/E70 -> 0.14456176 | H49: =E49*$B$3 -> 0
A51: Cosecha | B51: 1 | C51: Hás. | D51: 69 | E51: =+D51*B51 -> 69 | H51: 41245
C52: Total Cosecha | E52: =E51 -> 69 | F52: =E52/E70 -> 0.08288816 | H52: =E52*$B$3 -> 0
A53: Comercialización
A54: Extraccion/Embolsado | B54: 0 | C54: U$ / ton | D54: =Cotizaciones!F24 -> 3.3 | E54: =D54*B54*B73 -> 0
A55: Silobolsa | B55: 0 | C55: 180 Tons | D55: =Cotizaciones!I40/180 -> 2.1111111 | E55: =D55*B55*B73 -> 0
A56: Secada | B56: 0 | C56: U$ / ton | D56: =Cotizaciones!F27 -> 3 | E56: =+D56*B56*B73 -> 0
A57: Paritaria | B57: 0.4 | C57: U$ / ton | D57: =Cotizaciones!F35 -> 5 | E57: =+D57*B57*B73 -> 10
A58: Traspile | B58: 0.4 | C58: U$ / ton | D58: =Cotizaciones!F36 -> 6.5 | E58: =+D58*B58*B73 -> 13
A59: Analisis | B59: 0.4 | C59: U$ / ton | D59: =Cotizaciones!F5 -> 0 | E59: =+D59*B59*$B$73 -> 0
A60: Flete | B60: 1 | C60: U$ / ton | D60: =Cotizaciones!F25 -> 20 | E60: =B60*D60*B73 -> 100
A61: Comisión | B61: 0 | C61: % | D61: =B61%*B76 -> 0 | E61: =D61 -> 0
C62: Total Comercialización | E62: =SUM(E54:E61) -> 123 | F62: =E62/E70 -> 0.14775715 | H62: =E62*$B$3 -> 0
A64: Seguro (Granizo) | B64: 4 | C64: % Costo | D64: =B64%*B80 -> 22.7946 | E64: =D64 -> 22.7946 | H64: 40909
C65: Total Seguro | E65: =E64 -> 22.7946 | F65: =E65/E70 -> 0.027382644 | H65: =E65*$B$3 -> 0
A67: Costos Financiero | B67: 0 | C67: % | D67: 0 | E67: =(E20+E23+E35+E49)*D67/100 -> 0
C68: Total Costo Financ. | H68: =E68*$B$3 -> 0
C70: Costo Total | E70: =E20+E23+E26+E29+E35+E49+E52+E62+E65+E68 -> 832.447
A72: CEBADA SUELOS SOMEROS
A73: Rendimiento Estimado | B73: 5 | C73: Ton/Ha. | G73: Forrajera + Soja 2da
A74: Precio Estimado | B74: =Cotizaciones!B9 -> 245 | C74: Ton
A75: Costo Total | B75: =E70 -> 832.447 | C75: Ha | G75: Costo Total | H75: =B75+'Soja 2da. C'!B76 -> 1231.447 | I75: Ha
A76: Ingreso Bruto | B76: =+B74*B73 -> 1225 | C76: Ha | G76: Ingreso Bruto | H76: =B76+'Soja 2da. C'!B77 -> 1697.4127 | I76: Ha
A77: Margen | B77: =+B76-B75 -> 392.553 | C77: Ha | G77: Margen | H77: =H76-H75 -> 465.96567 | I77: Ha
A78: Retorno | B78: =B77/E70 -> 0.47156516 | G78: Retorno | H78: =H77/H75 -> 0.37838874
A79: Rendimiento de Indiferencia | B79: =(E20+E23+E26+E35+E49+E65+E52+E29)/(B74-B61%*B74-D54*B54-D55*B55-D56*B56-D57*B57-D58*B58-D59*B59-D60*B60) -> 3.2189065
A80: Inversión Real | B80: =E20+E26*0.8+E29*0.9+E35+E49 -> 569.865 | C80: Ha | G80: Inversión Real | H80: =B80+'Soja 2da. C'!B81 -> 870.865 | I80: Ha
A81: Retorno Real | B81: =B77/B80 -> 0.68885262 | G81: Retorno Real | H81: =H77/H80 -> 0.53506074
A83: Costo Total Cementera | C83: =E70 -> 832.447
A85: Retorno
A86: Px/Rinde | B86: =E86-1.5 -> 3.5 | C86: =E86-1 -> 4 | D86: =E86-0.5 -> 4.5 | E86: =B73 -> 5 | F86: =E86+0.5 -> 5.5 | G86: =E86+0.8 -> 5.8 | H86: =E86+1.2 -> 6.2
A87: =A88-10 -> 215 | B87: =B96/C83*100 -> -9.6038547 | C87: =C96/C83*100 -> 3.3098804 | D87: =D96/C83*100 -> 16.223615 | E87: =E96/C83*100 -> 29.13735 | F87: =F96/C83*100 -> 42.051086 | G87: =G96/C83*100 -> 49.799327 | H87: =H96/C83*100 -> 60.130315
A88: =A89-10 -> 225 | B88: =B97/C83*100 -> -5.3993828 | C88: =C97/C83*100 -> 8.1149911 | D88: =D97/C83*100 -> 21.629365 | E88: =E97/C83*100 -> 35.143739 | F88: =F97/C83*100 -> 48.658113 | G88: =G97/C83*100 -> 56.766737 | H88: =H97/C83*100 -> 67.578236
A89: =A90-10 -> 235 | B89: =B98/C83*100 -> -1.1949109 | C89: =C98/C83*100 -> 12.920102 | D89: =D98/C83*100 -> 27.035115 | E89: =E98/C83*100 -> 41.150127 | F89: =F98/C83*100 -> 55.26514 | G89: =G98/C83*100 -> 63.734148 | H89: =H98/C83*100 -> 75.026158
A90: =B74 -> 245 | B90: =B99/C83*100 -> 3.009561 | C90: =C99/C83*100 -> 17.725213 | D90: =D99/C83*100 -> 32.440864 | E90: =E99/C83*100 -> 47.156516 | F90: =F99/C83*100 -> 61.872167 | G90: =G99/C83*100 -> 70.701558 | H90: =H99/C83*100 -> 82.474079
A91: =A90+10 -> 255 | B91: =B100/C83*100 -> 7.2140328 | C91: =C100/C83*100 -> 22.530323 | D91: =D100/C83*100 -> 37.846614 | E91: =E100/C83*100 -> 53.162904 | F91: =F100/C83*100 -> 68.479194 | G91: =G100/C83*100 -> 77.668969 | H91: =H100/C83*100 -> 89.922001
A92: =A91+10 -> 265 | B92: =B101/C83*100 -> 11.418505 | C92: =C101/C83*100 -> 27.335434 | D92: =D101/C83*100 -> 43.252363 | E92: =E101/C83*100 -> 59.169292 | F92: =F101/C83*100 -> 75.086222 | G92: =G101/C83*100 -> 84.636379 | H92: =H101/C83*100 -> 97.369923
A93: =A92+10 -> 275 | B93: =B102/C83*100 -> 15.622977 | C93: =C102/C83*100 -> 32.140545 | D93: =D102/C83*100 -> 48.658113 | E93: =E102/C83*100 -> 65.175681 | F93: =F102/C83*100 -> 81.693249 | G93: =G102/C83*100 -> 91.60379 | H93: =H102/C83*100 -> 104.81784
A94: MB CEBADA SUELOS SOMEROS (USD/TON)
A95: Px/Rinde | B95: =E95-1.5 -> 3.5 | C95: =E95-1 -> 4 | D95: =E95-0.5 -> 4.5 | E95: =B73 -> 5 | F95: =E95+0.5 -> 5.5 | G95: =E95+0.8 -> 5.8 | H95: =E95+1.2 -> 6.2
A96: =A97-10 -> 215 | B96: =(B95*A96)-C83 -> -79.947 | C96: =(C95*A96)-C83 -> 27.553 | D96: =(D95*A96)-C83 -> 135.053 | E96: =(E95*A96)-C83 -> 242.553 | F96: =(F95*A96)-C83 -> 350.053 | G96: =(G95*A96)-C83 -> 414.553 | H96: =(H95*A96)-C83 -> 500.553
A97: =A98-10 -> 225 | B97: =(B95*A97)-C83 -> -44.947 | C97: =(C95*A97)-C83 -> 67.553 | D97: =(D95*A97)-C83 -> 180.053 | E97: =(E95*A97)-C83 -> 292.553 | F97: =(F95*A97)-C83 -> 405.053 | G97: =(G95*A97)-C83 -> 472.553 | H97: =(H95*A97)-C83 -> 562.553
A98: =A99-10 -> 235 | B98: =(A98*B95)-C83 -> -9.947 | C98: =(C95*A98)-C83 -> 107.553 | D98: =(D95*A98)-C83 -> 225.053 | E98: =(E95*A98)-C83 -> 342.553 | F98: =(F95*A98)-C83 -> 460.053 | G98: =(G95*A98)-C83 -> 530.553 | H98: =(H95*A98)-C83 -> 624.553
A99: =B74 -> 245 | B99: =(A99*B95)-C83 -> 25.053 | C99: =(A99*C95)-C83 -> 147.553 | D99: =(D95*A99)-C83 -> 270.053 | E99: =(A99*E95)-C83 -> 392.553 | F99: =(A99*F95)-C83 -> 515.053 | G99: =(G95*A99)-C83 -> 588.553 | H99: =(H95*A99)-C83 -> 686.553
A100: =A99+10 -> 255 | B100: =(A100*B95)-C83 -> 60.053 | C100: =(C95*A100)-C83 -> 187.553 | D100: =(D95*A100)-C83 -> 315.053 | E100: =(E95*A100)-C83 -> 442.553 | F100: =(F95*A100)-C83 -> 570.053 | G100: =(G95*A100)-C83 -> 646.553 | H100: =(H95*A100)-C83 -> 748.553
A101: =A100+10 -> 265 | B101: =(A101*B95)-C83 -> 95.053 | C101: =(C95*A101)-C83 -> 227.553 | D101: =(D95*A101)-C83 -> 360.053 | E101: =(E95*A101)-C83 -> 492.553 | F101: =(F95*A101)-C83 -> 625.053 | G101: =(G95*A101)-C83 -> 704.553 | H101: =(H95*A101)-C83 -> 810.553
A102: =A101+10 -> 275 | B102: =(B95*A102)-C83 -> 130.053 | C102: =(C95*A102)-C83 -> 267.553 | D102: =(D95*A102)-C83 -> 405.053 | E102: =(E95*A102)-C83 -> 542.553 | F102: =(F95*A102)-C83 -> 680.053 | G102: =(G95*A102)-C83 -> 762.553 | H102: =(A102*H95)-C83 -> 872.553

Sheet Soja 2da. C
A1: Proyección Soja 2da Cebada
A3: HECTAREAS | B3: =+'Cebada SP'!B3 -> 0
D5: UNITARIO | J5: MES CASH FLOW
A6: Labores
A7: Disco,rastra y rolo | B7: 0 | C7: Uni | D7: =Cotizaciones!F8 -> 0 | E7: =B7*D7 -> 0
A8: Rolo picador | B8: 0 | C8: Uni | D8: =Cotizaciones!F18 -> 17 | E8: =B8*D8 -> 0
A9: Barbecho Quimico | B9: 0 | C9: Uni | D9: 6.5 | E9: =B9*D9 -> 0
A10: Siembra Directa | B10: 1 | C10: Uni | D10: 55 | E10: =B10*D10 -> 55 | H10: 41245 | J10: ENERO
A11: Pulverizacion Herbicida | B11: 1 | C11: Uni | D11: 6.5 | E11: =B11*D11 -> 6.5 | H11: 40909 | I11: 40940 | J11: ENERO
A12: Pulverizacion Herbicida | B12: 1 | C12: Uni | D12: 6.5 | E12: =B12*D12 -> 6.5 | J12: MARZO
A13: Aplicación terrestre Insecticida | B13: 1 | C13: Uni | D13: 6.5 | E13: =B13*D13 -> 6.5 | H13: 40941 | J13: MARZO
A14: Muestreo de suelos | B14: 0 | C14: Uni | D14: 0 | E14: =B14*D14 -> 0
A15: Analisis de suelos | B15: 0 | C15: Uni | D15: =Cotizaciones!F5 -> 0 | E15: =B15*D15 -> 0
A16: Medicion satelital GPS | B16: 0 | C16: Uni | D16: =Cotizaciones!F13 -> 0 | E16: =B16*D16 -> 0
A17: Limpieza, Curada e Inoculada | B17: 0 | C17: Uni | D17: 0 | E17: =(B20*D17)/1000 -> 0 | H17: 41244 | J17: ENERO
C18: Total Labores | E18: =SUM(E7:E17) -> 74.5 | F18: =E18/E57 -> 0.18671679 | G18: =E18*B3 -> 0
A19: Semilla
A20: Semilla de Soja | B20: 90 | C20: Kgs. | D20: =+Cotizaciones!E45/40 -> 0.875 | E20: =B20*D20 -> 78.75
A21: Flete | D21: =+'Cebada SP'!D35 -> 35 | E21: =+D21*B20/1000 -> 3.15 | H21: 41215 | J21: ENERO
C22: Total Semilla | E22: =SUM(E20:E21) -> 81.9 | F22: =E22/E57 -> 0.20526316 | G22: =E22*B3 -> 0
A24: Arrendamiento | B24: 0.2 | C24: Uni | D24: =+'Resumen Proy'!C57 -> 426 | E24: =B24*D24 -> 85.2
C25: Total Arrendamiento | E25: =E24 -> 85.2 | F25: =E25/E57 -> 0.21353383
A27: Gerenciamiento | B27: 10 | C27: USD / Ha | D27: =B27 -> 10 | E27: =D27 -> 10
C28: Total Gerenciamiento | E28: =E27 -> 10
A30: Fertilizantes
A31: Fosforados ( puesto en el campo ) | B31: 0 | C31: Ton. | D31: 0 | E31: =B31*D31 -> 0
A32: Arrancador Azufrado | B32: 0 | C32: Ton. | D32: 0 | E32: =B32*D32 -> 0
A33: Flete
C34: Total Fertilizantes | E34: =SUM(E31:E32) -> 0 | G34: =E34*B3 -> 0
A35: Agroquímicos
A36: Aceite | B36: 1 | C36: Lts. | D36: =Cotizaciones!I6 -> 3 | E36: =B36*D36 -> 3 | H36: =A13 -> Aplicación terrestre Insecticida | J36: ENERO/MARZO
A37: Fomesafen | B37: 0 | C37: Lts. | D37: =+Cotizaciones!I51 -> 7.2 | E37: =B37*D37 -> 0 | H37: =A11 -> Pulverizacion Herbicida | J37: ENERO/MARZO
A38: Sulfentrazone | B38: 0.3 | C38: Lts. | D38: =+Cotizaciones!I52 -> 19 | E38: =B38*D38 -> 5.7 | H38: =H37 -> Pulverizacion Herbicida | J38: ENERO/MARZO
A39: Inoculante | B39: =B20/3000 -> 0.03 | C39: Pack 3 Ton | D39: =Cotizaciones!I29 -> 250 | E39: =(D39*B39) -> 7.5 | H39: =A10 -> Siembra Directa | J39: ENERO
A40: Glifosato | B40: 4 | C40: Lts. | D40: =Cotizaciones!I28 -> 4.5 | E40: =B40*D40 -> 18 | H40: =H37 -> Pulverizacion Herbicida | J40: ENERO/MARZO
A41: 2,4-D | B41: 2 | C41: Lts. | D41: =Cotizaciones!I5 -> 4.6 | E41: =B41*D41 -> 9.2
A42: Clorimuron | B42: 0 | C42: Lts. | D42: =Cotizaciones!I18 -> 22.05 | E42: =B42*D42 -> 0
A43: Lambda | B43: 0.05 | C43: Lts. | D43: =Cotizaciones!I15 -> 20 | E43: =B43*D43 -> 1 | H43: =H36 -> Aplicación terrestre Insecticida | J43: MARZO
A44: Clorpirifos | B44: 0 | C44: Lts. | D44: =Cotizaciones!I19 -> 7 | E44: =B44*D44 -> 0 | H44: =H36 -> Aplicación terrestre Insecticida | J44: MARZO
A45: Coragen | B45: 0.05 | C45: Lts. | D45: =Cotizaciones!I30 -> 100 | E45: =B45*D45 -> 5 | J45: MARZO
C46: Total Agroquimicos | E46: =SUM(E36:E45) -> 49.4 | F46: =E46/E57 -> 0.12380952 | G46: =E46*B3 -> 0
A48: Cosecha | B48: 1 | C48: Hás. | D48: 90 | E48: =+D48*B48 -> 90 | H48: 41031
E49: =E48 -> 90 | F49: =E49/E57 -> 0.22556391 | G49: =E49*B3 -> 0
A51: Seguro (Granizo) | B51: 2.5 | C51: % Costo | D51: 8 | E51: =D51 -> 8
C52: Total Seguro | E52: =E51 -> 8 | F52: =E52/E57 -> 0.020050125 | G52: =E52*B3 -> 0
A54: Costos Financiero | B54: 0 | C54: % | D54: 0 | E54: =(E46+E34+E25+E18)*D54/100 -> 0
C55: Total Costo Financ.
C57: Costo Total | E57: =E18+E22+E25+E28+E34+E46+E49+E52+E55 -> 399 | F57: =F52+F68+F49+F46+F22+F18+F25 -> 0.97493734 | G57: =+E57*B3 -> 0
A59: Comercialización
A60: Extraccion/Embolsado | B60: 0 | C60: U$ / ton | D60: =Cotizaciones!F24 -> 3.3 | E60: =D60*B60*B74 -> 0
A61: Silobolsa | B61: 0 | C61: 210 Tons | D61: =Cotizaciones!I41/210 -> 1.952381 | E61: =D61*B61*B74 -> 0
A62: Secada | B62: 0.5 | C62: U$ / ton | D62: =Cotizaciones!F33 -> 3 | E62: =+D62*B62*$B$74 -> 2.25
A63: Paritaria | B63: 0.7 | C63: U$ / ton | D63: =Cotizaciones!F35 -> 5 | E63: =+D63*B63*$B$74 -> 5.25
A64: Traspile | B64: 0.7 | C64: U$ / ton | D64: =+Cotizaciones!F36 -> 6.5 | E64: =+D64*B64*$B$74 -> 6.825
A65: Analisis | B65: 1 | C65: U$ / ton | D65: =+Cotizaciones!E5/Cotizaciones!M20 -> 0.53083473 | E65: =+D65*B65*$B$74 -> 0.79625209
A66: Flete | B66: 1 | C66: U$ / ton | D66: =+'Cebada SP'!D71 -> 20 | E66: =+D66*B66*$B$74 -> 30
A67: Comisión | B67: 1 | C67: % | D67: =B67%*B74*Cotizaciones!B14 -> 5.325 | E67: =D67 -> 5.325
C68: Total Comercialización | E68: =SUM(E60:E67) -> 50.446252
A70: Precio bruto | E70: =+Cotizaciones!B14 -> 355
A71: Gastos Comerciales/tn | E71: =+E68/B74 -> 33.630835 | F71: =+E71/E70 -> 0.094734746
A72: Precio Neto Estimado | E72: =+E70-E71 -> 321.36917
A73: Soja de segunda sobre Cebada
A74: Rendimiento Estimado | B74: 1.5 | C74: Ton/Ha. | D74: MB Ceb/soja | G74: El silencio | H74: Alea
A75: Precio Neto Estimado | B75: =+E72 -> 321.36917 | C75: Ton. | F75: labores | G75: =+E18 -> 74.5 | H75: 0
A76: Costo Total | B76: =+E57 -> 399 | C76: Ton | D76: =+B76+'Cebada SP'!B82 -> 1443.71 | F76: Alquiler | H76: =+E25 -> 85.2
A77: Ingreso Bruto (2% IB) | B77: =+B75*B74*0.98 -> 472.41267 | C77: Ha | D77: =+B77+'Cebada SP'!B84 -> 1625.1495 | F77: semilla | G77: =+E22 -> 81.9
A78: Margen | B78: =+B77-E57 -> 73.412673 | C78: Ha | D78: =+D77-D76 -> 181.43952 | F78: fertis | H78: =+D30 -> 0
A79: Retorno | B79: =B78/E57 -> 0.18399166 | D79: =+D78/D76 -> 0.12567587 | F79: agroquimicos | G79: =+E46 -> 49.4
A80: Rendimiento de Indiferencia | B80: =+E57/B75 -> 1.2415628 | F80: Gerenciamiento | H80: =+B27 -> 10
A81: Inversión Real | B81: =+E18+E22+E25+E28+E34+E46 -> 301 | D81: =+B81+'Cebada SP'!B88 -> 1240.71 | G81: =SUM(G75:G80) -> 205.8 | H81: =SUM(H75:H80) -> 95.2 | I81: =+H81+G81 -> 301
A82: Retorno Real | B82: =B78/B81 -> 0.24389592 | D82: =+D78/D81 -> 0.14623846 | G82: =+G81/I81 -> 0.68372093 | H82: =+H81/I81 -> 0.31627907
A84: Costo Total | C84: =E57 -> 399
A85: Retorno (%)
A86: Px/Rinde | B86: =B95 -> 0.6 | C86: =C95 -> 0.9 | D86: =D95 -> 1.2 | E86: =E95 -> 1.5 | F86: =F95 -> 1.8 | G86: =G95 -> 2.1 | H86: =H95 -> 2.4
A87: =A88-10 -> 291.36917 | B87: =B96/C84*100 -> -56.185088 | C87: =C96/C84*100 -> -34.277632 | D87: =D96/C84*100 -> -12.370176 | E87: =E96/C84*100 -> 9.5372802 | F87: =F96/C84*100 -> 31.444736 | G87: =G96/C84*100 -> 53.352192 | H87: =H96/C84*100 -> 75.259648
A88: =A89-10 -> 301.36917 | B88: =B97/C84*100 -> -54.681329 | C88: =C97/C84*100 -> -32.021993 | D88: =D97/C84*100 -> -9.3626571 | E88: =E97/C84*100 -> 13.296679 | F88: =F97/C84*100 -> 35.956014 | G88: =G97/C84*100 -> 58.61535 | H88: =H97/C84*100 -> 81.274686
A89: =A90-10 -> 311.36917 | B89: =B98/C84*100 -> -53.177569 | C89: =C98/C84*100 -> -29.766354 | D89: =D98/C84*100 -> -6.3551383 | E89: =E98/C84*100 -> 17.056077 | F89: =F98/C84*100 -> 40.467293 | G89: =G98/C84*100 -> 63.878508 | H89: =H98/C84*100 -> 87.289723
A90: =B75 -> 321.36917 | B90: =B99/C84*100 -> -51.67381 | C90: =C99/C84*100 -> -27.510715 | D90: =D99/C84*100 -> -3.3476195 | E90: =E99/C84*100 -> 20.815476 | F90: =F99/C84*100 -> 44.978571 | G90: =G99/C84*100 -> 69.141666 | H90: =H99/C84*100 -> 93.304761
A91: =A90+10 -> 331.36917 | B91: =B100/C84*100 -> -50.17005 | C91: =C100/C84*100 -> -25.255076 | D91: =D100/C84*100 -> -0.34010067 | E91: =E100/C84*100 -> 24.574874 | F91: =F100/C84*100 -> 49.489849 | G91: =G100/C84*100 -> 74.404824 | H91: =H100/C84*100 -> 99.319799
A92: =A91+10 -> 341.36917 | B92: =B101/C84*100 -> -48.666291 | C92: =C101/C84*100 -> -22.999436 | D92: =D101/C84*100 -> 2.6674181 | E92: =E101/C84*100 -> 28.334273 | F92: =F101/C84*100 -> 54.001127 | G92: =G101/C84*100 -> 79.667982 | H92: =H101/C84*100 -> 105.33484
A93: =A92+10 -> 351.36917 | B93: =B102/C84*100 -> -47.162532 | C93: =C102/C84*100 -> -20.743797 | D93: =D102/C84*100 -> 5.6749369 | E93: =E102/C84*100 -> 32.093671 | F93: =F102/C84*100 -> 58.512405 | G93: =G102/C84*100 -> 84.93114 | H93: =H102/C84*100 -> 111.34987
A94: MB SOJA SEGUNDA (USD / TON)
A95: Px/Rinde | B95: =C95-0.3 -> 0.6 | C95: =D95-0.3 -> 0.9 | D95: =E95-0.3 -> 1.2 | E95: =B74 -> 1.5 | F95: =E95+0.3 -> 1.8 | G95: =F95+0.3 -> 2.1 | H95: =G95+0.3 -> 2.4
A96: =A97-10 -> 291.36917 | B96: =(B95*A96)-C84 -> -224.1785 | C96: =(C95*A96)-C84 -> -136.76775 | D96: =(D95*A96)-C84 -> -49.357002 | E96: =(E95*A96)-C84 -> 38.053748 | F96: =(F95*A96)-C84 -> 125.4645 | G96: =(G95*A96)-C84 -> 212.87525 | H96: =(H95*A96)-C84 -> 300.286
A97: =A98-10 -> 301.36917 | B97: =(B95*A97)-C84 -> -218.1785 | C97: =(C95*A97)-C84 -> -127.76775 | D97: =(D95*A97)-C84 -> -37.357002 | E97: =(E95*A97)-C84 -> 53.053748 | F97: =(F95*A97)-C84 -> 143.4645 | G97: =(G95*A97)-C84 -> 233.87525 | H97: =(H95*A97)-C84 -> 324.286
A98: =A99-10 -> 311.36917 | B98: =(A98*B95)-C84 -> -212.1785 | C98: =(C95*A98)-C84 -> -118.76775 | D98: =(D95*A98)-C84 -> -25.357002 | E98: =(E95*A98)-C84 -> 68.053748 | F98: =(F95*A98)-C84 -> 161.4645 | G98: =(G95*A98)-C84 -> 254.87525 | H98: =(H95*A98)-C84 -> 348.286
A99: =B75 -> 321.36917 | B99: =(A99*B95)-C84 -> -206.1785 | C99: =(A99*C95)-C84 -> -109.76775 | D99: =(D95*A99)-C84 -> -13.357002 | E99: =(A99*E95)-C84 -> 83.053748 | F99: =(A99*F95)-C84 -> 179.4645 | G99: =(G95*A99)-C84 -> 275.87525 | H99: =(H95*A99)-C84 -> 372.286
A100: =A99+10 -> 331.36917 | B100: =(A100*B95)-C84 -> -200.1785 | C100: =(C95*A100)-C84 -> -100.76775 | D100: =(D95*A100)-C84 -> -1.3570017 | E100: =(E95*A100)-C84 -> 98.053748 | F100: =(F95*A100)-C84 -> 197.4645 | G100: =(G95*A100)-C84 -> 296.87525 | H100: =(H95*A100)-C84 -> 396.286
A101: =A100+10 -> 341.36917 | B101: =(A101*B95)-C84 -> -194.1785 | C101: =(C95*A101)-C84 -> -91.767751 | D101: =(D95*A101)-C84 -> 10.642998 | E101: =(E95*A101)-C84 -> 113.05375 | F101: =(F95*A101)-C84 -> 215.4645 | G101: =(G95*A101)-C84 -> 317.87525 | H101: =(H95*A101)-C84 -> 420.286
A102: =A101+10 -> 351.36917 | B102: =(B95*A102)-C84 -> -188.1785 | C102: =(C95*A102)-C84 -> -82.767751 | D102: =(D95*A102)-C84 -> 22.642998 | E102: =(E95*A102)-C84 -> 128.05375 | F102: =(F95*A102)-C84 -> 233.4645 | G102: =(G95*A102)-C84 -> 338.87525 | H102: =(A102*H95)-C84 -> 444.286

Sheet Trigo SP
A1: Proyección Trigo Suelos Profundos
A3: HECTAREAS | B3: 0
B5: CANTIDAD | C5: UNIDAD | D5: PRECIO | E5: TOTAL / HA | G5: Total
D6: UNITARIO | J6: MES CASH FLOW
A7: Labores
A8: Disco,rastra y rolo | B8: 0 | C8: Uni | D8: =+'Cebada SP'!D8 -> 29.014943 | E8: =B8*D8 -> 0 | J8: MAYO
A9: Rolo picador | B9: 1 | C9: Uni | D9: 23 | E9: =B9*D9 -> 23 | J9: MAYO
A10: Barbecho Quimico | B10: 2 | C10: Uni | D10: 6.5 | E10: =B10*D10 -> 13 | G10: 41030 | J10: MAYO
A11: Siembra | B11: 1 | C11: Uni | D11: 55 | E11: =B11*D11 -> 55 | G11: 2 mayo, 1 jun | J11: JUNIO
A12: Pulverizacion Post-emergente | B12: 1 | C12: Uni | D12: 6.5 | E12: =B12*D12 -> 6.5 | G12: 41091 | J12: AGOSTO
A13: Pulverización graminicidas | B13: 0 | C13: Uni | D13: 6.5 | E13: =B13*D13 -> 0 | G13: 41091 | J13: AGOSTO
A14: Aplicación Urea | B14: 2 | C14: Uni | D14: 11 | E14: =B14*D14 -> 22 | G14: 41061 | H14: 41122 | J14: JULIO/SEPTIEMBRE
A15: Aplicación terrestre Fungicida/Insecticida | B15: 2 | C15: Uni | D15: 6.5 | E15: =B15*D15 -> 13 | G15: 41184 | J15: DICIEMBRE
A16: Muestreo de suelos | B16: 1 | C16: Uni | D16: 0 | E16: =B16*D16 -> 0 | G16: =+G10 -> 41030 | J16: MAYO
A17: Analisis de suelos | B17: 1 | C17: Uni | D17: 1 | E17: =B17*D17 -> 1 | G17: =+G10 -> 41030 | J17: MAYO
A18: Medicion satelital GPS | B18: 0 | C18: Uni | D18: 0 | E18: =B18*D18 -> 0
A19: Limpieza, Curada e Inoculada | B19: 0 | C19: Uni | D19: =+'Cebada SP'!D20 -> 0 | E19: =B19*D19 -> 0 | J19: MAYO
C20: Total Labores | E20: =SUM(E8:E19) -> 133.5 | F20: =E20/E60 -> 0.13001938 | G20: =E20*D1 -> 0 | I20: =+E20*B3 -> 0
A21: Semilla
A22: Semilla de trigo curada | B22: 140 | C22: Kgs. | D22: =Cotizaciones!E47 -> 0.525 | E22: =B22*D22 -> 73.5 | G22: =+A11 -> Siembra
A23: Flete | D23: =+D35 -> 35 | E23: =+D23*B22/1000 -> 4.9 | J23: JULIO
C24: Total Semilla | E24: =SUM(E22:E23) -> 78.4 | F24: =E24/E60 -> 0.076355951 | G24: =E24*D1 -> 0 | H24: =+E24*B3 -> 0 | I24: =+E24*B3 -> 0
A26: Arrendamiento | B26: 0.8 | C26: Uni | D26: =+'Resumen Proy'!C57 -> 426 | E26: =B26*D26 -> 340.8
C27: Total Arrendamiento | E27: =E26 -> 340.8 | F27: =E27/E60 -> 0.33191464 | G27: =E27*D1 -> 0 | I27: =+'[2]Alquileres por campo'!$S$56 -> 19501.65
A29: Gerenciamiento | B29: 30 | C29: USD / Ha | D29: =B29 -> 30 | E29: =D29 -> 30
C30: Total Gerenciamiento | E30: =E29 -> 30 | F30: =E30/E60 -> 0.029217838 | G30: =E30*D1 -> 0
A32: Fertilizantes
A33: Fosforados | B33: 0.08 | C33: Ton. | D33: =+Cotizaciones!I25 -> 990 | E33: =B33*D33 -> 79.2 | G33: =+G22 -> Siembra | I33: =+E33*B3 -> 0 | J33: DICIEMBRE
A34: Nitrogenados | B34: 0.22 | C34: Ton. | D34: =Cotizaciones!I34 -> 610 | E34: =B34*D34 -> 134.2 | G34: =+G14 -> 41061 | H34: =+H14 -> 41122 | I34: =+E34*B3 -> 0 | J34: ENERO
A35: Flete | B35: =+B34+B33 -> 0.3 | D35: =+'Cebada SP'!D35 -> 35 | E35: =+D35*B35 -> 10.5
C36: Total Fertilizantes | E36: =+E35+E34+E33 -> 223.9 | F36: =E36/E60 -> 0.21806247 | G36: =E36*D1 -> 0 | H36: =+E36*B3 -> 0
A37: Agroquímicos
A38: Paraquat | B38: 2 | C38: Lts. | D38: =+Cotizaciones!I45 -> 2.6 | E38: =B38*D38 -> 5.2 | G38: =+G33 -> Siembra | J38: MAYO
A39: Piroxasulfone | B39: 0.12 | C39: Lts. | D39: =+Cotizaciones!I50 -> 80 | E39: =B39*D39 -> 9.6 | G39: =+A10 -> Barbecho Quimico | I39: =+A12 -> Pulverizacion Post-emergente | J39: MAYO
A40: Sulfosato | B40: 2 | C40: Lts. | D40: =+Cotizaciones!I43 -> 4.5 | E40: =B40*D40 -> 9 | G40: =+A10 -> Barbecho Quimico | J40: NOVIEMBRE
A41: 2,4-D | B41: 1.2 | C41: Lts. | D41: =Cotizaciones!I5 -> 4.6 | E41: =B41*D41 -> 5.52 | G41: =+G40 -> Barbecho Quimico | J41: NOVIEMBRE
A42: Picloran | B42: 0 | C42: Lts. | D42: =Cotizaciones!I36 -> 7 | E42: =B42*D42 -> 0 | J42: NOVIEMBRE
A43: batalium | B43: 0.5 | C43: Lts. | D43: 47 | E43: =B43*D43 -> 23.5 | G43: =+A13 -> Pulverización graminicidas | J43: ENERO
A44: Fungicida (Opera) | B44: 1.3 | C44: Lts. | D44: =Cotizaciones!I26 -> 28 | E44: =D44*B44 -> 36.4 | G44: =+A15 -> Aplicación terrestre Fungicida/Insecticida | J44: NOVIEMBRE
A45: Metsulfurón | B45: 0.05 | C45: Kg. | D45: =Cotizaciones!I37 -> 35 | E45: =B45*D45 -> 1.75 | G45: =+G39 -> Barbecho Quimico | J45: MAYO
A46: Flurocloridona | B46: 1 | C46: Kg. | D46: =+Cotizaciones!I24 -> 11.8 | E46: =B46*D46 -> 11.8 | J46: NOVIEMBRE
A47: CLETODIM | B47: 1 | C47: Lts. | D47: =+Cotizaciones!I27 -> 6 | E47: =B47*D47 -> 6 | G47: =+I39 -> Pulverizacion Post-emergente | J47: ENERO
A48: Affinity | B48: 0.08 | C48: Lts. | D48: =+Cotizaciones!I46 -> 80 | E48: =B48*D48 -> 6.4
A49: MCPA | B49: 0 | C49: Lts. | D49: =+Cotizaciones!I32 -> 11 | E49: =B49*D49 -> 0 | G49: =+G44 -> Aplicación terrestre Fungicida/Insecticida | J49: AGOSTO
C50: Total Agroquimicos | E50: =SUM(E38:E49) -> 115.17 | F50: =E50/E60 -> 0.11216728 | G50: =+E50*B3 -> 0
A52: Cosecha | B52: 1 | C52: Hás. | D52: 85 | E52: =+D52*B52 -> 85
C53: Total Cosecha | E53: =E52 -> 85 | F53: =E53/E60 -> 0.082783876 | G53: =+E53*B3 -> 0
A54: Seguro (Granizo) | B54: 2 | C54: % Costo | D54: 20 | E54: =D54 -> 20
C55: Total Seguro | E55: =+E54 -> 20 | F55: =E55/E60 -> 0.019478559 | G55: =+E55*B3 -> 0
A57: Costos Financiero | B57: 0 | C57: % | D57: 0 | E57: 0
C58: Total Costo Financ. | E58: =E57 -> 0 | F58: =E58/E60 -> 0
C60: Costo Total | E60: =E20+E24+E27+E30+E36+E50+E53+E55+E58 -> 1026.77 | F60: =F58+F55+F70+F53+F50+F36+F30+F27+F24+F20 -> 1 | G60: =+E60*B3 -> 0
A61: Comercialización
A62: Extraccion/Embolsado | B62: 1.4 | C62: U$ / ton | D62: =+Cotizaciones!F24 -> 3.3 | E62: =D62*B62*B75 -> 26.334 | I62: Alea/ha | J62: Total | K62: Socio | L62: Total | M62: Total/ha
A63: Silobolsa | B63: 0.7 | C63: 180 Tons | D63: =Cotizaciones!I40/180 -> 2.1111111 | E63: =D63*B63*B75 -> 8.4233333 | H63: =+A7 -> Labores | I63: 0 | J63: =+I63*B$3 -> 0 | K63: =+E20 -> 133.5 | L63: =+K63*B$3 -> 0 | M63: =+K63+I63 -> 133.5
A64: Secada | B64: 0 | C64: $ / ton | D64: =Cotizaciones!F28 -> 3 | E64: =+D64*B64*B75 -> 0 | H64: =+A21 -> Semilla | I64: =+E24 -> 78.4 | J64: =+I64*B$3 -> 0 | L64: =+K64*B$3 -> 0 | M64: =+K64+I64 -> 78.4
A65: Paritaria | B65: 0 | C65: $ / ton | D65: =Cotizaciones!F35 -> 5 | E65: =+D65*B65*B75 -> 0 | H65: =+A26 -> Arrendamiento | I65: =+E27 -> 340.8 | J65: =+I65*B$3 -> 0 | L65: =+K65*B$3 -> 0 | M65: =+K65+I65 -> 340.8
A66: Traspile | B66: 0 | C66: $ / ton | D66: =+Cotizaciones!F36 -> 6.5 | E66: =+D66*B66*B75 -> 0 | H66: =+A29 -> Gerenciamiento | I66: =+B29 -> 30 | J66: =+I66*B$3 -> 0 | K66: 0 | L66: =+K66*B$3 -> 0 | M66: =+K66+I66 -> 30
A67: Analisis | B67: 1 | C67: $ / ton | D67: =+Cotizaciones!E5/Cotizaciones!M16 -> 0.55913978 | E67: =+D67*B67*$B$75 -> 3.1870968 | H67: =+A32 -> Fertilizantes | I67: =+E36 -> 223.9 | J67: =+I67*B$3 -> 0 | L67: =+K67*B$3 -> 0 | M67: =+K67+I67 -> 223.9
A68: Flete | B68: 1 | C68: $ / ton | D68: =+'Cebada SP'!D71 -> 20 | E68: =B68*D68*B75 -> 114 | H68: =+A37 -> Agroquímicos | J68: =+I68*B$3 -> 0 | K68: =+E50 -> 115.17 | L68: =+K68*B$3 -> 0 | M68: =+K68+I68 -> 115.17
A69: Comisión | B69: 1 | C69: % | D69: =B69%*B75*Cotizaciones!B15 -> 13.11 | E69: =B75*Cotizaciones!B15*B69% -> 13.11 | J69: =+I69*B$3 -> 0 | L69: =+K69*B$3 -> 0
C70: Total Comercialización | E70: =SUM(E62:E69) -> 165.05443 | G70: =+E70*B3 -> 0 | H70: Total | I70: =SUM(I63:I69) -> 673.1 | J70: =+I70*B$3 -> 0 | K70: =SUM(K63:K68) -> 248.67 | L70: =+K70*B$3 -> 0 | M70: =+K70+I70 -> 921.77
A71: Precio bruto | E71: =+Cotizaciones!B15 -> 230 | I71: =+I70/M70 -> 0.73022554 | K71: =+K70/M70 -> 0.26977446
A72: Gastos Comerciales/tn | E72: =+E70/B75 -> 28.956918 | F72: =+E72/E71 -> 0.12589964
A73: Precio Neto Estimado | E73: =+E71-E72 -> 201.04308
A74: TRIGO SUELO PROFUNDO
A75: Rendimiento Estimado | B75: 5.7 | C75: Ton/Ha.
A76: Precio Neto Estimado | B76: =+E73 -> 201.04308 | C76: Ton
A77: Costo Total | B77: =E60 -> 1026.77 | C77: Ha
A78: Costo/tn | B78: =+B77/B75 -> 180.13509 | F78: trigo + Soja 2da
A79: Ingreso (2% IIB) | B79: =+B76*B75*0.98 -> 1123.0267 | C79: Ha
A80: Margen | B80: =+B79-B77 -> 96.256658 | C80: Ha | F80: Costo Total | G80: =+'Soja 2da. C'!B76+B77 -> 1425.77 | H80: Ha
A81: Retorno | B81: =B80/B77 -> 0.09374705 | F81: Ingreso Bruto | G81: =+B79+'Soja 2da. T'!B76 -> 1537.3616 | H81: Ha
A82: Rendimiento de Indiferencia | B82: =+B77/E73 -> 5.1072138 | D82: =+B82*B76 -> 1026.77 | F82: Margen | G82: =G81-G80 -> 111.59157 | H82: Ha
A83: Inversión Real | B83: =+E20+E24+E27+E30+E36+E50 -> 921.77 | C83: Ha | F83: Retorno | G83: =G82/G80 -> 0.078267584
A84: Retorno Real | B84: =B80/B83 -> 0.1044259 | C84: =+B82/B75 -> 0.89600242
F85: Inversión Real | G85: =+B83+'Soja 2da. T'!B80 -> 1218.42 | H85: Ha
A86: Costo Total | C86: =E60 -> 1026.77 | F86: Retorno Real | G86: =G82/G85 -> 0.091587116
A87: RENTABILIDAD TRIGO SUELOS PROFUNDOS (%)
A88: Px/Rinde | B88: =E88-1.5 -> 4.2 | C88: =E88-1 -> 4.7 | D88: =E88-0.5 -> 5.2 | E88: =B75 -> 5.7 | F88: =E88+0.5 -> 6.2 | G88: =E88+0.8 -> 6.5 | H88: =E88+1.2 -> 6.9
A89: =A90-10 -> 171.04308 | B89: =B98/C86*100 -> -30.034872 | C89: =C98/C86*100 -> -21.70569 | D89: =D98/C86*100 -> -13.376508 | E89: =E98/C86*100 -> -5.0473261 | F89: =F98/C86*100 -> 3.2818558 | G89: =G98/C86*100 -> 8.279365 | H89: =H98/C86*100 -> 14.942711
A90: =A91-10 -> 181.04308 | B90: =B99/C86*100 -> -25.944374 | C90: =C99/C86*100 -> -17.128229 | D90: =D99/C86*100 -> -8.3120827 | E90: =E99/C86*100 -> 0.50406322 | F90: =F99/C86*100 -> 9.3202091 | G90: =G99/C86*100 -> 14.609897 | H90: =H99/C86*100 -> 21.662813
A91: =A92-10 -> 191.04308 | B91: =B100/C86*100 -> -21.853877 | C91: =C100/C86*100 -> -12.550767 | D91: =D100/C86*100 -> -3.2476573 | E91: =E100/C86*100 -> 6.0554525 | F91: =F100/C86*100 -> 15.358562 | G91: =G100/C86*100 -> 20.940428 | H91: =H100/C86*100 -> 28.382916
A92: =B76 -> 201.04308 | B92: =B101/C86*100 -> -17.76338 | C92: =C101/C86*100 -> -7.9733059 | D92: =D101/C86*100 -> 1.816768 | E92: =E101/C86*100 -> 11.606842 | F92: =F101/C86*100 -> 21.396916 | G92: =G101/C86*100 -> 27.27096 | H92: =H101/C86*100 -> 35.103019
A93: =A92+10 -> 211.04308 | B93: =B102/C86*100 -> -13.672882 | C93: =C102/C86*100 -> -3.3958445 | D93: =D102/C86*100 -> 6.8811933 | E93: =E102/C86*100 -> 17.158231 | F93: =F102/C86*100 -> 27.435269 | G93: =G102/C86*100 -> 33.601492 | H93: =H102/C86*100 -> 41.823122
A94: =A93+10 -> 221.04308 | B94: =B103/C86*100 -> -9.5823849 | C94: =C103/C86*100 -> 1.1816169 | D94: =D103/C86*100 -> 11.945619 | E94: =E103/C86*100 -> 22.70962 | F94: =F103/C86*100 -> 33.473622 | G94: =G103/C86*100 -> 39.932023 | H94: =H103/C86*100 -> 48.543225
A95: =A94+10 -> 231.04308 | B95: =B104/C86*100 -> -5.4918875 | C95: =C104/C86*100 -> 5.7590782 | D95: =D104/C86*100 -> 17.010044 | E95: =E104/C86*100 -> 28.26101 | F95: =F104/C86*100 -> 39.511976 | G95: =G104/C86*100 -> 46.262555 | H95: =H104/C86*100 -> 55.263328
A96: MB TRIGO SUELOS PROFUNDOS (USD / TON)
A97: Px/Rinde | B97: =E97-1.5 -> 4.2 | C97: =E97-1 -> 4.7 | D97: =E97-0.5 -> 5.2 | E97: =B75 -> 5.7 | F97: =E97+0.5 -> 6.2 | G97: =E97+0.8 -> 6.5 | H97: =E97+1.2 -> 6.9
A98: =A99-10 -> 171.04308 | B98: =(B97*A98)-C86 -> -308.38905 | C98: =(C97*A98)-C86 -> -222.86751 | D98: =(D97*A98)-C86 -> -137.34597 | E98: =(E97*A98)-C86 -> -51.82443 | F98: =(F97*A98)-C86 -> 33.697111 | G98: =(G97*A98)-C86 -> 85.010036 | H98: =(H97*A98)-C86 -> 153.42727
A99: =A100-10 -> 181.04308 | B99: =(B97*A99)-C86 -> -266.38905 | C99: =(C97*A99)-C86 -> -175.86751 | D99: =(D97*A99)-C86 -> -85.345971 | E99: =(E97*A99)-C86 -> 5.1755699 | F99: =(F97*A99)-C86 -> 95.697111 | G99: =(G97*A99)-C86 -> 150.01004 | H99: =(H97*A99)-C86 -> 222.42727
A100: =A101-10 -> 191.04308 | B100: =(A100*B97)-C86 -> -224.38905 | C100: =(C97*A100)-C86 -> -128.86751 | D100: =(D97*A100)-C86 -> -33.345971 | E100: =(E97*A100)-C86 -> 62.17557 | F100: =(F97*A100)-C86 -> 157.69711 | G100: =(G97*A100)-C86 -> 215.01004 | H100: =(H97*A100)-C86 -> 291.42727
A101: =B76 -> 201.04308 | B101: =(A101*B97)-C86 -> -182.38905 | C101: =(A101*C97)-C86 -> -81.867513 | D101: =(D97*A101)-C86 -> 18.654029 | E101: =(A101*E97)-C86 -> 119.17557 | F101: =(A101*F97)-C86 -> 219.69711 | G101: =(G97*A101)-C86 -> 280.01004 | H101: =(H97*A101)-C86 -> 360.42727
A102: =A101+10 -> 211.04308 | B102: =(A102*B97)-C86 -> -140.38905 | C102: =(C97*A102)-C86 -> -34.867513 | D102: =(D97*A102)-C86 -> 70.654029 | E102: =(E97*A102)-C86 -> 176.17557 | F102: =(F97*A102)-C86 -> 281.69711 | G102: =(G97*A102)-C86 -> 345.01004 | H102: =(H97*A102)-C86 -> 429.42727
A103: =A102+10 -> 221.04308 | B103: =(A103*B97)-C86 -> -98.389054 | C103: =(C97*A103)-C86 -> 12.132487 | D103: =(D97*A103)-C86 -> 122.65403 | E103: =(E97*A103)-C86 -> 233.17557 | F103: =(F97*A103)-C86 -> 343.69711 | G103: =(G97*A103)-C86 -> 410.01004 | H103: =(H97*A103)-C86 -> 498.42727
A104: =A103+10 -> 231.04308 | B104: =(B97*A104)-C86 -> -56.389054 | C104: =(C97*A104)-C86 -> 59.132487 | D104: =(D97*A104)-C86 -> 174.65403 | E104: =(E97*A104)-C86 -> 290.17557 | F104: =(F97*A104)-C86 -> 405.69711 | G104: =(G97*A104)-C86 -> 475.01004 | H104: =(A104*H97)-C86 -> 567.42727

Sheet Camelina
A1: Proyección Soja Suelos Profundos
A3: HECTAREAS | B3: 0
B5: CANTIDAD | C5: UNIDAD | D5: PRECIO | E5: TOTAL / HA | F5: % Costo | G5: Inv Real | H5: Mes
D6: UNITARIO | J6: MES CASH FLOW
A7: Labores
A8: Disco,rastra y rolo | B8: 0 | C8: Uni | D8: =Cotizaciones!F8 -> 0 | E8: =B8*D8 -> 0
A9: Rolo picador | B9: 0 | C9: Uni | D9: 24 | E9: =B9*D9 -> 0 | J9: JUNIO
A10: Barbecho Quimico | B10: 2 | C10: Uni | D10: 7 | E10: =B10*D10 -> 14 | H10: 41061 | I10: 41153 | J10: AGOSTO
A11: Preemergente | B11: 1 | C11: UNI | D11: 8 | E11: =B11*D11 -> 8 | J11: OCTUBRE
A12: Siembra Directa | B12: 1 | C12: Uni | D12: 55 | E12: =B12*D12 -> 55 | H12: 41214 | J12: DICIEMBRE
A13: Fertilizacion | B13: 1 | C13: Uni | D13: 12 | E13: =B13*D13 -> 12 | H13: 41215 | I13: 40940 | J13: DICIEMBRE
A14: Pulverizacion | B14: 0 | C14: Uni | D14: 7 | E14: =B14*D14 -> 0 | J14: FEBRERO
A15: Aplicación terrestre Insecticida/ Fungicida | B15: 0 | C15: Uni | D15: =+D14 -> 7 | E15: =B15*D15 -> 0 | H15: 40941 | J15: MARZO
A16: Monitoreo B y BB. | B16: 0 | C16: Uni | D16: 6 | E16: =B16*D16 -> 0 | H16: 41183 | J16: NOVIEMBRE
A17: Limpieza e inoculado | B17: 0 | C17: Uni | D17: =+((Cotizaciones!E12/Cotizaciones!M14)/1000)*B23 -> 0.50819816 | E17: =B17*D17 -> 0
A18: Aplicacion Cebo | B18: 0 | C18: Uni | D18: =Cotizaciones!F6 -> 5 | E18: =B18*D18 -> 0 | H18: 41214 | J18: NOVIEMBRE
C20: Total Labores | E20: =SUM(E8:E19) -> 89 | F20: =E20/E64 -> 0.22277847 | G20: =E20*D1 -> 0
A21: Semilla
A23: Semilla de Soja propia | B23: 24 | C23: Kgs. | D23: 0.45 | E23: =B23*D23 -> 10.8 | H23: 41214 | J23: NOVIEMBRE
C24: Total Semilla | E24: =SUM(E23:E23) -> 10.8 | F24: =E24/E64 -> 0.027033792 | G24: =E24*D1 -> 0
A26: Arrendamiento | B26: 0 | C26: Uni | D26: ='Resumen Proy'!D15 -> 426 | E26: =B26*D26 -> 0
C27: Total Arrendamiento | E27: =E26 -> 0 | F27: =E27/E64 -> 0 | G27: =E27*D1 -> 0
A29: Gerenciamiento | B29: =0.3*40 -> 12 | C29: USD / Ha | D29: =B29 -> 12 | E29: =D29 -> 12
C30: Total Gerenciamiento | E30: =E29 -> 12 | F30: =E30/E64 -> 0.030037547 | G30: =E30*D1 -> 0
A32: Fertilizantes
A33: Fosforados | B33: 0.07 | C33: Ton. | D33: =Cotizaciones!I25 -> 990 | E33: =B33*D33 -> 69.3 | H33: 41214
A34: UREA | B34: 0.06 | C34: Ton. | D34: =+Cotizaciones!I34 -> 610 | E34: =B34*D34 -> 36.6 | I34: =+E34*B3 -> 0 | J34: NOVIEMBRE
B35: =+B34+B33 -> 0.13 | D35: =+'Cebada SP'!D35 -> 35 | E35: =+D35*B35 -> 4.55
C36: Total Fertilizantes | E36: =+E35+E34+E33 -> 110.45 | F36: =E36/E64 -> 0.27647059 | G36: =E36*D1 -> 0
A37: Agroquímicos
A39: Aceite | B39: 1 | C39: Lts. | D39: =Cotizaciones!I6 -> 3 | E39: =B39*D39 -> 3 | H39: pulv | I39: fung | J39: DICIEMBRE
A40: Coadyudante | B40: 0 | C40: Lts. | D40: =Cotizaciones!I21 -> 12 | E40: =B40*D40 -> 0 | H40: =+A10 -> Barbecho Quimico | J40: JULIO
A41: Lactofen | B41: 0 | C41: Lts. | D41: =+Cotizaciones!I51 -> 7.2 | E41: =B41*D41 -> 0 | H41: =+H40 -> Barbecho Quimico | J41: =+J40 -> JULIO
A42: Paraquat | B42: 2 | C42: Lts. | D42: =+Cotizaciones!I45 -> 2.6 | E42: =B42*D42 -> 5.2 | H42: =+A12 -> Siembra Directa | J42: NOVIEMBRE
A43: sulfo | B43: 2.5 | C43: Lts. | D43: =+Cotizaciones!I43 -> 4.5 | E43: =B43*D43 -> 11.25 | H43: Barbecho Quimico | J43: JULIO
A44: 2,4-D | B44: 1 | C44: Lts. | D44: =Cotizaciones!I5 -> 4.6 | E44: =B44*D44 -> 4.6 | H44: barb (1ro) | J44: JULIO
A45: Graminicida | B45: 1.2 | C45: Lts. | D45: =Cotizaciones!I27 -> 6 | E45: =B45*D45 -> 7.2
A46: Trifluralina | B46: 1 | C46: Lts. | D46: 17 | E46: =B46*D46 -> 17 | H46: fung | J46: MARZO
A47: Diquat | B47: 2 | C47: Lts. | D47: 17 | E47: =B47*D47 -> 34 | J47: DICIEMBRE
H48: pulv | J48: DICIEMBRE
H49: fung | J49: DICIEMBRE
H50: pulv (1ra) | J50: DICIEMBRE
H51: fung | J51: MARZO
H52: =+A18 -> Aplicacion Cebo | J52: NOVIEMBRE
C53: Total Agroquimicos | E53: =SUM(E39:E52) -> 82.25 | F53: =E53/E64 -> 0.20588235 | G53: =E53*D1 -> 0
A55: Cosecha | B55: 1 | C55: Hás. | D55: 80 | E55: =+D55*B55 -> 80
C56: Total Cosecha | E56: =E55 -> 80 | F56: =E56/E64 -> 0.20025031
A58: Seguro (Granizo) | B58: 2.8 | C58: % Costo | D58: 15 | E58: =D58 -> 15
C59: Total Seguro | E59: =E58 -> 15 | F59: =E59/E64 -> 0.037546934
A61: Costos Financiero | B61: 0 | C61: % | D61: 0 | E61: =(E53+E36+E27+E20+E24)*D61/100 -> 0
C62: Total Costo Financ.
C64: Costo Total | E64: =E20+E24+E27+E30+E36+E53+E56+E59+E62 -> 399.5 | F64: =F59+F75+F56+F53+F36+F30+F27+F24+F20 -> 1.08398
A66: Comercialización
A67: Extraccion/Embolsado | B67: 0 | C67: U$ / ton | D67: =Cotizaciones!F24 -> 3.3 | E67: =D67*B67*B82 -> 0
A68: Silobolsa | B68: 0 | C68: 210 Tons | D68: =Cotizaciones!I41/210 -> 1.952381 | E68: =+D68*B68*$B$82 -> 0
A69: Secada | B69: 0 | C69: U$ / ton | D69: =Cotizaciones!F33 -> 3 | E69: =+D69*B69*$B$82 -> 0
A70: Paritaria | B70: 0 | C70: U$ / ton | D70: =Cotizaciones!F35 -> 5 | E70: =+D70*B70*$B$82 -> 0
A71: Traspile | B71: 0 | C71: U$ / ton | D71: =+Cotizaciones!F36 -> 6.5 | E71: =+D71*B71*$B$82 -> 0
A72: Analisis | B72: 1 | C72: U$ / ton | D72: =Cotizaciones!F5 -> 0 | E72: =+D72*B72*$B$82 -> 0
A73: Flete | B73: 1 | C73: U$ / ton | D73: 30 | E73: =+D73*B73*$B$82 -> 30
A74: Comisión | B74: 1 | C74: % | D74: =B74%*B82*Cotizaciones!B14 -> 3.55 | E74: =D74 -> 3.55
C75: Total Comercialización | E75: =SUM(E69:E74) -> 33.55 | F75: =E75/E64 -> 0.083979975
A76: Precio bruto | E76: 450
A77: Gastos Comerciales/tn | E77: =+E75/B82 -> 33.55
A78: Precio Neto Estimado | E78: =+E76-E77 -> 416.45
E79: =+E64*B3 -> 0
A81: SOJA SUELOS PROFUNDOS
A82: Rendimiento Estimado | B82: 1 | C82: Ton/Ha.
A83: Precio Neto Estimado | B83: =+E78 -> 416.45 | C83: Ton.
A84: Costo Total | B84: =E64 -> 399.5 | C84: Ton
A85: Ingreso Bruto (2% IB) | B85: =+B83*B82 -> 416.45 | C85: Ha
A86: Margen | B86: =+B85-E64 -> 16.95 | C86: Ha
A87: Retorno | B87: =B86/B84 -> 0.042428035
A88: Rendimiento de Indiferencia | B88: =+B84/B83 -> 0.95929884
A89: Inversión Real | B89: =+E53+E36+aquimsj1+E27+E24+E20 -> 304.5
A90: Retorno Real | B90: =+B86/B89 -> 0.055665025
A93: Costo Total | C93: =E64 -> 399.5
A94: Retorno (%)
A95: Px/Rinde | B95: =B104 -> 1.9 | C95: =C104 -> 0.4 | D95: =D104 -> 0.7 | E95: =E104 -> 1 | F95: =F104 -> 1.3 | G95: =G104 -> 1.6 | H95: =H104 -> 1.9
A96: =A97-10 -> 386.45 | B96: =B105/C93*100 -> 83.793492 | C96: =C105/C93*100 -> -61.306633 | D96: =D105/C93*100 -> -32.286608 | E96: =E105/C93*100 -> -3.2665832 | F96: =F105/C93*100 -> 25.753442 | G96: =G105/C93*100 -> 54.773467 | H96: =H105/C93*100 -> 83.793492
A97: =A98-10 -> 396.45 | B97: =B106/C93*100 -> 88.549437 | C97: =C106/C93*100 -> -60.305382 | D97: =D106/C93*100 -> -30.534418 | E97: =E106/C93*100 -> -0.76345432 | F97: =F106/C93*100 -> 29.007509 | G97: =G106/C93*100 -> 58.778473 | H97: =H106/C93*100 -> 88.549437
A98: =A99-10 -> 406.45 | B98: =B107/C93*100 -> 93.305382 | C98: =C107/C93*100 -> -59.30413 | D98: =D107/C93*100 -> -28.782228 | E98: =E107/C93*100 -> 1.7396746 | F98: =F107/C93*100 -> 32.261577 | G98: =G107/C93*100 -> 62.783479 | H98: =H107/C93*100 -> 93.305382
A99: =B83 -> 416.45 | B99: =B108/C93*100 -> 98.061327 | C99: =C108/C93*100 -> -58.302879 | D99: =D108/C93*100 -> -27.030038 | E99: =E108/C93*100 -> 4.2428035 | F99: =F108/C93*100 -> 35.515645 | G99: =G108/C93*100 -> 66.788486 | H99: =H108/C93*100 -> 98.061327
A100: =A99+10 -> 426.45 | B100: =B109/C93*100 -> 102.81727 | C100: =C109/C93*100 -> -57.301627 | D100: =D109/C93*100 -> -25.277847 | E100: =E109/C93*100 -> 6.7459324 | F100: =F109/C93*100 -> 38.769712 | G100: =G109/C93*100 -> 70.793492 | H100: =H109/C93*100 -> 102.81727
A101: =A100+10 -> 436.45 | B101: =B110/C93*100 -> 107.57322 | C101: =C110/C93*100 -> -56.300375 | D101: =D110/C93*100 -> -23.525657 | E101: =E110/C93*100 -> 9.2490613 | F101: =F110/C93*100 -> 42.02378 | G101: =G110/C93*100 -> 74.798498 | H101: =H110/C93*100 -> 107.57322
A102: =A101+10 -> 446.45 | B102: =B111/C93*100 -> 112.32916 | C102: =C111/C93*100 -> -55.299124 | D102: =D111/C93*100 -> -21.773467 | E102: =E111/C93*100 -> 11.75219 | F102: =F111/C93*100 -> 45.277847 | G102: =G111/C93*100 -> 78.803504 | H102: =H111/C93*100 -> 112.32916
A103: MB
A104: Px/Rinde | B104: 1.9 | C104: =D104-0.3 -> 0.4 | D104: =E104-0.3 -> 0.7 | E104: =B82 -> 1 | F104: =E104+0.3 -> 1.3 | G104: =F104+0.3 -> 1.6 | H104: =G104+0.3 -> 1.9
A105: =A106-10 -> 386.45 | B105: =(B104*A105)-C93 -> 334.755 | C105: =(C104*A105)-C93 -> -244.92 | D105: =(D104*A105)-C93 -> -128.985 | E105: =(E104*A105)-C93 -> -13.05 | F105: =(F104*A105)-C93 -> 102.885 | G105: =(G104*A105)-C93 -> 218.82 | H105: =(H104*A105)-C93 -> 334.755
A106: =A107-10 -> 396.45 | B106: =(B104*A106)-C93 -> 353.755 | C106: =(C104*A106)-C93 -> -240.92 | D106: =(D104*A106)-C93 -> -121.985 | E106: =(E104*A106)-C93 -> -3.05 | F106: =(F104*A106)-C93 -> 115.885 | G106: =(G104*A106)-C93 -> 234.82 | H106: =(H104*A106)-C93 -> 353.755
A107: =A108-10 -> 406.45 | B107: =(A107*B104)-C93 -> 372.755 | C107: =(C104*A107)-C93 -> -236.92 | D107: =(D104*A107)-C93 -> -114.985 | E107: =(E104*A107)-C93 -> 6.95 | F107: =(F104*A107)-C93 -> 128.885 | G107: =(G104*A107)-C93 -> 250.82 | H107: =(H104*A107)-C93 -> 372.755
A108: =B83 -> 416.45 | B108: =(A108*B104)-C93 -> 391.755 | C108: =(A108*C104)-C93 -> -232.92 | D108: =(D104*A108)-C93 -> -107.985 | E108: =(A108*E104)-C93 -> 16.95 | F108: =(A108*F104)-C93 -> 141.885 | G108: =(G104*A108)-C93 -> 266.82 | H108: =(H104*A108)-C93 -> 391.755
A109: =A108+10 -> 426.45 | B109: =(A109*B104)-C93 -> 410.755 | C109: =(C104*A109)-C93 -> -228.92 | D109: =(D104*A109)-C93 -> -100.985 | E109: =(E104*A109)-C93 -> 26.95 | F109: =(F104*A109)-C93 -> 154.885 | G109: =(G104*A109)-C93 -> 282.82 | H109: =(H104*A109)-C93 -> 410.755
A110: =A109+10 -> 436.45 | B110: =(A110*B104)-C93 -> 429.755 | C110: =(C104*A110)-C93 -> -224.92 | D110: =(D104*A110)-C93 -> -93.985 | E110: =(E104*A110)-C93 -> 36.95 | F110: =(F104*A110)-C93 -> 167.885 | G110: =(G104*A110)-C93 -> 298.82 | H110: =(H104*A110)-C93 -> 429.755
A111: =A110+10 -> 446.45 | B111: =(B104*A111)-C93 -> 448.755 | C111: =(C104*A111)-C93 -> -220.92 | D111: =(D104*A111)-C93 -> -86.985 | E111: =(E104*A111)-C93 -> 46.95 | F111: =(F104*A111)-C93 -> 180.885 | G111: =(G104*A111)-C93 -> 314.82 | H111: =(A111*H104)-C93 -> 448.755

Sheet Soja 2da. T
A1: Proyección Soja 2da Trigo
A3: HECTAREAS | B3: =+'Trigo SP'!B3 -> 0
D5: UNITARIO | J5: MES CASH FLOW
A6: Labores
A7: Disco,rastra y rolo | B7: 0 | C7: Uni | D7: =Cotizaciones!F8 -> 0 | E7: =B7*D7 -> 0 | K7: =+E7*$B$3 -> 0
A8: Rolo picador | B8: 0 | C8: Uni | D8: =Cotizaciones!F18 -> 17 | E8: =B8*D8 -> 0 | K8: =+E8*$B$3 -> 0
A9: Barbecho Quimico | B9: 0 | C9: Uni | D9: 6.5 | E9: =B9*D9 -> 0 | K9: =+E9*$B$3 -> 0
A10: Siembra Directa | B10: 1 | C10: Uni | D10: 55 | E10: =B10*D10 -> 55 | H10: 41245 | J10: ENERO | K10: =+E10*$B$3 -> 0
A11: Pulverizacion Herbicida | B11: 1 | C11: Uni | D11: 6.5 | E11: =B11*D11 -> 6.5 | H11: 40909 | J11: ENERO | K11: =+E11*$B$3 -> 0
A12: Pulverizacion Herbicida | B12: 1 | D12: 6.5 | E12: =B12*D12 -> 6.5 | J12: MARZO | K12: =+E12*$B$3 -> 0
A13: Aplicación terrestre Insecticida | B13: 1 | C13: Uni | D13: 6.5 | E13: =B13*D13 -> 6.5 | H13: 40941 | J13: MARZO | K13: =+E13*$B$3 -> 0
A14: Muestreo de suelos | B14: 0 | C14: Uni | D14: =Cotizaciones!F15 -> 1 | E14: =B14*D14 -> 0 | J14: MARZO | K14: =+E14*$B$3 -> 0
A15: Analisis de suelos | B15: 0 | C15: Uni | D15: =Cotizaciones!F5 -> 0 | E15: =B15*D15 -> 0 | J15: MARZO | K15: =+E15*$B$3 -> 0
A16: Medicion satelital GPS | B16: 0 | C16: Uni | D16: =Cotizaciones!F13 -> 0 | E16: =B16*D16 -> 0 | J16: MARZO | K16: =+E16*$B$3 -> 0
A17: Limpieza e inoculada | B17: 0 | C17: Uni | D17: =+'Soja 2da. C'!D17 -> 0 | E17: =(B21*D17)/1000 -> 0 | H17: 41244 | J17: ENERO | K17: =+E17*$B$3 -> 0
C18: Total Labores | E18: =SUM(E7:E17) -> 74.5 | F18: =E18/E56 -> 0.18410972 | G18: =E18*B3 -> 0 | K18: =SUM(K7:K17) -> 0
A19: Semilla
A21: Semilla de Soja | B21: 90 | C21: Kgs. | D21: =+Cotizaciones!E45/40 -> 0.875 | E21: =B21*D21 -> 78.75 | H21: 41215 | J21: ENERO
C22: Total Semilla | E22: =SUM(E21:E21) -> 78.75 | F22: =E22/E56 -> 0.19461263 | G22: =E22*B3 -> 0
A24: Arrendamiento | B24: 0.2 | C24: Uni | D24: =+'Resumen Proy'!C57 -> 426 | E24: =B24*D24 -> 85.2
C25: Total Arrendamiento | E25: =E24 -> 85.2 | F25: =E25/E56 -> 0.21055233
A27: Gerenciamiento | B27: 10 | C27: USD / Ha | D27: =B27 -> 10 | E27: =D27 -> 10
C28: Total Gerenciamiento | E28: =E27 -> 10
A30: Fertilizantes
A31: Fosforados ( puesto en el campo ) | B31: 0 | C31: Ton. | D31: 0 | E31: =B31*D31 -> 0
A32: Arrancador Azufrado | B32: 0 | C32: Ton. | D32: 0 | E32: =B32*D32 -> 0
C33: Total Fertilizantes | E33: =SUM(E31:E32) -> 0
A34: Agroquímicos
A35: Aceite | B35: 1 | C35: Lts. | D35: =Cotizaciones!I6 -> 3 | E35: =B35*D35 -> 3 | H35: =A13 -> Aplicación terrestre Insecticida | J35: ENERO/MARZO
A36: Coadyugante (Lecitina) | B36: 0 | C36: Lts. | D36: =Cotizaciones!I21 -> 12 | E36: =B36*D36 -> 0 | H36: =A11 -> Pulverizacion Herbicida | J36: ENERO/MARZO
A37: sulfentrazone | B37: 0 | C37: Lts. | D37: =+Cotizaciones!I52 -> 19 | E37: =B37*D37 -> 0 | H37: =H36 -> Pulverizacion Herbicida | J37: ENERO/MARZO
A38: Inoculante | B38: =B21/2500 -> 0.036 | C38: Pack 2,5 Ton | D38: =Cotizaciones!I29 -> 250 | E38: =(D38*B38) -> 9 | H38: =A10 -> Siembra Directa | J38: ENERO
A39: Sulfosato | B39: 4 | C39: Lts. | D39: =+Cotizaciones!I43 -> 4.5 | E39: =B39*D39 -> 18 | H39: =H36 -> Pulverizacion Herbicida | J39: ENERO/MARZO
A40: 2,4-D | B40: 2 | C40: Lts. | D40: =Cotizaciones!I5 -> 4.6 | E40: =B40*D40 -> 9.2
A41: Clorimuron | B41: 0 | C41: Lts. | D41: =Cotizaciones!I18 -> 22.05 | E41: =B41*D41 -> 0
A42: lambda | B42: 0.15 | C42: Lts. | D42: =Cotizaciones!I15 -> 20 | E42: =B42*D42 -> 3 | H42: =H35 -> Aplicación terrestre Insecticida | J42: MARZO
A43: fomsesafen | B43: 0 | C43: Lts. | D43: =+Cotizaciones!I51 -> 7.2 | E43: =B43*D43 -> 0 | H43: =H35 -> Aplicación terrestre Insecticida | J43: MARZO
A44: coragen | B44: 0.16 | C44: Lts. | D44: =Cotizaciones!I30 -> 100 | E44: =B44*D44 -> 16 | J44: MARZO
C45: Total Agroquimicos | E45: =SUM(E35:E44) -> 58.2 | F45: =E45/E56 -> 0.143828 | G45: =E45*B3 -> 0
A47: Cosecha | B47: 1 | D47: 90 | E47: =+D47*B47 -> 90 | H47: 41031
C48: } | E48: =E47 -> 90 | F48: =E48/E56 -> 0.22241443 | G48: =E48*B3 -> 0
A50: Seguro (Granizo) | B50: 2.5 | C50: % Costo | D50: 8 | E50: =D50 -> 8
C51: Total Seguro | E51: =E50 -> 8 | F51: =E51/E56 -> 0.019770172 | G51: =E51*B3 -> 0
A53: Costos Financiero | B53: 0 | C53: % | D53: 0 | E53: =(E45+E33+E25+E18)*D53/100 -> 0
C54: Total Costo Financ.
C56: Costo Total | E56: =E18+E22+E25+E28+E33+E45+E48+E51+E54 -> 404.65 | F56: =F51+F67+F48+F45+F22+F18+F25 -> 0.97528729
A58: Comercialización
A59: Extraccion/Embolsado | B59: 0 | C59: U$ / ton | D59: =Cotizaciones!E24 -> 0 | E59: =D59*B59*B73 -> 0
A60: Silobolsa | B60: 0 | C60: 210 Tons | D60: =Cotizaciones!I41/210 -> 1.952381 | E60: =D60*B60*B74 -> 0
A61: Secada | B61: 1 | C61: U$ / ton | D61: =Cotizaciones!F33 -> 3 | E61: =+D61*B61*$B$73 -> 3.9
A62: Paritaria | B62: 0.8 | C62: U$ / ton | D62: =Cotizaciones!F35 -> 5 | E62: =+D62*B62*$B$73 -> 5.2
A63: Traspile | B63: 0.8 | C63: U$ / ton | D63: =+Cotizaciones!F36 -> 6.5 | E63: =+D63*B63*$B$73 -> 6.76
A64: Analisis | B64: 1 | C64: U$ / ton | D64: =+Cotizaciones!E5/Cotizaciones!M20 -> 0.53083473 | E64: =+D64*B64*$B$73 -> 0.69008514
A65: Flete | B65: 1 | C65: U$ / ton | D65: =+'Soja 2da. C'!D66 -> 20 | E65: =+D65*B65*$B$73 -> 26
A66: Comisión | B66: 1 | C66: % | D66: =B66%*B73*Cotizaciones!B14 -> 4.615 | E66: =D66 -> 4.615
C67: Total Comercialización | E67: =SUM(E61:E66) -> 47.165085 | G67: =E67*B3 -> 0
A68: Precio bruto | E68: =+Cotizaciones!B14 -> 355
A69: Gastos Comerciales/tn | E69: =+E67/B73 -> 36.280835 | F69: =+E69/E68 -> 0.10219953
A70: Precio Neto Estimado | E70: =+E68-E69 -> 318.71917
G71: Alea | I71: Socio | K71: Total/ha
A72: SOJA DE SEGUNDA SUELO PROFUNDO | F72: Labores | H72: =+G72*B$3 -> 0 | I72: =+E18 -> 74.5 | J72: =+I72*B$3 -> 0
A73: Rendimiento Estimado | B73: 1.3 | C73: Ton/Ha. | F73: Semilla | G73: 0 | H73: =+G73*B$3 -> 0 | I73: =+E25 -> 85.2 | J73: =+I73*B$3 -> 0 | K73: =+I73+G73 -> 85.2
A74: Precio Neto Estimado | B74: =+E70 -> 318.71917 | C74: Ton. | F74: Arrendamiento | G74: =+E25 -> 85.2 | H74: =+G74*B$3 -> 0 | J74: =+I74*B$3 -> 0 | K74: =+I74+G74 -> 85.2
A75: Costo Total | B75: =+E56 -> 404.65 | C75: Ton | F75: Gerenciamiento | G75: =+B27 -> 10 | H75: =+G75*B$3 -> 0 | J75: =+I75*B$3 -> 0 | K75: =+I75+G75 -> 10
A76: Ingreso Bruto | B76: =+B74*B73 -> 414.33491 | C76: Ha | F76: Fertilizantes | G76: 0 | H76: =+G76*B$3 -> 0 | I76: 0 | J76: =+I76*B$3 -> 0 | K76: =+I76+G76 -> 0
A77: Margen | B77: =+B76-E56 -> 9.6849149 | C77: Ha | F77: Agroquímicos | H77: =+G77*B$3 -> 0 | I77: =+E45 -> 58.2 | J77: =+I77*B$3 -> 0 | K77: =+I77+G77 -> 58.2
A78: Retorno | B78: =B77/E56 -> 0.023934054 | J78: =+I78*B$3 -> 0 | K78: =+I78+G78 -> 0
A79: Rendimiento de Indiferencia | B79: =+B75/B74 -> 1.269613 | F79: Total
A80: Inversión Real | B80: =+E45+E33+E25+E22+E18 -> 296.65 | G80: =SUM(G72:G79) -> 95.2 | H80: =SUM(H72:H79) -> 0 | I80: =SUM(I72:I79) -> 217.9 | J80: =SUM(J72:J79) -> 0 | K80: =+I80+G80 -> 313.1
A81: Retorno Real | B81: =B77/B80 -> 0.032647615 | G81: =+G80/K80 -> 0.30405621 | I81: =+I80/K80 -> 0.69594379
A83: Costo Total | C83: =E56 -> 404.65
A84: Retorno (%)
A85: Px/Rinde | B85: =B94 -> 0.4 | C85: =C94 -> 0.7 | D85: =D94 -> 1 | E85: =E94 -> 1.3 | F85: =F94 -> 1.6 | G85: =G94 -> 1.9 | H85: =H94 -> 2.2
A86: =A87-10 -> 288.71917 | B86: =B95/C83*100 -> -71.459863 | C86: =C95/C83*100 -> -50.054759 | D86: =D95/C83*100 -> -28.649656 | E86: =E95/C83*100 -> -7.2445534 | F86: =F95/C83*100 -> 14.16055 | G86: =G95/C83*100 -> 35.565653 | H86: =H95/C83*100 -> 56.970756
A87: =A88-10 -> 298.71917 | B87: =B96/C83*100 -> -70.471354 | C87: =C96/C83*100 -> -48.324869 | D87: =D96/C83*100 -> -26.178385 | E87: =E96/C83*100 -> -4.0319004 | F87: =F96/C83*100 -> 18.114584 | G87: =G96/C83*100 -> 40.261069 | H87: =H96/C83*100 -> 62.407553
A88: =A89-10 -> 308.71917 | B88: =B97/C83*100 -> -69.482845 | C88: =C97/C83*100 -> -46.594979 | D88: =D97/C83*100 -> -23.707113 | E88: =E97/C83*100 -> -0.81924753 | F88: =F97/C83*100 -> 22.068618 | G88: =G97/C83*100 -> 44.956484 | H88: =H97/C83*100 -> 67.84435
A89: =B74 -> 318.71917 | B89: =B98/C83*100 -> -68.494337 | C89: =C98/C83*100 -> -44.865089 | D89: =D98/C83*100 -> -21.235842 | E89: =E98/C83*100 -> 2.3934054 | F89: =F98/C83*100 -> 26.022653 | G89: =G98/C83*100 -> 49.6519 | H89: =H98/C83*100 -> 73.281148
A90: =A89+10 -> 328.71917 | B90: =B99/C83*100 -> -67.505828 | C90: =C99/C83*100 -> -43.135199 | D90: =D99/C83*100 -> -18.764571 | E90: =E99/C83*100 -> 5.6060583 | F90: =F99/C83*100 -> 29.976687 | G90: =G99/C83*100 -> 54.347316 | H90: =H99/C83*100 -> 78.717945
A91: =A90+10 -> 338.71917 | B91: =B100/C83*100 -> -66.51732 | C91: =C100/C83*100 -> -41.405309 | D91: =D100/C83*100 -> -16.293299 | E91: =E100/C83*100 -> 8.8187112 | F91: =F100/C83*100 -> 33.930721 | G91: =G100/C83*100 -> 59.042732 | H91: =H100/C83*100 -> 84.154742
A92: =A91+10 -> 348.71917 | B92: =B101/C83*100 -> -65.528811 | C92: =C101/C83*100 -> -39.675419 | D92: =D101/C83*100 -> -13.822028 | E92: =E101/C83*100 -> 12.031364 | F92: =F101/C83*100 -> 37.884756 | G92: =G101/C83*100 -> 63.738148 | H92: =H101/C83*100 -> 89.591539
A93: MB SOJA DE SEGUNDA SUELOS PROFUNDOS (USD / TON)
A94: Px/Rinde | B94: =C94-0.3 -> 0.4 | C94: =D94-0.3 -> 0.7 | D94: =E94-0.3 -> 1 | E94: =B73 -> 1.3 | F94: =E94+0.3 -> 1.6 | G94: =F94+0.3 -> 1.9 | H94: =G94+0.3 -> 2.2
A95: =A96-10 -> 288.71917 | B95: =(B94*A95)-C83 -> -289.16233 | C95: =(C94*A95)-C83 -> -202.54658 | D95: =(D94*A95)-C83 -> -115.93083 | E95: =(E94*A95)-C83 -> -29.315085 | F95: =(F94*A95)-C83 -> 57.300664 | G95: =(G94*A95)-C83 -> 143.91641 | H95: =(H94*A95)-C83 -> 230.53216
A96: =A97-10 -> 298.71917 | B96: =(B94*A96)-C83 -> -285.16233 | C96: =(C94*A96)-C83 -> -195.54658 | D96: =(D94*A96)-C83 -> -105.93083 | E96: =(E94*A96)-C83 -> -16.315085 | F96: =(F94*A96)-C83 -> 73.300664 | G96: =(G94*A96)-C83 -> 162.91641 | H96: =(H94*A96)-C83 -> 252.53216
A97: =A98-10 -> 308.71917 | B97: =(A97*B94)-C83 -> -281.16233 | C97: =(C94*A97)-C83 -> -188.54658 | D97: =(D94*A97)-C83 -> -95.930835 | E97: =(E94*A97)-C83 -> -3.3150851 | F97: =(F94*A97)-C83 -> 89.300664 | G97: =(G94*A97)-C83 -> 181.91641 | H97: =(H94*A97)-C83 -> 274.53216
A98: =B74 -> 318.71917 | B98: =(A98*B94)-C83 -> -277.16233 | C98: =(A98*C94)-C83 -> -181.54658 | D98: =(D94*A98)-C83 -> -85.930835 | E98: =(A98*E94)-C83 -> 9.6849149 | F98: =(A98*F94)-C83 -> 105.30066 | G98: =(G94*A98)-C83 -> 200.91641 | H98: =(H94*A98)-C83 -> 296.53216
A99: =A98+10 -> 328.71917 | B99: =(A99*B94)-C83 -> -273.16233 | C99: =(C94*A99)-C83 -> -174.54658 | D99: =(D94*A99)-C83 -> -75.930835 | E99: =(E94*A99)-C83 -> 22.684915 | F99: =(F94*A99)-C83 -> 121.30066 | G99: =(G94*A99)-C83 -> 219.91641 | H99: =(H94*A99)-C83 -> 318.53216
A100: =A99+10 -> 338.71917 | B100: =(A100*B94)-C83 -> -269.16233 | C100: =(C94*A100)-C83 -> -167.54658 | D100: =(D94*A100)-C83 -> -65.930835 | E100: =(E94*A100)-C83 -> 35.684915 | F100: =(F94*A100)-C83 -> 137.30066 | G100: =(G94*A100)-C83 -> 238.91641 | H100: =(H94*A100)-C83 -> 340.53216
A101: =A100+10 -> 348.71917 | B101: =(B94*A101)-C83 -> -265.16233 | C101: =(C94*A101)-C83 -> -160.54658 | D101: =(D94*A101)-C83 -> -55.930835 | E101: =(E94*A101)-C83 -> 48.684915 | F101: =(F94*A101)-C83 -> 153.30066 | G101: =(G94*A101)-C83 -> 257.91641 | H101: =(A101*H94)-C83 -> 362.53216

Sheet Maiz 2da
A1: Proyección Maíz RR SP
A3: HECTAREAS | B3: 0
D4: UNITARIO | J4: MES CASH FLOW
A5: Labores
A6: Disco,rastra y rolo | B6: 0 | C6: Uni | D6: =Cotizaciones!F8 -> 0 | E6: =B6*D6 -> 0
A7: Rolo picador | B7: 0 | C7: Uni | D7: =Cotizaciones!F18 -> 17 | E7: =B7*D7 -> 0
A8: Barbecho Quimico | B8: 0 | C8: Uni | D8: 7 | E8: =B8*D8 -> 0 | G8: 41061 | H8: 41122
A9: Barbecho Quimico | B9: 0 | C9: Uni | D9: 7 | E9: =B9*D9 -> 0
A10: Siembra Directa | B10: 1 | C10: Uni | D10: 55 | E10: =B10*D10 -> 55 | G10: 41183 | J10: FEBRERO
A11: Pulverizacion Post-emergente | B11: 1 | C11: Uni | D11: 7 | E11: =B11*D11 -> 7 | G11: 41184 | H11: 41215 | J11: FEBRERO
A12: Pulverizacion Post-emergente | B12: 0.5 | C12: Uni | D12: 7 | E12: =B12*D12 -> 3.5 | J12: FEBRERO
A13: Pulverizacion Pre-emergente | B13: 0 | C13: Uni | D13: 7 | E13: =B13*D13 -> 0
A14: Fertilización | B14: 1 | C14: Uni | D14: 30 | E14: =B14*D14 -> 30 | G14: 41184
A15: Fertilización | B15: 0 | C15: Uni | D15: =D14 -> 30 | E15: =B15*D15 -> 0
A16: Aplicación terrestre Fungicida | B16: 0 | C16: Uni | D16: =+Cotizaciones!F17 -> 5 | E16: =B16*D16 -> 0
A17: Aplicación aerea insecticida | B17: 0 | C17: Uni | D17: =+Cotizaciones!F16 -> 13 | E17: =B17*D17 -> 0
A18: Muestreo de suelos | B18: 0 | C18: Uni | D18: =+Cotizaciones!F15 -> 1 | E18: =B18*D18 -> 0 | G18: =+G8 -> 41061
A19: Analisis de suelos | B19: 0 | C19: Uni | D19: =+Cotizaciones!F5 -> 0 | E19: =B19*D19 -> 0
A20: Medicion satelital GPS | B20: 0 | C20: Uni | D20: =+Cotizaciones!F13 -> 0 | E20: =B20*D20 -> 0
C21: Total Labores | E21: =SUM(E6:E20) -> 95.5 | F21: =E21/E69 -> 0.14587948 | G21: =E21*D1 -> 0
A22: Semilla
A24: Semilla de Maiz curada | B24: 0.6875 | C24: Bolsa | D24: =Cotizaciones!E44 -> 180 | E24: =B24*D24 -> 123.75 | G24: =+A10 -> Siembra Directa | J24: FEBRERO
C25: Total Semilla | E25: =SUM(E24:E24) -> 123.75 | F25: =E25/E69 -> 0.18903231 | G25: =E25*D1 -> 0
A27: Arrendamiento | B27: 0.2 | C27: Uni | D27: =+B27*'Resumen Proy'!B56 -> 85.2 | E27: =+D27 -> 85.2
C28: Total Arrendamiento | E28: =E27 -> 85.2 | F28: =E28/E69 -> 0.13014588 | G28: =E28*D1 -> 0
A30: Gerenciamiento | B30: 10 | C30: USD / Ha | D30: =B30 -> 10 | E30: =D30 -> 10
C31: Total Gerenciamiento | E31: =E30 -> 10 | F31: =E31/E69 -> 0.015275338 | G31: =E31*D1 -> 0
A32: Fertilizantes
A33: Fosforados (MAP / DAP) | B33: 0.08 | C33: Ton. | D33: =Cotizaciones!I25+Cotizaciones!F26 -> 1025 | E33: =B33*D33 -> 82 | G33: =+A10 -> Siembra Directa | I33: =+E33*B3 -> 0 | J33: FEBRERO
A34: Nitrogenados (Urea) | B34: 0.16 | C34: Ton. | D34: =Cotizaciones!I34+Cotizaciones!F26 -> 645 | E34: =B34*D34 -> 103.2 | G34: =+A14 -> Fertilización | I34: =+E34*B3 -> 0 | J34: ENERO
C35: Total Fertilizantes | E35: =SUM(E33:E34) -> 185.2 | F35: =E35/E69 -> 0.28289926 | G35: =E35*D1 -> 0
A36: Agroquímicos
A37: Coadyuvante | B37: 0.15 | C37: Lts. | D37: =+Cotizaciones!I20 -> 20 | E37: =B37*D37 -> 3 | G37: =+A8 -> Barbecho Quimico | I37: =+A11 -> Pulverizacion Post-emergente | J37: MARZO
A38: Inoculante | B38: 0 | C38: Lts. | E38: =B38*D38 -> 0
A39: Sulfosato | B39: 4 | C39: Lts. | D39: 7.2 | E39: =B39*D39 -> 28.8 | G39: =+G37 -> Barbecho Quimico | I39: =+I37 -> Pulverizacion Post-emergente | J39: FEBRERO
A40: 2,4-D | B40: 0 | C40: Lts. | D40: 6.2 | E40: =B40*D40 -> 0 | G40: =+G39 -> Barbecho Quimico
A41: Picloran | B41: 0 | C41: Lts. | D41: =+Cotizaciones!I36 -> 7 | E41: =B41*D41 -> 0
A42: Fungicida | B42: 0 | C42: Lts. | D42: =+Cotizaciones!I26 -> 28 | E42: 0
A43: Atrazina | B43: 2 | C43: Lts. | D43: =+Cotizaciones!I10 -> 5.7 | E43: =B43*D43 -> 11.4 | G43: =+I37 -> Pulverizacion Post-emergente | J43: FEBRERO
A44: Flurocloridona | B44: 1 | C44: Lts. | D44: =+Cotizaciones!I24 -> 11.8 | E44: =B44*D44 -> 11.8 | G44: =+I37 -> Pulverizacion Post-emergente
A45: Karate Zeon | B45: 0 | C45: Lts. | D45: =+Cotizaciones!I31 -> 20 | E45: =B45*D45 -> 0 | G45: =+I37 -> Pulverizacion Post-emergente
C46: Total Agroquimicos | E46: =SUM(E37:E45) -> 55 | F46: =E46/E69 -> 0.084014359 | G46: =E46*D1 -> 0
A48: Cosecha | B48: 1 | C48: Hás. | D48: 90 | E48: =+D48*B48 -> 90
C49: Total Cosecha | E49: =E48 -> 90 | F49: =E49/E69 -> 0.13747804
A50: Comercialización
A51: Extraccion/Embolsado | B51: 0 | C51: U$ / ton | D51: =Cotizaciones!F24 -> 3.3 | E51: =D51*B51*B74 -> 0
A52: Silobolsa | B52: 0 | C52: 210 Tons | D52: =Cotizaciones!I41/210 -> 1.952381 | E52: =D52*B52*B74 -> 0
A53: Secada | B53: 3 | C53: U$ / ton | D53: =Cotizaciones!F30 -> 3 | E53: =+D53*B53*$B$76 -> 40.5
A55: Paritaria | B55: 1 | C55: U$ / ton | D55: =Cotizaciones!F35 -> 5 | E55: =+D55*B55*$B$76 -> 22.5
A56: Traspile | B56: 1 | C56: U$ / ton | D56: =Cotizaciones!F36/Cotizaciones!M20 -> 0.26541736 | E56: =+D56*B56*$B$76 -> 1.1943781
A57: Analisis | B57: 1 | C57: U$ / ton | D57: =+Cotizaciones!E5/Cotizaciones!M20 -> 0.53083473 | E57: =+D57*B57*$B$76 -> 2.3887563
A58: Flete | B58: 1 | C58: U$ / ton | D58: =+'Cebada SP'!D71 -> 20 | E58: =+D58*B58*$B$76 -> 90
A59: Comisión | B59: 1 | C59: % | D59: =+Cotizaciones!B13*'Maiz 2da'!B76% -> 9 | E59: =D59 -> 9
C60: Total Comercialización | E60: =SUM(E53:E59) -> 165.58313 | F60: =E60/E69 -> 0.25293383
A63: Seguro (Granizo) | B63: 1 | C63: % Costo | D63: =B63%*1000 -> 10 | E63: =D63 -> 10
C64: Total Seguro | E64: =E63 -> 10 | F64: =E64/E69 -> 0.015275338
A66: Costos Financiero | B66: 0 | C66: % | D66: 0 | E66: 0
C67: Total Costo Financ. | E67: 0
C69: Costo Total | E69: =E21+E25+E28+E31+E35+E46+E49+E64+E67 -> 654.65 | F69: =F21+F25+F28+F31+F35+F46+F49+F60+F64 -> 1.2529338
A71: Precio bruto | E71: =+Cotizaciones!B13 -> 200
A72: Gastos Comerciales/tn | E72: =+E60/B76 -> 36.796252 | F72: =+E72/E71 -> 0.18398126
A73: Precio Neto Estimado | E73: =+E71-E72 -> 163.20375
A76: Rendimiento Estimado | B76: 4.5 | C76: Ton/Ha. | D76: Ceb/maiz
A77: Precio Estimado | B77: =+E73 -> 163.20375 | C77: Ton
A78: Costo Total | B78: =E21+E25+E28+E31+E35+E46+E49+E64+E67 -> 654.65 | C78: Ha | D78: =+B78+'Cebada SP'!B82 -> 1699.36
A79: Ingreso Bruto (2% IB) | B79: =+B77*B76*0.98 -> 719.72853 | C79: Ha | D79: =+B79+'Cebada SP'!B84 -> 1872.4654
A80: Margen | B80: =B79-B78 -> 65.078528 | C80: Ha | D80: =+D79-D78 -> 173.10537
A81: Retorno | B81: =B80/B78 -> 0.099409651 | D81: =+D80/D78 -> 0.10186504
A82: Rendimiento de Indiferencia | B82: =+B78/E73 -> 4.0112437
A83: Inversión Real | B83: =E21+E25+E28*0.8+E31*0.9+E35+E46+E67 -> 536.61 | C83: Ha | D83: =+B83+'Cebada SP'!B88 -> 1476.32
A84: Retorno Real | B84: =B80/B83 -> 0.12127714 | D84: =+D80/D83 -> 0.11725464
A87: Costo Total | C87: =E69 -> 654.65
A88: Rentabilidad (%)
A89: Px/Rinde | B89: =E89-1.5 -> 3 | C89: =E89-1 -> 3.5 | D89: =E89-0.5 -> 4 | E89: =B76 -> 4.5 | F89: =E89+0.5 -> 5 | G89: =E89+0.8 -> 5.3 | H89: =E89+1.2 -> 5.7
A90: =A91-10 -> 133.20375 | B90: =B99/C87*100 -> -38.958032 | C90: =C99/C87*100 -> -28.784371 | D90: =D99/C87*100 -> -18.610709 | E90: =E99/C87*100 -> -8.4370479 | F90: =F99/C87*100 -> 1.7366134 | G90: =G99/C87*100 -> 7.8408102 | H90: =H99/C87*100 -> 15.979739
A91: =A92-10 -> 143.20375 | B91: =B100/C87*100 -> -34.375431 | C91: =C100/C87*100 -> -23.438002 | D91: =D100/C87*100 -> -12.500574 | E91: =E100/C87*100 -> -1.5631459 | F91: =F100/C87*100 -> 9.3742824 | G91: =G100/C87*100 -> 15.936739 | H91: =H100/C87*100 -> 24.686682
A92: =A93-10 -> 153.20375 | B92: =B101/C87*100 -> -29.792829 | C92: =C101/C87*100 -> -18.091634 | D92: =D101/C87*100 -> -6.3904389 | E92: =E101/C87*100 -> 5.3107562 | F92: =F101/C87*100 -> 17.011951 | G92: =G101/C87*100 -> 24.032668 | H92: =H101/C87*100 -> 33.393625
A93: =B77 -> 163.20375 | B93: =B102/C87*100 -> -25.210228 | C93: =C102/C87*100 -> -12.745266 | D93: =D102/C87*100 -> -0.28030373 | E93: =E102/C87*100 -> 12.184658 | F93: =F102/C87*100 -> 24.64962 | G93: =G102/C87*100 -> 32.128598 | H93: =H102/C87*100 -> 42.100567
A94: =A93+10 -> 173.20375 | B94: =B103/C87*100 -> -20.627626 | C94: =C103/C87*100 -> -7.3988975 | D94: =D103/C87*100 -> 5.8298315 | E94: =E103/C87*100 -> 19.05856 | F94: =F103/C87*100 -> 32.287289 | G94: =G103/C87*100 -> 40.224527 | H94: =H103/C87*100 -> 50.80751
A95: =A94+10 -> 183.20375 | B95: =B104/C87*100 -> -16.045025 | C95: =C104/C87*100 -> -2.0525292 | D95: =D104/C87*100 -> 11.939967 | E95: =E104/C87*100 -> 25.932462 | F95: =F104/C87*100 -> 39.924958 | G95: =G104/C87*100 -> 48.320456 | H95: =H104/C87*100 -> 59.514452
A96: =A95+10 -> 193.20375 | B96: =B105/C87*100 -> -11.462424 | C96: =C105/C87*100 -> 3.2938391 | D96: =D105/C87*100 -> 18.050102 | E96: =E105/C87*100 -> 32.806365 | F96: =F105/C87*100 -> 47.562627 | G96: =G105/C87*100 -> 56.416385 | H96: =H105/C87*100 -> 68.221395
A97: MB Maiz
A98: Px/Rinde | B98: =E98-1.5 -> 3 | C98: =E98-1 -> 3.5 | D98: =E98-0.5 -> 4 | E98: =B76 -> 4.5 | F98: =E98+0.5 -> 5 | G98: =E98+0.8 -> 5.3 | H98: =E98+1.2 -> 5.7
A99: =A100-10 -> 133.20375 | B99: =(B98*A99)-C87 -> -255.03876 | C99: =(C98*A99)-C87 -> -188.43688 | D99: =(D98*A99)-C87 -> -121.83501 | E99: =(E98*A99)-C87 -> -55.233134 | F99: =(F98*A99)-C87 -> 11.36874 | G99: =(G98*A99)-C87 -> 51.329864 | H99: =(H98*A99)-C87 -> 104.61136
A100: =A101-10 -> 143.20375 | B100: =(B98*A100)-C87 -> -225.03876 | C100: =(C98*A100)-C87 -> -153.43688 | D100: =(D98*A100)-C87 -> -81.835008 | E100: =(E98*A100)-C87 -> -10.233134 | F100: =(F98*A100)-C87 -> 61.36874 | G100: =(G98*A100)-C87 -> 104.32986 | H100: =(H98*A100)-C87 -> 161.61136
A101: =A102-10 -> 153.20375 | B101: =(A101*B98)-C87 -> -195.03876 | C101: =(C98*A101)-C87 -> -118.43688 | D101: =(D98*A101)-C87 -> -41.835008 | E101: =(E98*A101)-C87 -> 34.766866 | F101: =(F98*A101)-C87 -> 111.36874 | G101: =(G98*A101)-C87 -> 157.32986 | H101: =(H98*A101)-C87 -> 218.61136
A102: =B77 -> 163.20375 | B102: =(A102*B98)-C87 -> -165.03876 | C102: =(A102*C98)-C87 -> -83.436882 | D102: =(D98*A102)-C87 -> -1.8350084 | E102: =(A102*E98)-C87 -> 79.766866 | F102: =(A102*F98)-C87 -> 161.36874 | G102: =(G98*A102)-C87 -> 210.32986 | H102: =(H98*A102)-C87 -> 275.61136
A103: =A102+10 -> 173.20375 | B103: =(A103*B98)-C87 -> -135.03876 | C103: =(C98*A103)-C87 -> -48.436882 | D103: =(D98*A103)-C87 -> 38.164992 | E103: =(E98*A103)-C87 -> 124.76687 | F103: =(F98*A103)-C87 -> 211.36874 | G103: =(G98*A103)-C87 -> 263.32986 | H103: =(H98*A103)-C87 -> 332.61136
A104: =A103+10 -> 183.20375 | B104: =(A104*B98)-C87 -> -105.03876 | C104: =(C98*A104)-C87 -> -13.436882 | D104: =(D98*A104)-C87 -> 78.164992 | E104: =(E98*A104)-C87 -> 169.76687 | F104: =(F98*A104)-C87 -> 261.36874 | G104: =(G98*A104)-C87 -> 316.32986 | H104: =(H98*A104)-C87 -> 389.61136
A105: =A104+10 -> 193.20375 | B105: =(B98*A105)-C87 -> -75.038756 | C105: =(C98*A105)-C87 -> 21.563118 | D105: =(D98*A105)-C87 -> 118.16499 | E105: =(E98*A105)-C87 -> 214.76687 | F105: =(F98*A105)-C87 -> 311.36874 | G105: =(G98*A105)-C87 -> 369.32986 | H105: =(A105*H98)-C87 -> 446.61136

Sheet Girasol 2da
A1: Proyección Girasol SS
A3: HECTAREAS | B3: 0
B5: CANTIDAD | C5: UNIDAD | D5: PRECIO | E5: TOTAL / HA | G5: Total
D6: UNITARIO | J6: MES CASH FLOW
A7: Labores | E7: 450
A8: Siembra | B8: 1 | C8: Uni | D8: 52 | E8: =B8*D8 -> 52 | G8: 40970 | J8: ENERO
A9: Pulverizacion Pre-emergente | B9: 2 | C9: Uni | D9: 6 | E9: =B9*D9 -> 12 | G9: 41030 | J9: FEBRERO
A10: Aplicación terrestre Fungicida/Insecticida | B10: 1 | C10: Uni | D10: =+Cotizaciones!F16 -> 13 | E10: =B10*D10 -> 13 | G10: 41061 | H10: 41123 | J10: MARZO
A11: Muestreo de suelos | B11: 0 | C11: Uni | D11: =+Cotizaciones!F15 -> 1 | E11: =B11*D11 -> 0 | G11: 40969
A12: Fertilizacion | B12: 1 | C12: Uni | D12: 27 | E12: =B12*D12 -> 27 | G12: 40969
A13: Medicion satelital GPS | B13: 0 | C13: Uni | D13: 0 | E13: =B13*D13 -> 0
A14: Monitoreo de BB y B | B14: 0 | C14: Uni | D14: =+Cotizaciones!F14 -> 5 | E14: =+B14*D14 -> 0
A15: Aplicación de Cebo | B15: 0 | D15: =+Cotizaciones!F6 -> 5 | E15: =+D15*B15 -> 0
C16: Total Labores | E16: =SUM(E8:E15) -> 104 | F16: =E16/E60 -> 0.20499343 | G16: =E16*#REF! -> #REF!
A17: Semilla
A19: semilla Girasol | B19: 0.27777778 | C19: Kgs. | D19: =+Cotizaciones!E42 -> 300 | E19: =B19*D19 -> 83.333333 | G19: =+A8 -> Siembra | J19: FEBRERO
C20: Total Semilla | E20: =SUM(E19:E19) -> 83.333333 | F20: =E20/E60 -> 0.16425756 | G20: =E20*#REF! -> #REF!
A22: Arrendamiento | B22: 0.2 | C22: Uni | D22: =+'Resumen Proy'!C57 -> 426 | E22: =B22*D22 -> 85.2
C23: Total Arrendamiento | E23: =E22 -> 85.2 | F23: =E23/E60 -> 0.16793693 | G23: =E23*#REF! -> #REF!
A25: Gerenciamiento | B25: 1 | C25: USD / Ha | D25: 10 | E25: =D25 -> 10
C26: Total Gerenciamiento | E26: =E25 -> 10 | F26: =E26/E60 -> 0.019710907 | G26: =E26*#REF! -> #REF!
A28: Fertilizantes
A29: Fosforados (S10) | B29: 0.04 | C29: Ton. | D29: =Cotizaciones!I25+Cotizaciones!F26 -> 1025 | E29: =B29*D29 -> 41 | G29: =+A8 -> Siembra | J29: FEBRERO
A30: Nitrogenados (Solmix) | B30: 0.06 | C30: Ton. | D30: =Cotizaciones!F26+Cotizaciones!I34 -> 645 | E30: =B30*D30 -> 38.7 | G30: =+#REF! -> #REF!
C31: Total Fertilizantes | E31: =SUM(E29:E30) -> 79.7 | F31: =E31/E60 -> 0.15709593 | G31: =E31*#REF! -> #REF!
A32: Agroquímicos
A33: clearsol | B33: =+'Girasol SP'!B46 -> 0.08 | C33: Lts. | D33: =+'Girasol SP'!D46 -> 170 | E33: =B33*D33 -> 13.6 | G33: =+#REF! -> #REF! | J33: MARZO
A34: Glifosato | B34: 1 | C34: Lts. | D34: =+Cotizaciones!I28 -> 4.5 | E34: =B34*D34 -> 4.5 | G34: =+A9 -> Pulverizacion Pre-emergente | J34: MARZO
A35: Flurocloridona | B35: 1 | C35: Lts. | D35: =+Cotizaciones!I24 -> 11.8 | E35: =B35*D35 -> 11.8 | G35: =+A9 -> Pulverizacion Pre-emergente | J35: MARZO
A36: Paraquat | B36: 2 | C36: Lts. | D36: =+Cotizaciones!I45 -> 2.6 | E36: =B36*D36 -> 5.2 | G36: =+#REF! -> #REF! | J36: MARZO
A37: Fungicida | B37: 1 | C37: Lts. | D37: =+Cotizaciones!I8 -> 20 | E37: =B37*D37 -> 20
A38: Intrepid | B38: 0.12 | C38: Lts. | D38: =+Cotizaciones!I30 -> 100 | E38: =B38*D38 -> 12 | G38: =+#REF! -> #REF! | J38: MARZO
C39: Total Agroquimicos | E39: =SUM(E33:E38) -> 67.1 | F39: =E39/E60 -> 0.13226018 | G39: =E39*#REF! -> #REF!
A41: Cosecha | B41: 1 | C41: Hás. | D41: 70 | E41: =+D41*B41 -> 70 | J41: MAYO
C42: Total Cosecha | E42: =E41 -> 70 | F42: =E42/E60 -> 0.13797635
A43: Comercialización
A44: Extraccion/Embolsado | B44: 0 | C44: U$ / ton | D44: =Cotizaciones!F24 -> 3.3 | E44: =D44*B44*B68 -> 0 | J44: MAYO
A45: Silobolsa | B45: 0 | C45: 210 Tons | D45: =Cotizaciones!I45/210 -> 0.012380952 | E45: =D45*B45*B68 -> 0 | J45: MAYO
A46: Secada | B46: 2 | C46: $ / ton | D46: 2.5 | E46: =+D46*B46*B69 -> 6.5 | J46: MAYO
A47: Paritaria | B47: 1 | C47: $ / ton | D47: 7 | E47: =+D47*B47*B69 -> 9.1 | J47: MAYO
A48: Traspile | B48: 1 | C48: $ / ton | D48: =+Cotizaciones!F36/Cotizaciones!M19 -> 0.26888687 | E48: =+D48*B48*B69 -> 0.34955293 | J48: MAYO
A49: Analisis | B49: 1 | C49: $ / ton | D49: =+Cotizaciones!E5/Cotizaciones!M20 -> 0.53083473 | E49: =+D49*B49*$B$69 -> 0.69008514 | J49: MAYO
A50: Flete | B50: 1 | C50: $ / ton | D50: =Cotizaciones!F25 -> 20 | E50: =B50*D50*B69 -> 26 | J50: MAYO
A51: Comisión | B51: 1.5 | C51: % | D51: =B51%*B69*Cotizaciones!B12 -> 8.775 | E51: =D51 -> 8.775 | J51: MAYO
C52: Total Comercialización | E52: =SUM(E44:E51) -> 51.414638 | F52: =E52/E60 -> 0.10134291
A54: Seguro (Granizo) | B54: 2.2 | D54: 8 | E54: =+D54 -> 8 | J54: MAYO
C55: Total Seguro | E55: =+E54 -> 8 | F55: =E55/E60 -> 0.015768725
A57: Costos Financiero | B57: 1.5 | C57: % | D57: 6 | E57: 0
C58: Total Costo Financ. | E58: =E57 -> 0 | F58: =E58/E60 -> 0
C60: Costo Total | E60: =E16+E20+E23+E26+E31+E39+E42+E55+E58 -> 507.33333 | F60: =F58+F55+F52+F42+F39+F31+F26+F23+F20+F16 -> 1.1013429
A62: Precio bruto | E62: 450
A63: Gastos Comerciales/tn | E63: =+E52/B69 -> 39.549722 | F63: =+E63/E62 -> 0.08788827
A64: Precio Neto Estimado | E64: =+E62-E63 -> 410.45028
A69: Rendimiento Estimado | B69: 1.3 | C69: Ton/Ha.
A70: Precio Estimado | B70: =+E64 -> 410.45028 | C70: Ton
A71: bonif 10% | B71: =+B70*1.1 -> 451.49531
A72: Costo Total | B72: =E60 -> 507.33333 | C72: Ha
A73: Ingreso Bruto | B73: =+B70*B69*0.98 -> 522.91365 | C73: Ha
A74: Margen | B74: =+B73-E60 -> 15.580321 | C74: Ha
A75: Retorno | B75: =B74/E60 -> 0.030710226
A76: Rendimiento de Indiferencia | B76: =+B72/B71 -> 1.1236735
A77: Inversión Real | B77: =E16+E23*0.8+E26*0.9+E31+E39+E20 -> 411.29333 | C77: Ha
A78: Retorno Real | B78: =B74/B77 -> 0.037881288
A80: Costo Total | C80: =E60 -> 507.33333
A81: Rentabilidad (%)
A82: Px/Rinde | B82: =E82-1.5 -> -0.2 | C82: =E82-1 -> 0.3 | D82: =E82-0.5 -> 0.8 | E82: =B69 -> 1.3 | F82: =E82+0.5 -> 1.8 | G82: =E82+0.8 -> 2.1 | H82: =E82+1.2 -> 2.5
A83: =A84-10 -> 380.45028 | B83: =B92/C80*100 -> -114.99804 | C83: =C92/C80*100 -> -77.50294 | D83: =D92/C80*100 -> -40.00784 | E83: =E92/C80*100 -> -2.5127408 | F83: =F92/C80*100 -> 34.982359 | G83: =G92/C80*100 -> 57.479419 | H83: =H92/C80*100 -> 87.475499
A84: =A85-10 -> 390.45028 | B84: =B93/C80*100 -> -115.39226 | C84: =C93/C80*100 -> -76.911613 | D84: =D93/C80*100 -> -38.430968 | E84: =E93/C80*100 -> 0.04967712 | F84: =F93/C80*100 -> 38.530322 | G84: =G93/C80*100 -> 61.618709 | H84: =H93/C80*100 -> 92.403225
A85: =A86-10 -> 400.45028 | B85: =B94/C80*100 -> -115.78648 | C85: =C94/C80*100 -> -76.320286 | D85: =D94/C80*100 -> -36.854095 | E85: =E94/C80*100 -> 2.612095 | F85: =F94/C80*100 -> 42.078285 | G85: =G94/C80*100 -> 65.758 | H85: =H94/C80*100 -> 97.330952
A86: =B70 -> 410.45028 | B86: =B95/C80*100 -> -116.18069 | C86: =C95/C80*100 -> -75.728959 | D86: =D95/C80*100 -> -35.277223 | E86: =E95/C80*100 -> 5.1745129 | F86: =F95/C80*100 -> 45.626249 | G86: =G95/C80*100 -> 69.89729 | H86: =H95/C80*100 -> 102.25868
A87: =A86+10 -> 420.45028 | B87: =B96/C80*100 -> -116.57491 | C87: =C96/C80*100 -> -75.137631 | D87: =D96/C80*100 -> -33.70035 | E87: =E96/C80*100 -> 7.7369307 | F87: =F96/C80*100 -> 49.174212 | G87: =G96/C80*100 -> 74.03658 | H87: =H96/C80*100 -> 107.18641
A88: =A87+10 -> 430.45028 | B88: =B97/C80*100 -> -116.96913 | C88: =C97/C80*100 -> -74.546304 | D88: =D97/C80*100 -> -32.123478 | E88: =E97/C80*100 -> 10.299349 | F88: =F97/C80*100 -> 52.722175 | G88: =G97/C80*100 -> 78.175871 | H88: =H97/C80*100 -> 112.11413
A89: =A88+10 -> 440.45028 | B89: =B98/C80*100 -> -117.36335 | C89: =C98/C80*100 -> -73.954977 | D89: =D98/C80*100 -> -30.546605 | E89: =E98/C80*100 -> 12.861766 | F89: =F98/C80*100 -> 56.270138 | G89: =G98/C80*100 -> 82.315161 | H89: =H98/C80*100 -> 117.04186
A90: MB
A91: Px/Rinde | B91: =E91-1.5 -> -0.2 | C91: =E91-1 -> 0.3 | D91: =E91-0.5 -> 0.8 | E91: =B69 -> 1.3 | F91: =E91+0.5 -> 1.8 | G91: =E91+0.8 -> 2.1 | H91: =E91+1.2 -> 2.5
A92: =A93-10 -> 380.45028 | B92: =(B91*A92)-C80 -> -583.42339 | C92: =(C91*A92)-C80 -> -393.19825 | D92: =(D91*A92)-C80 -> -202.97311 | E92: =(E91*A92)-C80 -> -12.747971 | F92: =(F91*A92)-C80 -> 177.47717 | G92: =(G91*A92)-C80 -> 291.61225 | H92: =(H91*A92)-C80 -> 443.79236
A93: =A94-10 -> 390.45028 | B93: =(B91*A93)-C80 -> -585.42339 | C93: =(C91*A93)-C80 -> -390.19825 | D93: =(D91*A93)-C80 -> -194.97311 | E93: =(E91*A93)-C80 -> 0.25202859 | F93: =(F91*A93)-C80 -> 195.47717 | G93: =(G91*A93)-C80 -> 312.61225 | H93: =(H91*A93)-C80 -> 468.79236
A94: =A95-10 -> 400.45028 | B94: =(A94*B91)-C80 -> -587.42339 | C94: =(C91*A94)-C80 -> -387.19825 | D94: =(D91*A94)-C80 -> -186.97311 | E94: =(E91*A94)-C80 -> 13.252029 | F94: =(F91*A94)-C80 -> 213.47717 | G94: =(G91*A94)-C80 -> 333.61225 | H94: =(H91*A94)-C80 -> 493.79236
A95: =B70 -> 410.45028 | B95: =(A95*B91)-C80 -> -589.42339 | C95: =(A95*C91)-C80 -> -384.19825 | D95: =(D91*A95)-C80 -> -178.97311 | E95: =(A95*E91)-C80 -> 26.252029 | F95: =(A95*F91)-C80 -> 231.47717 | G95: =(G91*A95)-C80 -> 354.61225 | H95: =(H91*A95)-C80 -> 518.79236
A96: =A95+10 -> 420.45028 | B96: =(A96*B91)-C80 -> -591.42339 | C96: =(C91*A96)-C80 -> -381.19825 | D96: =(D91*A96)-C80 -> -170.97311 | E96: =(E91*A96)-C80 -> 39.252029 | F96: =(F91*A96)-C80 -> 249.47717 | G96: =(G91*A96)-C80 -> 375.61225 | H96: =(H91*A96)-C80 -> 543.79236
A97: =A96+10 -> 430.45028 | B97: =(A97*B91)-C80 -> -593.42339 | C97: =(C91*A97)-C80 -> -378.19825 | D97: =(D91*A97)-C80 -> -162.97311 | E97: =(E91*A97)-C80 -> 52.252029 | F97: =(F91*A97)-C80 -> 267.47717 | G97: =(G91*A97)-C80 -> 396.61225 | H97: =(H91*A97)-C80 -> 568.79236
A98: =A97+10 -> 440.45028 | B98: =(B91*A98)-C80 -> -595.42339 | C98: =(C91*A98)-C80 -> -375.19825 | D98: =(D91*A98)-C80 -> -154.97311 | E98: =(E91*A98)-C80 -> 65.252029 | F98: =(F91*A98)-C80 -> 285.47717 | G98: =(G91*A98)-C80 -> 417.61225 | H98: =(A98*H91)-C80 -> 593.79236

Sheet Soja 2da. Co
A1: Proyección Soja 2da SS
A3: HECTAREAS | B3: ='Resumen Proy'!B11+'Resumen Proy'!B27 -> 0
D5: UNITARIO | J5: MES CASH FLOW
A6: Labores
A7: Disco,rastra y rolo | B7: 0 | C7: Uni | D7: =Cotizaciones!F8 -> 0 | E7: =B7*D7 -> 0
A8: Rolo picador | B8: 0 | C8: Uni | D8: =Cotizaciones!F18 -> 17 | E8: =B8*D8 -> 0
A9: Barbecho Quimico | B9: 0 | C9: Uni | D9: =Cotizaciones!F17 -> 5 | E9: =B9*D9 -> 0
A10: Siembra Directa | B10: 1 | C10: Uni | D10: =Cotizaciones!F22 -> 42 | E10: =B10*D10 -> 42 | H10: 41245 | J10: ENERO
A11: Pulverizacion Herbicida | B11: 1 | C11: Uni | D11: =Cotizaciones!F17 -> 5 | E11: =B11*D11 -> 5 | H11: 40909 | I11: 40940 | J11: ENERO
A12: Pulverizacion Herbicida | B12: 1 | C12: Uni | D12: =D11 -> 5 | E12: =B12*D12 -> 5 | J12: MARZO
A13: Aplicación terrestre Insecticida | B13: 1 | C13: Uni | D13: =Cotizaciones!F10 -> 0 | E13: =B13*D13 -> 0 | H13: 40941 | J13: MARZO
A14: Muestreo de suelos | B14: 0 | C14: Uni | D14: =Cotizaciones!F15 -> 1 | E14: =B14*D14 -> 0
A15: Analisis de suelos | B15: 0 | C15: Uni | D15: =Cotizaciones!F5 -> 0 | E15: =B15*D15 -> 0
A16: Medicion satelital GPS | B16: 0 | C16: Uni | D16: =Cotizaciones!F13 -> 0 | E16: =B16*D16 -> 0
A17: Limpieza e inoculada | B17: 1 | C17: Uni | D17: =Cotizaciones!F12 -> 0 | E17: =(B21*D17)/1000 -> 0 | H17: 41244 | J17: ENERO
C18: Total Labores | E18: =SUM(E7:E17) -> 52 | F18: =E18/E67 -> 0.074410352 | G18: =E18*D1 -> 0
A19: Semilla
A21: Semilla de Soja | B21: 100 | C21: Kgs. | D21: =Cotizaciones!E46/1000 -> 0.355 | E21: =B21*D21 -> 35.5 | H21: 41215 | J21: ENERO
C22: Total Semilla | E22: =SUM(E21:E21) -> 35.5 | F22: =E22/E67 -> 0.050799375 | G22: =E22*D1 -> 0
A24: Arrendamiento | B24: 1 | C24: Uni | D24: ='Resumen Proy'!D11 -> 426 | E24: =B24*D24 -> 426
C25: Total Arrendamiento | E25: =E24 -> 426 | F25: =E25/E67 -> 0.6095925
A27: Gerenciamiento | B27: 8 | C27: USD / Ha | D27: =B27 -> 8 | E27: =D27 -> 8
C28: Total Gerenciamiento | E28: =E27 -> 8
A30: Fertilizantes
A31: Fosforados ( puesto en el campo ) | B31: 0 | C31: Ton. | D31: 0 | E31: =B31*D31 -> 0
A32: Arrancador Azufrado | B32: 0 | C32: Ton. | D32: 0 | E32: =B32*D32 -> 0
C33: Total Fertilizantes | E33: =SUM(E31:E32) -> 0
A34: Agroquímicos
A35: Aceite | B35: 0.5 | C35: Lts. | D35: =Cotizaciones!I6 -> 3 | E35: =B35*D35 -> 1.5 | H35: =A13 -> Aplicación terrestre Insecticida | J35: ENERO/MARZO
A36: Coayudante | B36: 0.3 | C36: Lts. | D36: =Cotizaciones!I20 -> 20 | E36: =B36*D36 -> 6 | H36: =A11 -> Pulverizacion Herbicida | J36: ENERO/MARZO
A37: Sulfato de Amonio | B37: 2 | C37: Lts. | D37: =Cotizaciones!I42 -> 1.1 | E37: =B37*D37 -> 2.2 | H37: =H36 -> Pulverizacion Herbicida | J37: ENERO/MARZO
A38: Inoculante | B38: =B21/2500 -> 0.04 | C38: Pack 2,5 Ton | D38: =Cotizaciones!I29 -> 250 | E38: =(D38*B38) -> 10 | H38: =A10 -> Siembra Directa | J38: ENERO
A39: Glifosato | B39: 7 | C39: Lts. | D39: =Cotizaciones!I28 -> 4.5 | E39: =B39*D39 -> 31.5 | H39: =H36 -> Pulverizacion Herbicida | J39: ENERO/MARZO
A40: 2,4-D | B40: 0 | C40: Lts. | D40: =Cotizaciones!I5 -> 4.6 | E40: =B40*D40 -> 0
A41: Clorimuron | B41: 0.05 | C41: Lts. | D41: =Cotizaciones!I18 -> 22.05 | E41: =B41*D41 -> 1.1025 | J41: ENERO
A42: Cipermetrina | B42: 0 | C42: Lts. | D42: =Cotizaciones!I15 -> 20 | E42: =B42*D42 -> 0 | H42: =H35 -> Aplicación terrestre Insecticida | J42: MARZO
A43: Clorpirifos | B43: 0.4 | C43: Lts. | D43: =Cotizaciones!I19 -> 7 | E43: =B43*D43 -> 2.8 | H43: =H35 -> Aplicación terrestre Insecticida | J43: MARZO
A44: Intrepid | B44: 0.12 | C44: Lts. | D44: =Cotizaciones!I30 -> 100 | E44: =B44*D44 -> 12 | J44: MARZO
C45: Total Agroquimicos | E45: =SUM(E35:E44) -> 67.1025 | F45: =E45/E67 -> 0.09602155 | G45: =E45*D1 -> 0
A47: Cosecha | B47: 1 | C47: Hás. | D47: 65 | E47: =+D47*B47 -> 65 | H47: 41031
E48: =E47 -> 65 | F48: =E48/E67 -> 0.09301294
A49: Comercialización
A50: Extraccion/Embolsado | B50: 0 | C50: U$ / ton | D50: =Cotizaciones!F24 -> 3.3 | E50: =D50*B50*B71 -> 0
A51: Silobolsa | B51: 0 | C51: 210 Tons | D51: =Cotizaciones!I41/210 -> 1.952381 | E51: =D51*B51*B72 -> 0
A52: Secada | B52: 0 | C52: U$ / ton | D52: =Cotizaciones!F33 -> 3 | E52: =+D52*B52*$B$71 -> 0
A53: Paritaria | B53: 0.5 | C53: U$ / ton | D53: =Cotizaciones!F35 -> 5 | E53: =+D53*B53*$B$71 -> 3.75
A54: Traspile | B54: 0.5 | C54: U$ / ton | D54: =Cotizaciones!F36 -> 6.5 | E54: =+D54*B54*$B$71 -> 4.875
A55: Analisis | B55: 1 | C55: U$ / ton | D55: =Cotizaciones!F5 -> 0 | E55: =+D55*B55*$B$71 -> 0
A56: Flete | B56: 1 | C56: U$ / ton | D56: =Cotizaciones!F25 -> 20 | E56: =+D56*B56*$B$71 -> 30
A57: Comisión | B57: 0 | C57: % | D57: =B57%*B74 -> 0 | E57: =D57 -> 0
C58: Total Comercialización | E58: =SUM(E52:E57) -> 38.625 | F58: =E58/E67 -> 0.055271151
A61: Seguro (Granizo) | B61: 2.2 | C61: % Costo | D61: =B61%*300 -> 6.6 | E61: =D61 -> 6.6
C62: Total Seguro | E62: =E61 -> 6.6 | F62: =E62/E67 -> 0.0094443908
A64: Costos Financiero | B64: 0 | C64: % | D64: 0 | E64: =(E45+E33+E25+E18)*D64/100 -> 0
C65: Total Costo Financ.
C67: Costo Total | E67: =E18+E22+E25+E28+E33+E45+E48+E58+E62+E65 -> 698.8275 | F67: =F62+F58+F48+F45+F22+F18+F25 -> 0.98855225
E68: =+E67*B3 -> 0
A71: Rendimiento Estimado | B71: 1.5 | C71: Ton/Ha.
A72: Precio Estimado | B72: =Cotizaciones!B14 -> 355 | C72: Ton.
A73: Costo Total | B73: =E18+E22+E25+E28+E33+E45+E48+E58+E62+E65 -> 698.8275 | C73: Ton
A74: Ingreso Bruto | B74: =+B72*B71 -> 532.5 | C74: Ha | D74: =+B74*B3 -> 0
A75: Margen | B75: =+B74-E67 -> -166.3275 | C75: Ha
A76: Retorno | B76: =B75/E67 -> -0.23800938
A77: Rendimiento de Indiferencia | B77: =(E18+E22+E25+E33+E45+E62+E48+E28)/(B72-B57%*B72-D50*B50-D51*B51-D54*B54-D55*B55-D56*B56-D52*B52-D53*B53) -> 2.0051708
A78: Inversión Real | B78: =E18+E22+E25*0.8+(E28*0.9)+E33+E45 -> 502.6025
A79: Retorno Real | B79: =B75/B78 -> -0.3309325
A81: Costo Total | C81: =E67 -> 698.8275
A82: Retorno (%)
A83: Px/Rinde | B83: =E83-1.5 -> 0 | C83: =E83-1 -> 0.5 | D83: =E83-0.5 -> 1 | E83: =B71 -> 1.5 | F83: =E83+0.5 -> 2 | G83: =E83+0.8 -> 2.3 | H83: =E83+1.2 -> 2.7
A84: =A85-10 -> 325 | B84: =B93/C81*100 -> -100 | C84: =C93/C81*100 -> -76.746765 | D84: =D93/C81*100 -> -53.49353 | E84: =E93/C81*100 -> -30.240295 | F84: =F93/C81*100 -> -6.9870605 | G84: =G93/C81*100 -> 6.9648805 | H84: =H93/C81*100 -> 25.567468
A85: =A86-10 -> 335 | B85: =B94/C81*100 -> -100 | C85: =C94/C81*100 -> -76.031281 | D85: =D94/C81*100 -> -52.062562 | E85: =E94/C81*100 -> -28.093843 | F85: =F94/C81*100 -> -4.1251239 | G85: =G94/C81*100 -> 10.256108 | H85: =H94/C81*100 -> 29.431083
A86: =A87-10 -> 345 | B86: =B95/C81*100 -> -100 | C86: =C95/C81*100 -> -75.315797 | D86: =D95/C81*100 -> -50.631594 | E86: =E95/C81*100 -> -25.94739 | F86: =F95/C81*100 -> -1.2631873 | G86: =G95/C81*100 -> 13.547335 | H86: =H95/C81*100 -> 33.294697
A87: =B72 -> 355 | B87: =B96/C81*100 -> -100 | C87: =C96/C81*100 -> -74.600313 | D87: =D96/C81*100 -> -49.200625 | E87: =E96/C81*100 -> -23.800938 | F87: =F96/C81*100 -> 1.5987493 | G87: =G96/C81*100 -> 16.838562 | H87: =H96/C81*100 -> 37.158312
A88: =A87+10 -> 365 | B88: =B97/C81*100 -> -100 | C88: =C97/C81*100 -> -73.884829 | D88: =D97/C81*100 -> -47.769657 | E88: =E97/C81*100 -> -21.654486 | F88: =F97/C81*100 -> 4.4606859 | G88: =G97/C81*100 -> 20.129789 | H88: =H97/C81*100 -> 41.021926
A89: =A88+10 -> 375 | B89: =B98/C81*100 -> -100 | C89: =C98/C81*100 -> -73.169344 | D89: =D98/C81*100 -> -46.338689 | E89: =E98/C81*100 -> -19.508033 | F89: =F98/C81*100 -> 7.3226225 | G89: =G98/C81*100 -> 23.421016 | H89: =H98/C81*100 -> 44.88554
A90: =A89+10 -> 385 | B90: =B99/C81*100 -> -100 | C90: =C99/C81*100 -> -72.45386 | D90: =D99/C81*100 -> -44.90772 | E90: =E99/C81*100 -> -17.361581 | F90: =F99/C81*100 -> 10.184559 | G90: =G99/C81*100 -> 26.712243 | H90: =H99/C81*100 -> 48.749155
A91: MB
A92: Px/Rinde | B92: =E92-1.5 -> 0 | C92: =E92-1 -> 0.5 | D92: =E92-0.5 -> 1 | E92: =B71 -> 1.5 | F92: =E92+0.5 -> 2 | G92: =E92+0.8 -> 2.3 | H92: =E92+1.2 -> 2.7
A93: =A94-10 -> 325 | B93: =(B92*A93)-C81 -> -698.8275 | C93: =(C92*A93)-C81 -> -536.3275 | D93: =(D92*A93)-C81 -> -373.8275 | E93: =(E92*A93)-C81 -> -211.3275 | F93: =(F92*A93)-C81 -> -48.8275 | G93: =(G92*A93)-C81 -> 48.6725 | H93: =(H92*A93)-C81 -> 178.6725
A94: =A95-10 -> 335 | B94: =(B92*A94)-C81 -> -698.8275 | C94: =(C92*A94)-C81 -> -531.3275 | D94: =(D92*A94)-C81 -> -363.8275 | E94: =(E92*A94)-C81 -> -196.3275 | F94: =(F92*A94)-C81 -> -28.8275 | G94: =(G92*A94)-C81 -> 71.6725 | H94: =(H92*A94)-C81 -> 205.6725
A95: =A96-10 -> 345 | B95: =(A95*B92)-C81 -> -698.8275 | C95: =(C92*A95)-C81 -> -526.3275 | D95: =(D92*A95)-C81 -> -353.8275 | E95: =(E92*A95)-C81 -> -181.3275 | F95: =(F92*A95)-C81 -> -8.8275 | G95: =(G92*A95)-C81 -> 94.6725 | H95: =(H92*A95)-C81 -> 232.6725
A96: =B72 -> 355 | B96: =(A96*B92)-C81 -> -698.8275 | C96: =(A96*C92)-C81 -> -521.3275 | D96: =(D92*A96)-C81 -> -343.8275 | E96: =(A96*E92)-C81 -> -166.3275 | F96: =(A96*F92)-C81 -> 11.1725 | G96: =(G92*A96)-C81 -> 117.6725 | H96: =(H92*A96)-C81 -> 259.6725
A97: =A96+10 -> 365 | B97: =(A97*B92)-C81 -> -698.8275 | C97: =(C92*A97)-C81 -> -516.3275 | D97: =(D92*A97)-C81 -> -333.8275 | E97: =(E92*A97)-C81 -> -151.3275 | F97: =(F92*A97)-C81 -> 31.1725 | G97: =(G92*A97)-C81 -> 140.6725 | H97: =(H92*A97)-C81 -> 286.6725
A98: =A97+10 -> 375 | B98: =(A98*B92)-C81 -> -698.8275 | C98: =(C92*A98)-C81 -> -511.3275 | D98: =(D92*A98)-C81 -> -323.8275 | E98: =(E92*A98)-C81 -> -136.3275 | F98: =(F92*A98)-C81 -> 51.1725 | G98: =(G92*A98)-C81 -> 163.6725 | H98: =(H92*A98)-C81 -> 313.6725
A99: =A98+10 -> 385 | B99: =(B92*A99)-C81 -> -698.8275 | C99: =(C92*A99)-C81 -> -506.3275 | D99: =(D92*A99)-C81 -> -313.8275 | E99: =(E92*A99)-C81 -> -121.3275 | F99: =(F92*A99)-C81 -> 71.1725 | G99: =(G92*A99)-C81 -> 186.6725 | H99: =(A99*H92)-C81 -> 340.6725

Sheet Maiz SP
A1: Proyección Maíz RR SP
A3: HECTAREAS | B3: 0
D4: UNITARIO | J4: MES CASH FLOW
A5: Labores
A6: Disco,rastra y rolo | B6: 0 | C6: Uni | D6: 35 | E6: =B6*D6 -> 0 | J6: AGOSTO
A7: Rolo picador | B7: 1 | C7: Uni | D7: 23 | E7: =B7*D7 -> 23 | J7: AGOSTO
A8: Barbecho Quimico | B8: 3 | C8: Uni | D8: 6.5 | E8: =B8*D8 -> 19.5 | G8: 41061 | H8: 41122 | J8: AGOSTO
A9: Pre emergente | B9: 1 | C9: Uni | D9: 6.5 | E9: =B9*D9 -> 6.5 | J9: OCTUBRE
A10: Siembra Directa | B10: 1 | C10: Uni | D10: 55 | E10: =B10*D10 -> 55 | G10: 41183 | J10: OCTUBRE
A11: Pulverizacion Post-emergente | B11: 0 | C11: Uni | D11: 6.5 | E11: =B11*D11 -> 0 | G11: 41184 | H11: 41215 | J11: NOVIEMBRE
A12: Pulverizacion Post-emergente | B12: 0 | C12: Uni | D12: 6.5 | E12: =B12*D12 -> 0 | J12: ENERO
A13: Pulverizacion Pre-emergente | B13: 0 | C13: Uni | D13: 6 | E13: =B13*D13 -> 0 | J13: ENERO
A14: Fertilización | B14: 1 | C14: Uni | D14: 32 | E14: =B14*D14 -> 32 | G14: 41184 | J14: NOVIEMBRE
A15: Fertilización | B15: 0 | C15: Uni | D15: 9 | E15: =B15*D15 -> 0 | J15: ENERO
A16: Aplicación terrestre Fungicida | B16: 0 | C16: Uni | D16: 6 | E16: =B16*D16 -> 0 | J16: ENERO
A17: Aplicación aerea insecticida | B17: 0 | C17: Uni | D17: =+Cotizaciones!F16 -> 13 | E17: =B17*D17 -> 0 | J17: ENERO
A18: Muestreo de suelos | B18: 1 | C18: Uni | D18: 0 | E18: =B18*D18 -> 0 | G18: =+G8 -> 41061 | J18: OCTUBRE
A19: Analisis de suelos | B19: 0 | C19: Uni | D19: 1 | E19: =B19*D19 -> 0 | J19: OCTUBRE
A20: Medicion satelital GPS | B20: 0 | C20: Uni | D20: 1 | E20: =B20*D20 -> 0
C21: Total Labores | E21: =SUM(E6:E20) -> 136 | F21: =E21/E59 -> 0.11805453 | G21: =E21*$B$3 -> 0
A22: Semilla
A24: Semilla de Maiz curada | B24: 0.6 | C24: Bolsa | D24: =Cotizaciones!E44 -> 180 | E24: =B24*D24 -> 108 | G24: =+A10 -> Siembra Directa | J24: ENERO
C25: Total Semilla | E25: =SUM(E24:E24) -> 108 | F25: =E25/E59 -> 0.093749186 | G25: =E25*$B$3 -> 0
A27: Arrendamiento | B27: 1 | C27: Uni | D27: =+'Resumen Proy'!C57 -> 426 | E27: =D27*B27 -> 426
C28: Total Arrendamiento | E28: =E27 -> 426 | F28: =E28/E59 -> 0.36978846 | G28: =+'[2]Alquileres por campo'!$S$62 -> 1182540.2
A30: Gerenciamiento | B30: 30 | C30: USD / Ha | D30: =B30 -> 30 | E30: =D30 -> 30
C31: Total Gerenciamiento | E31: =E30 -> 30 | F31: =E31/E59 -> 0.026041441 | G31: =E31*$B$3 -> 0
A32: Fertilizantes
A33: Fosforados (MAP / DAP) | B33: 0.09 | C33: Ton. | D33: =+Cotizaciones!I25 -> 990 | E33: =B33*D33 -> 89.1 | G33: =+A10 -> Siembra Directa | I33: =+E33*B3 -> 0 | J33: DICIEMBRE
A34: Nitrogenados (Urea) | B34: 0.16 | C34: Ton. | D34: =+Cotizaciones!I34 -> 610 | E34: =B34*D34 -> 97.6 | G34: =+A14 -> Fertilización
A35: Flete | B35: =+B34+B33 -> 0.25 | D35: =+'Trigo SP'!D35 -> 35 | E35: =+D35*B35 -> 8.75 | I35: =+E34*B3 -> 0 | J35: ENERO
C36: Total Fertilizantes | E36: =SUM(E33:E35) -> 195.45 | F36: =E36/E59 -> 0.16965999 | G36: =E36*$B$3 -> 0
A37: Agroquímicos
A38: Coadyuvante | B38: 1 | C38: Lts. | D38: =+Cotizaciones!I20 -> 20 | E38: =B38*D38 -> 20 | G38: =+A8 -> Barbecho Quimico | I38: =+A11 -> Pulverizacion Post-emergente | J38: JULIO
A39: Paraquat | B39: 2 | C39: Lts. | D39: =+Cotizaciones!I45 -> 2.6 | E39: =B39*D39 -> 5.2
A40: Sulfosato | B40: 8 | C40: Lts. | D40: =+Cotizaciones!I28 -> 4.5 | E40: =B40*D40 -> 36 | G40: =+G38 -> Barbecho Quimico | I40: =+I38 -> Pulverizacion Post-emergente | J40: NOVIEMBRE
A41: 2,4-D | B41: 1.6 | C41: Lts. | D41: =+Cotizaciones!I5 -> 4.6 | E41: =B41*D41 -> 7.36 | G41: =+G40 -> Barbecho Quimico | J41: NOVIEMBRE
A42: Picloran | B42: 0 | C42: Lts. | D42: =+Cotizaciones!I36 -> 7 | E42: =B42*D42 -> 0 | J42: OCTUBRE
A43: Convey | B43: 0.1 | C43: Lts. | D43: =+Cotizaciones!I53 -> 200 | E43: =+D43*B43 -> 20 | J43: OCTUBRE
A44: Atrazina | B44: 2 | C44: Lts. | D44: =+Cotizaciones!I10 -> 5.7 | E44: =B44*D44 -> 11.4 | G44: =+I38 -> Pulverizacion Post-emergente | J44: OCTUBRE
A45: Cletodyn | B45: 1.6 | C45: Lts. | D45: =+Cotizaciones!I27 -> 6 | E45: =B45*D45 -> 9.6 | J45: OCTUBRE
A46: Dicamba | B46: 0 | C46: Lts. | D46: =+Cotizaciones!I23 -> 7 | E46: =B46*D46 -> 0 | G46: =+I38 -> Pulverizacion Post-emergente | J46: OCTUBRE
A47: yamato | B47: 0.15 | C47: Lts. | D47: =+Cotizaciones!I50 -> 80 | E47: =B47*D47 -> 12 | G47: =+I38 -> Pulverizacion Post-emergente | J47: OCTUBRE
C48: Total Agroquimicos | E48: =SUM(E38:E47) -> 121.56 | F48: =E48/E59 -> 0.10551992 | G48: =E48*$B$3 -> 0
A50: Cosecha | B50: 1 | C50: Hás. | D50: 110 | E50: =+D50*B50 -> 110
C51: Total Cosecha | E51: =+E50 -> 110 | F51: =E51/E59 -> 0.095485282 | G51: =E51*$B$3 -> 0
A53: Seguro (Granizo) | B53: 3 | C53: % Costo | D53: 25 | E53: =D53 -> 25
C54: Total Seguro | E54: =E53 -> 25 | F54: =E54/E59 -> 0.021701201 | G54: =E54*$B$3 -> 0
A56: Costos Financiero | B56: 0 | C56: % | D56: 0 | E56: 0
C57: Total Costo Financ. | E57: 0 | G57: =E57*$B$3 -> 0
C59: Costo Total | E59: =E21+E25+E28+E31+E36+E48+E51+E54+E57 -> 1152.01 | F59: =F21+F25+F28+F31+F36+F48+F51+F71+F54 -> 1 | G59: =E59*$B$3 -> 0
E60: =+E59*B3 -> 0
A61: Comercialización
A62: Extraccion/Embolsado | B62: 0 | C62: U$ / ton | D62: =+Cotizaciones!E24/Cotizaciones!M20 -> 0 | E62: =D62*B62*B76 -> 0
A63: Silobolsa | B63: 0 | C63: 210 Tons | D63: =+(Cotizaciones!I41/210) -> 1.952381 | E63: =D63*B63*B76 -> 0
A64: Secada | B64: 2 | C64: U$ / ton | D64: 3 | E64: =+D64*B64*$B$76 -> 51
A65: Merma | B65: 0 | C65: % | E65: =D65 -> 0
A66: Paritaria | B66: 1 | C66: U$ / ton | D66: =Cotizaciones!F35 -> 5 | E66: =+D66*B66*$B$76 -> 42.5
A67: Traspile | B67: 1 | C67: U$ / ton | D67: =+Cotizaciones!F36 -> 6.5 | E67: =+D67*B67*$B$76 -> 55.25
A68: Analisis | B68: 1 | C68: U$ / ton | D68: =+Cotizaciones!E5/Cotizaciones!M20 -> 0.53083473 | E68: =+D68*B68*$B$76 -> 4.5120952
A69: Flete | B69: 1 | C69: U$ / ton | D69: =+'Cebada SP'!D71 -> 20 | E69: =+D69*B69*$B$76 -> 170
A70: Comisión | B70: 1 | C70: % | D70: =B70%*B76*Cotizaciones!B14 -> 30.175 | E70: =D70 -> 30.175
C71: Total Comercialización | E71: =SUM(E62:E70) -> 353.4371 | G71: =E71*$B$3 -> 0
A72: Precio bruto | E72: =+Cotizaciones!B13 -> 200
A73: Gastos Comerciales/tn | E73: =+E71/B76 -> 41.580835 | F73: =+E73/E72 -> 0.20790417
A74: Precio Neto Estimado | E74: =+E72-E73 -> 158.41917
A76: Rendimiento Estimado | B76: 8.5 | C76: Ton/Ha. | H76: Alea | J76: Socio | L76: Total/ha
A77: Precio Neto Estimado | B77: =+E74 -> 158.41917 | C77: Ton | G77: Labores | I77: =+H77*B$3 -> 0 | J77: =+E21 -> 136 | K77: =+J77*B$3 -> 0
A78: Costo Total | B78: =+E59 -> 1152.01 | C78: Ha | G78: Semilla | H78: 0 | I78: =+H78*B$3 -> 0 | J78: =+E25 -> 108 | K78: =+J78*B$3 -> 0 | L78: =+J78+H78 -> 108
A79: Ingreso Bruto (2% IB) | B79: =+B77*B76 -> 1346.5629 | C79: Ha | G79: Arrendamiento | H79: =+E28 -> 426 | I79: =+H79*B$3 -> 0 | K79: =+J79*B$3 -> 0 | L79: =+J79+H79 -> 426
A80: Margen | B80: =B79-B78 -> 194.5529 | C80: Ha | G80: Gerenciamiento | H80: =+E31 -> 30 | I80: =+H80*B$3 -> 0 | K80: =+J80*B$3 -> 0 | L80: =+J80+H80 -> 30
A81: Retorno | B81: =B80/B78 -> 0.16888126 | G81: Fertilizantes | H81: =+E36 -> 195.45 | I81: =+H81*B$3 -> 0 | J81: 0 | K81: =+J81*B$3 -> 0 | L81: =+J81+H81 -> 195.45
A82: Rendimiento de Indiferencia | B82: =+B78/B77 -> 7.2719106 | G82: Agroquímicos | I82: =+H82*B$3 -> 0 | J82: =+E48 -> 121.56 | K82: =+J82*B$3 -> 0 | L82: =+J82+H82 -> 121.56
A83: Inversión Real | B83: =+E48+E36+E31+E28+E25+E21 -> 1017.01 | C83: Ha | L83: =+J83+H83 -> 0
A84: Retorno Real | B84: =B80/B83 -> 0.19129891 | G84: Total
H85: =SUM(H77:H84) -> 651.45 | I85: =SUM(I77:I84) -> 0 | J85: =SUM(J77:J84) -> 365.56 | K85: =SUM(K77:K84) -> 0 | L85: =+J85+H85 -> 1017.01
H86: =+H85/L85 -> 0.64055417 | J86: =+J85/L85 -> 0.35944583
A87: Costo Total | C87: =E59 -> 1152.01
A88: Rentabilidad (%)
A89: Px/Rinde | B89: =E89-1.5 -> 7 | C89: =E89-1 -> 7.5 | D89: =E89-0.5 -> 8 | E89: =B76 -> 8.5 | F89: =E89+0.5 -> 9 | G89: =E89+0.8 -> 9.3 | H89: =E89+1.2 -> 9.7
A90: =A91-10 -> 128.41917 | B90: =B99/C87*100 -> -21.968198 | C90: =C99/C87*100 -> -16.394498 | D90: =D99/C87*100 -> -10.820798 | E90: =E99/C87*100 -> -5.2470981 | F90: =F99/C87*100 -> 0.32660198 | G90: =G99/C87*100 -> 3.670822 | H90: =H99/C87*100 -> 8.1297821
A91: =A92-10 -> 138.41917 | B91: =B100/C87*100 -> -15.891862 | C91: =C100/C87*100 -> -9.8841382 | D91: =D100/C87*100 -> -3.8764141 | E91: =E100/C87*100 -> 2.13131 | F91: =F100/C87*100 -> 8.1390342 | G91: =G100/C87*100 -> 11.743669 | H91: =H100/C87*100 -> 16.549848
A92: =A93-10 -> 148.41917 | B92: =B101/C87*100 -> -9.8155262 | C92: =C101/C87*100 -> -3.373778 | D92: =D101/C87*100 -> 3.0679701 | E92: =E101/C87*100 -> 9.5097182 | F92: =F101/C87*100 -> 15.951466 | G92: =G101/C87*100 -> 19.816515 | H92: =H101/C87*100 -> 24.969914
A93: =B77 -> 158.41917 | B93: =B102/C87*100 -> -3.73919 | C93: =C102/C87*100 -> 3.1365821 | D93: =D102/C87*100 -> 10.012354 | E93: =E102/C87*100 -> 16.888126 | F93: =F102/C87*100 -> 23.763899 | G93: =G102/C87*100 -> 27.889362 | H93: =H102/C87*100 -> 33.38998
A94: =A93+10 -> 168.41917 | B94: =B103/C87*100 -> 2.3371461 | C94: =C103/C87*100 -> 9.6469423 | D94: =D103/C87*100 -> 16.956738 | E94: =E103/C87*100 -> 24.266535 | F94: =F103/C87*100 -> 31.576331 | G94: =G103/C87*100 -> 35.962208 | H94: =H103/C87*100 -> 41.810045
A95: =A94+10 -> 178.41917 | B95: =B104/C87*100 -> 8.4134823 | C95: =C104/C87*100 -> 16.157302 | D95: =D104/C87*100 -> 23.901123 | E95: =E104/C87*100 -> 31.644943 | F95: =F104/C87*100 -> 39.388763 | G95: =G104/C87*100 -> 44.035055 | H95: =H104/C87*100 -> 50.230111
A96: =A95+10 -> 188.41917 | B96: =B105/C87*100 -> 14.489818 | C96: =C105/C87*100 -> 22.667663 | D96: =D105/C87*100 -> 30.845507 | E96: =E105/C87*100 -> 39.023351 | F96: =F105/C87*100 -> 47.201195 | G96: =G105/C87*100 -> 52.107902 | H96: =H105/C87*100 -> 58.650177
A97: MB Maiz
A98: Px/Rinde | B98: =E98-1.5 -> 7 | C98: =E98-1 -> 7.5 | D98: =E98-0.5 -> 8 | E98: =B76 -> 8.5 | F98: =E98+0.5 -> 9 | G98: =E98+0.8 -> 9.3 | H98: =E98+1.2 -> 9.7
A99: =A100-10 -> 128.41917 | B99: =(B98*A99)-C87 -> -253.07584 | C99: =(C98*A99)-C87 -> -188.86626 | D99: =(D98*A99)-C87 -> -124.65668 | E99: =(E98*A99)-C87 -> -60.447095 | F99: =(F98*A99)-C87 -> 3.7624875 | G99: =(G98*A99)-C87 -> 42.288237 | H99: =(H98*A99)-C87 -> 93.655903
A100: =A101-10 -> 138.41917 | B100: =(B98*A100)-C87 -> -183.07584 | C100: =(C98*A100)-C87 -> -113.86626 | D100: =(D98*A100)-C87 -> -44.656678 | E100: =(E98*A100)-C87 -> 24.552905 | F100: =(F98*A100)-C87 -> 93.762487 | G100: =(G98*A100)-C87 -> 135.28824 | H100: =(H98*A100)-C87 -> 190.6559
A101: =A102-10 -> 148.41917 | B101: =(A101*B98)-C87 -> -113.07584 | C101: =(C98*A101)-C87 -> -38.86626 | D101: =(D98*A101)-C87 -> 35.343322 | E101: =(E98*A101)-C87 -> 109.5529 | F101: =(F98*A101)-C87 -> 183.76249 | G101: =(G98*A101)-C87 -> 228.28824 | H101: =(H98*A101)-C87 -> 287.6559
A102: =B77 -> 158.41917 | B102: =(A102*B98)-C87 -> -43.075843 | C102: =(A102*C98)-C87 -> 36.13374 | D102: =(D98*A102)-C87 -> 115.34332 | E102: =(A102*E98)-C87 -> 194.5529 | F102: =(A102*F98)-C87 -> 273.76249 | G102: =(G98*A102)-C87 -> 321.28824 | H102: =(H98*A102)-C87 -> 384.6559
A103: =A102+10 -> 168.41917 | B103: =(A103*B98)-C87 -> 26.924157 | C103: =(C98*A103)-C87 -> 111.13374 | D103: =(D98*A103)-C87 -> 195.34332 | E103: =(E98*A103)-C87 -> 279.5529 | F103: =(F98*A103)-C87 -> 363.76249 | G103: =(G98*A103)-C87 -> 414.28824 | H103: =(H98*A103)-C87 -> 481.6559
A104: =A103+10 -> 178.41917 | B104: =(A104*B98)-C87 -> 96.924157 | C104: =(C98*A104)-C87 -> 186.13374 | D104: =(D98*A104)-C87 -> 275.34332 | E104: =(E98*A104)-C87 -> 364.5529 | F104: =(F98*A104)-C87 -> 453.76249 | G104: =(G98*A104)-C87 -> 507.28824 | H104: =(H98*A104)-C87 -> 578.6559
A105: =A104+10 -> 188.41917 | B105: =(B98*A105)-C87 -> 166.92416 | C105: =(C98*A105)-C87 -> 261.13374 | D105: =(D98*A105)-C87 -> 355.34332 | E105: =(E98*A105)-C87 -> 449.5529 | F105: =(F98*A105)-C87 -> 543.76249 | G105: =(G98*A105)-C87 -> 600.28824 | H105: =(A105*H98)-C87 -> 675.6559

Sheet Girasol SP
A1: Proyección Girasol CL Suelos Profundos
A3: HECTAREAS | B3: 0
B5: CANTIDAD | C5: UNIDAD | D5: PRECIO | E5: TOTAL / HA | F5: % Costo | G5: Inv Real | H5: Mes
D6: UNITARIO | J6: MES CASH FLOW
A7: Labores
A9: Disco,rastra y rolo | B9: 0 | C9: Uni | D9: =+'Maiz SP'!D6 -> 35 | E9: =B9*D9 -> 0 | H9: jun | J9: AGOSTO
A10: Rolo picador | B10: 0 | C10: Uni | D10: 8 | E10: =B10*D10 -> 0
A11: Barbecho Quimico | B11: 3 | C11: Uni | D11: 6.5 | E11: =B11*D11 -> 19.5 | G11: 41062 | H11: 41154 | J11: SEPTIEMBRE
A12: Siembra Directa | B12: 1 | C12: Uni | D12: 53 | E12: =B12*D12 -> 53 | G12: 41184 | J12: NOVIEMBRE
A13: Pulverizacion Post-emergente (CL) | B13: 1 | C13: Uni | D13: 6.5 | E13: =B13*D13 -> 6.5 | G13: 41215 | J13: NOVIEMBRE
A14: Pulverizacion Pre-emergente | B14: 1 | C14: Uni | D14: 6.5 | E14: =B14*D14 -> 6.5 | J14: NOVIEMBRE
A15: Pulverización graminicidas | B15: 0 | C15: Uni | D15: =+D11 -> 6.5 | E15: =B15*D15 -> 0 | J15: NOVIEMBRE
A16: Fertilización | B16: 0 | C16: Uni | D16: 12 | E16: =B16*D16 -> 0 | G16: 41214 | J16: DICIEMBRE
A17: Aplicación terrestre Fungicida | B17: 0 | C17: Uni | D17: =Cotizaciones!F17 -> 5 | E17: =B17*D17 -> 0 | J17: ENERO
A18: Aplicación aerea insecticida | B18: 0.5 | C18: Uni | D18: =Cotizaciones!F16 -> 13 | E18: =B18*D18 -> 6.5 | G18: 41245 | J18: FEBRERO
A19: Muestreo de suelos | B19: 0 | C19: Uni | D19: =Cotizaciones!F15 -> 1 | E19: =B19*D19 -> 0 | J19: FEBRERO
A20: Analisis de suelos | B20: 0 | C20: Uni | D20: =Cotizaciones!F5 -> 0 | E20: =B20*D20 -> 0 | J20: FEBRERO
A21: Monitoreo bb y b | B21: 1 | C21: Uni | D21: 4 | E21: =B21*D21 -> 4 | G21: 41183 | J21: OCTUBRE
A22: Aplicacion Cebo | B22: 0.5 | C22: Uni | D22: =Cotizaciones!F6 -> 5 | E22: =D22*B22 -> 2.5 | J22: OCTUBRE
C23: Total Labores | E23: =SUM(E9:E22) -> 98.5 | F23: =E23/E65 -> 0.10126348 | G23: =E23*$B$3 -> 0
A24: Semilla
A25: Semilla de girasol cl | B25: 0.3 | C25: Bolsa 180 | D25: =Cotizaciones!E42 -> 300 | E25: =B25*D25 -> 90 | J25: NOVIEMBRE
C26: Total Semilla | E26: =SUM(E25:E25) -> 90 | F26: =E26/E65 -> 0.092525007 | G26: =E26*$B$3 -> 0
A28: Arrendamiento | B28: 1 | C28: Uni | D28: =+'Resumen Proy'!C57 -> 426 | E28: =D28*B28 -> 426
C29: Total Arrendamiento | E29: =E28 -> 426 | F29: =E29/E65 -> 0.4379517 | G29: =+'[2]Alquileres por campo'!$S$60 -> 0
A31: Gerenciamiento | B31: 40 | C31: USD / Ha | D31: =B31 -> 40 | E31: =D31 -> 40
C32: Total Gerenciamiento | E32: =E31 -> 40 | F32: =E32/E65 -> 0.041122226 | G32: =E32*$B$3 -> 0
A34: Fertilizantes
A35: Fosforados | B35: 0.06 | C35: Ton. | D35: =+Cotizaciones!I25 -> 990 | E35: =D35*B35 -> 59.4 | G35: =+A12 -> Siembra Directa | I35: =+E35*B3 -> 0 | J35: DICIEMBRE
A36: Nitrogenados | B36: 0.06 | C36: Ton. | D36: =+Cotizaciones!I34 -> 610 | E36: =D36*B36 -> 36.6 | G36: =+A16 -> Fertilización | J36: ENERO
A37: Flete | B37: =+B36+B35 -> 0.12 | D37: =+'Trigo SP'!D35 -> 35 | E37: =+D37*B37 -> 4.2
C38: Total Fertilizantes | E38: =+E37+E36+E35 -> 100.2 | F38: =E38/E65 -> 0.10301117 | G38: =E38*$B$3 -> 0
A39: Agroquímicos
A41: sulfentrazone | B41: 0.3 | C41: Lts. | D41: =+Cotizaciones!I52 -> 19 | E41: =B41*D41 -> 5.7 | G41: =+A11 -> Barbecho Quimico | J41: JULIO
A42: Sulfosato | B42: 4.5 | C42: Lts. | D42: =+Cotizaciones!I28 -> 4.5 | E42: =B42*D42 -> 20.25 | G42: =+G41 -> Barbecho Quimico | J42: JULIO
A43: 2,4-D | B43: 1.6 | C43: Lts. | D43: =+Cotizaciones!I5 -> 4.6 | E43: =B43*D43 -> 7.36 | G43: barb (1ro) | J43: JULIO
A44: Aceite | B44: 1 | C44: Lts. | D44: 20 | E44: =B44*D44 -> 20 | J44: JULIO
A45: Flurocloridona | B45: 1 | C45: Lts. | D45: =+Cotizaciones!I24 -> 11.8 | E45: =+D45*B45 -> 11.8 | J45: JULIO
A46: Clearsol | B46: 0.08 | C46: Pack | D46: =+'Girasol O SP'!D46 -> 170 | E46: =B46*D46 -> 13.6 | G46: =+A13 -> Pulverizacion Post-emergente (CL) | J46: OCTUBRE
A47: =+'Girasol O SP'!A45 -> Coragen | B47: 0.015 | C47: Lts. | D47: =Cotizaciones!I31 -> 20 | E47: =B47*D47 -> 0.3 | G47: barb (2do) | J47: NOVIEMBRE
A48: cletodim | B48: 1.6 | C48: Lts. | D48: =+Cotizaciones!I27 -> 6 | E48: =B48*D48 -> 9.6 | J48: NOVIEMBRE
A49: lamba | B49: 0.1 | C49: Lts. | D49: 10 | E49: =B49*D49 -> 1 | G49: =+A18 -> Aplicación aerea insecticida | J49: FEBRERO
A50: Affinity | B50: 0.05 | D50: =+Cotizaciones!I46 -> 80 | E50: =B50*D50 -> 4 | J50: FEBRERO
A51: Paraquat | B51: 4 | C51: Lts. | D51: =+Cotizaciones!I45 -> 2.6 | E51: =B51*D51 -> 10.4 | J51: NOVIEMBRE
A52: cebo | B52: 2 | C52: kgs. | D52: =Cotizaciones!I14 -> 7 | E52: =+D52*B52 -> 14 | G52: =+A21 -> Monitoreo bb y b
C53: Total Agroquimicos | E53: =SUM(E41:E52) -> 118.01 | F53: =E53/E65 -> 0.12132085 | G53: =E53*$B$3 -> 0
A55: Cosecha | B55: 1 | C55: Hás. | D55: 85 | E55: =+B55*D55 -> 85
C56: Total Cosecha | E56: =E55 -> 85 | F56: =E56/E65 -> 0.087384729 | G56: =E56*$B$3 -> 0
A59: Seguro (Granizo y viento) | B59: 2.8 | C59: % Ing Bruto | D59: 15 | E59: =D59 -> 15
C60: Total Seguro | E60: =+E59 -> 15 | F60: =E60/E65 -> 0.015420835 | G60: =E60*$B$3 -> 0
A62: Costos Financiero | B62: 0 | C62: % | D62: 0 | E62: 0
C63: Total Costo Financ. | E63: =E62 -> 0 | F63: =D63*$B$3 -> 0 | G63: =E63*$B$3 -> 0
C65: Costo Total | E65: =E23+E26+E29+E32+E38+E53+E56+E60+E63 -> 972.71 | F65: =F23+F26+F29+F32+F38+F53+F77+F60+F56 -> 1 | G65: =E65*$B$3 -> 0
A68: Comercialización
A69: Extraccion/Embolsado | B69: 0 | C69: U$ / ton | D69: =Cotizaciones!F24 -> 3.3 | E69: =D69*B69*B83 -> 0
A70: Silobolsa | B70: 0 | C70: 210 Tons | D70: =Cotizaciones!I41/210 -> 1.952381 | E70: =D70*B70*B83 -> 0
A71: Secada | B71: 0 | C71: $ / ton | D71: =Cotizaciones!F31 -> 3 | E71: =+D71*B71*$B$83 -> 0
A72: Paritaria | B72: 0.5 | C72: $ / ton | D72: =Cotizaciones!F35 -> 5 | E72: =+D72*B72*$B$83 -> 6.5
A73: Traspile | B73: 0.5 | C73: $ / ton | D73: =+Cotizaciones!F36 -> 6.5 | E73: =+D73*B73*$B$83 -> 8.45
A74: Analisis | B74: 1 | C74: $ / ton | D74: =+Cotizaciones!E5/Cotizaciones!M20 -> 0.53083473 | E74: =+D74*B74*$B$83 -> 1.3801703
A75: Flete | B75: 1 | C75: $ / ton | D75: =+'Cebada SP'!D71 -> 20 | E75: =+D75*B75*$B$83 -> 52
A76: Comisión | B76: 1 | C76: % | D76: =B76%*B83*Cotizaciones!B12 -> 11.7 | E76: =D76 -> 11.7
C77: Total Comercialización | E77: =SUM(E69:E76) -> 80.03017 | G77: =E77*$B$3 -> 0
A78: Precio bruto | E78: 358
A79: Gastos Comerciales/tn | E79: =+E77/B83 -> 30.780835 | F79: =+E79/E78 -> 0.085979985
A80: Precio Neto Estimado | E80: =+E78-E79 -> 327.21917
A82: GIRASOL COMÚN SUELO PROFUNDO
A83: Rendimiento Estimado | B83: 2.6 | C83: Ton/Ha.
A84: Precio Neto Estimado | B84: =+E80 -> 327.21917 | C84: Ton.
A85: Bonificación MG | B85: =E78*0.13 -> 46.54 | C85: Ton.
A86: Bonificación H. | B86: 0 | C86: Ton.
A87: Precio Neto con Bonif | B87: =B84+B85+B86 -> 373.75917 | C87: Ton.
A88: Costo Total | B88: =E65 -> 972.71 | C88: Ton | D88: =+B88/B83 -> 374.11923
A89: Ingreso Bruto (2% IB) | B89: =+(B84+B85+B86)*B83 -> 971.77383 | C89: Ha | D89: =+D88/B87 -> 1.0009634
A90: Margen | B90: =+B89-E65 -> -0.93617029 | C90: Ha
A91: Retorno | B91: =+B90/B88 -> -0.00096243514
A92: Rendimiento de Indiferencia | B92: =+B88/B87 -> 2.6025047
A93: Inversión Real | B93: =+E53+E38+E32+E29+E26+E23 -> 872.71
A94: Retorno Real | B94: =B90/B93 -> -0.0010727164
A95: Costo Total | C95: =E65 -> 972.71
A97: Retorno (%)
A98: Px/Rinde | B98: =B107 -> 1.7 | C98: =C107 -> 2 | D98: =D107 -> 2.3 | E98: =E107 -> 2.6 | F98: =F107 -> 2.9 | G98: =G107 -> 3.2 | H98: =H107 -> 3.5
A99: =A100-10 -> 343.75917 | B99: =B108/C95*100 -> -39.921397 | C99: =C108/C95*100 -> -29.31929 | D99: =D108/C95*100 -> -18.717184 | E99: =E108/C95*100 -> -8.1150775 | F99: =F108/C95*100 -> 2.4870289 | G99: =G108/C95*100 -> 13.089135 | H99: =H108/C95*100 -> 23.691242
A100: =A101-10 -> 353.75917 | B100: =B109/C95*100 -> -38.173702 | C100: =C109/C95*100 -> -27.263179 | D100: =D109/C95*100 -> -16.352656 | E100: =E109/C95*100 -> -5.4421328 | F100: =F109/C95*100 -> 5.4683903 | G100: =G109/C95*100 -> 16.378913 | H100: =H109/C95*100 -> 27.289437
A101: =A102-10 -> 363.75917 | B101: =B110/C95*100 -> -36.426008 | C101: =C110/C95*100 -> -25.207068 | D101: =D110/C95*100 -> -13.988128 | E101: =E110/C95*100 -> -2.7691882 | F101: =F110/C95*100 -> 8.4497517 | G101: =G110/C95*100 -> 19.668691 | H101: =H110/C95*100 -> 30.887631
A102: =B87 -> 373.75917 | B102: =B111/C95*100 -> -34.678313 | C102: =C111/C95*100 -> -23.150957 | D102: =D111/C95*100 -> -11.6236 | E102: =E111/C95*100 -> -0.096243514 | F102: =F111/C95*100 -> 11.431113 | G102: =G111/C95*100 -> 22.95847 | H102: =H111/C95*100 -> 34.485826
A103: =A102+10 -> 383.75917 | B103: =B112/C95*100 -> -32.930618 | C103: =C112/C95*100 -> -21.094845 | D103: =D112/C95*100 -> -9.2590721 | E103: =E112/C95*100 -> 2.5767011 | F103: =F112/C95*100 -> 14.412474 | G103: =G112/C95*100 -> 26.248248 | H103: =H112/C95*100 -> 38.084021
A104: =A103+10 -> 393.75917 | B104: =B113/C95*100 -> -31.182924 | C104: =C113/C95*100 -> -19.038734 | D104: =D113/C95*100 -> -6.8945441 | E104: =E113/C95*100 -> 5.2496458 | F104: =F113/C95*100 -> 17.393836 | G104: =G113/C95*100 -> 29.538026 | H104: =H113/C95*100 -> 41.682216
A105: =A104+10 -> 403.75917 | B105: =B114/C95*100 -> -29.435229 | C105: =C114/C95*100 -> -16.982623 | D105: =D114/C95*100 -> -4.5300161 | E105: =E114/C95*100 -> 7.9225905 | F105: =F114/C95*100 -> 20.375197 | G105: =G114/C95*100 -> 32.827804 | H105: =H114/C95*100 -> 45.28041
A106: MB
A107: Px/Rinde | B107: =C107-0.3 -> 1.7 | C107: =D107-0.3 -> 2 | D107: =E107-0.3 -> 2.3 | E107: =B83 -> 2.6 | F107: =E107+0.3 -> 2.9 | G107: =F107+0.3 -> 3.2 | H107: =G107+0.3 -> 3.5
A108: =A109-10 -> 343.75917 | B108: =(B107*A108)-C95 -> -388.31942 | C108: =(C107*A108)-C95 -> -285.19167 | D108: =(D107*A108)-C95 -> -182.06392 | E108: =(E107*A108)-C95 -> -78.93617 | F108: =(F107*A108)-C95 -> 24.191579 | G108: =(G107*A108)-C95 -> 127.31933 | H108: =(H107*A108)-C95 -> 230.44708
A109: =A110-10 -> 353.75917 | B109: =(B107*A109)-C95 -> -371.31942 | C109: =(C107*A109)-C95 -> -265.19167 | D109: =(D107*A109)-C95 -> -159.06392 | E109: =(E107*A109)-C95 -> -52.93617 | F109: =(F107*A109)-C95 -> 53.191579 | G109: =(G107*A109)-C95 -> 159.31933 | H109: =(H107*A109)-C95 -> 265.44708
A110: =A111-10 -> 363.75917 | B110: =(A110*B107)-C95 -> -354.31942 | C110: =(C107*A110)-C95 -> -245.19167 | D110: =(D107*A110)-C95 -> -136.06392 | E110: =(E107*A110)-C95 -> -26.93617 | F110: =(F107*A110)-C95 -> 82.191579 | G110: =(G107*A110)-C95 -> 191.31933 | H110: =(H107*A110)-C95 -> 300.44708
A111: =B87 -> 373.75917 | B111: =(A111*B107)-C95 -> -337.31942 | C111: =(A111*C107)-C95 -> -225.19167 | D111: =(D107*A111)-C95 -> -113.06392 | E111: =(A111*E107)-C95 -> -0.93617029 | F111: =(A111*F107)-C95 -> 111.19158 | G111: =(G107*A111)-C95 -> 223.31933 | H111: =(H107*A111)-C95 -> 335.44708
A112: =A111+10 -> 383.75917 | B112: =(A112*B107)-C95 -> -320.31942 | C112: =(C107*A112)-C95 -> -205.19167 | D112: =(D107*A112)-C95 -> -90.06392 | E112: =(E107*A112)-C95 -> 25.06383 | F112: =(F107*A112)-C95 -> 140.19158 | G112: =(G107*A112)-C95 -> 255.31933 | H112: =(H107*A112)-C95 -> 370.44708
A113: =A112+10 -> 393.75917 | B113: =(A113*B107)-C95 -> -303.31942 | C113: =(C107*A113)-C95 -> -185.19167 | D113: =(D107*A113)-C95 -> -67.06392 | E113: =(E107*A113)-C95 -> 51.06383 | F113: =(F107*A113)-C95 -> 169.19158 | G113: =(G107*A113)-C95 -> 287.31933 | H113: =(H107*A113)-C95 -> 405.44708
A114: =A113+10 -> 403.75917 | B114: =(B107*A114)-C95 -> -286.31942 | C114: =(C107*A114)-C95 -> -165.19167 | D114: =(D107*A114)-C95 -> -44.06392 | E114: =(E107*A114)-C95 -> 77.06383 | F114: =(F107*A114)-C95 -> 198.19158 | G114: =(G107*A114)-C95 -> 319.31933 | H114: =(A114*H107)-C95 -> 440.44708

Sheet Girasol SS
A1: Proyección Girasol CL Suelos Someros
A3: HECTAREAS | B3: ='Resumen Proy'!B29 -> 0
B5: CANTIDAD | C5: UNIDAD | D5: PRECIO | E5: TOTAL / HA | F5: % Costo | G5: Inv Real | H5: Mes
D6: UNITARIO | J6: MES CASH FLOW
A7: Labores
A9: Disco,rastra y rolo | B9: 0 | C9: Uni | D9: =Cotizaciones!F8 -> 0 | E9: =B9*D9 -> 0 | J9: JULIO/SEPTIEMBRE
A10: Rolo picador | B10: 0 | C10: Uni | D10: =Cotizaciones!F18 -> 17 | E10: =B10*D10 -> 0
A11: Barbecho Quimico | B11: 2 | C11: Uni | D11: =Cotizaciones!F17 -> 5 | E11: =B11*D11 -> 10 | G11: 41062 | H11: 41154 | J11: JULIO/OCTUBRE
A12: Siembra Directa | B12: 1 | C12: Uni | D12: =Cotizaciones!F22 -> 42 | E12: =B12*D12 -> 42 | G12: 41184 | J12: NOVIEMBRE
A13: Pulverizacion Post-emergente (CL) | B13: 1 | C13: Uni | D13: =Cotizaciones!F17 -> 5 | E13: =B13*D13 -> 5 | G13: 41215 | J13: NOVIEMBRE
A14: Pulverizacion Pre-emergente | B14: 0 | C14: Uni | D14: =Cotizaciones!F17 -> 5 | E14: =B14*D14 -> 0
A15: Pulverización graminicidas | B15: 0 | C15: Uni | D15: =Cotizaciones!F17 -> 5 | E15: =B15*D15 -> 0
A16: Fertilización | B16: 0 | C16: Uni | D16: =Cotizaciones!F10 -> 0 | E16: =B16*D16 -> 0 | G16: 41214 | J16: DICIEMBRE
A17: Aplicación terrestre Fungicida | B17: 0 | C17: Uni | D17: =Cotizaciones!F17 -> 5 | E17: =B17*D17 -> 0 | J17: ENERO
A18: Aplicación aerea insecticida | B18: 1 | C18: Uni | D18: =Cotizaciones!F16 -> 13 | E18: =B18*D18 -> 13 | G18: 41245 | J18: FEBRERO
A19: Muestreo de suelos | B19: 0 | C19: Uni | D19: =Cotizaciones!F15 -> 1 | E19: =B19*D19 -> 0
A20: Analisis de suelos | B20: 0 | C20: Uni | D20: =Cotizaciones!F5 -> 0 | E20: =B20*D20 -> 0
A21: Monitoreo bb y b | B21: 1 | C21: Uni | D21: =Cotizaciones!F14 -> 5 | E21: =B21*D21 -> 5 | G21: 41183 | J21: OCTUBRE
A22: Aplicacion Cebo | B22: 0.5 | C22: Uni | D22: =Cotizaciones!F6 -> 5 | E22: =D22*B22 -> 2.5 | J22: OCTUBRE
C23: Total Labores | E23: =SUM(E9:E22) -> 77.5 | F23: =E23/E72 -> 0.10390515 | G23: =E23*D1 -> 0
A24: Semilla
A25: Semilla de girasol 202 cl curada | B25: 0.33 | C25: Bolsa 150mil | D25: =Cotizaciones!E42 -> 300 | E25: =B25*D25 -> 99 | J25: OCTUVBRE
C26: Total Semilla | E26: =SUM(E25:E25) -> 99 | F26: =E26/E72 -> 0.13273045 | G26: =E26*D1 -> 0
A28: Arrendamiento | B28: 1 | C28: Uni | D28: ='Resumen Proy'!D29 -> 280 | E28: =D28*B28 -> 280
C29: Total Arrendamiento | E29: =E28 -> 280 | F29: =E29/E72 -> 0.37539926 | G29: =E29*D1 -> 0
A31: Gerenciamiento | B31: 20 | C31: USD / Ha | D31: =B31 -> 20 | E31: =D31 -> 20
C32: Total Gerenciamiento | E32: =E31 -> 20 | F32: =E32/E72 -> 0.026814233 | G32: =E32*D1 -> 0
A34: Fertilizantes
A35: Fosforados | B35: 0.04 | C35: Ton. | D35: =Cotizaciones!I25+Cotizaciones!F26 -> 1025 | E35: =D35*B35 -> 41 | G35: =+A12 -> Siembra Directa | J35: JUNIO
A36: Nitrogenados | B36: 0 | C36: Ton. | D36: =Cotizaciones!I34+Cotizaciones!F26 -> 645 | E36: =D36*B36 -> 0 | G36: =+A16 -> Fertilización | J36: JUNIO
C37: Total Fertilizantes | E37: =SUM(E35:E36) -> 41 | F37: =E37/E72 -> 0.054969178 | G37: =E37*D1 -> 0
A38: Agroquímicos
A40: Coadyuvante | B40: 0.2 | C40: Lts. | D40: =Cotizaciones!I21 -> 12 | E40: =B40*D40 -> 2.4 | G40: =+A11 -> Barbecho Quimico | J40: JULIO
A41: Glifosato | B41: 7 | C41: Lts. | D41: =Cotizaciones!I28 -> 4.5 | E41: =B41*D41 -> 31.5 | G41: =+G40 -> Barbecho Quimico | J41: JULIO
A42: 2,4-D | B42: 0.5 | C42: Lts. | D42: =Cotizaciones!I5 -> 4.6 | E42: =B42*D42 -> 2.3 | G42: barb (1ro) | J42: JULIO
A43: Graminicida | B43: 0 | C43: Lts. | D43: =Cotizaciones!I27 -> 6 | E43: =B43*D43 -> 0
A44: Fungicida | B44: 0 | C44: Lts. | D44: =Cotizaciones!I45 -> 2.6 | E44: 0
A45: Clearsol | B45: =1/6 -> 0.16666667 | C45: Pack | D45: =Cotizaciones!I16 -> 170 | E45: =B45*D45 -> 28.333333 | G45: =+A13 -> Pulverizacion Post-emergente (CL) | J45: OCTUBRE
A46: Karate Zeon | B46: 0.015 | C46: Lts. | D46: =Cotizaciones!I31 -> 20 | E46: =B46*D46 -> 0.3 | G46: =+A11 -> Barbecho Quimico | J46: NOVIEMBRE
A47: Clorpirifos | B47: 0.8 | C47: Lts. | D47: =Cotizaciones!I19 -> 7 | E47: =B47*D47 -> 5.6 | G47: =+A18 -> Aplicación aerea insecticida | J47: FEBRERO
A48: cebo | B48: 3 | C48: kgs. | D48: =Cotizaciones!I14 -> 7 | E48: =+D48*B48 -> 21 | G48: =+A21 -> Monitoreo bb y b | J48: NOVIEMBRE
C50: Total Agroquimicos | E50: =SUM(E40:E49) -> 91.433333 | F50: =E50/E72 -> 0.12258574 | G50: =E50*D1 -> 0
A52: Cosecha | B52: 1 | C52: Hás. | D52: 52 | E52: =+D52*B52 -> 52
C53: Total Cosecha | E53: =E52 -> 52 | F53: =E53/E72 -> 0.069717006 | G53: =E53*D1 -> 0
A54: Comercialización
A55: Extraccion/Embolsado | B55: 0 | C55: U$ / ton | D55: =Cotizaciones!F24 -> 3.3 | E55: =D55*B55*B76 -> 0
A56: Silobolsa | B56: 0 | C56: 210 Tons | D56: =Cotizaciones!I41/210 -> 1.952381 | E56: =D56*B56*B76 -> 0
A57: Secada | B57: 0 | C57: $ / ton | D57: =Cotizaciones!F31 -> 3 | E57: =+D57*B57*$B$76 -> 0
A58: Paritaria | B58: 0.5 | C58: $ / ton | D58: =Cotizaciones!F35 -> 5 | E58: =+D58*B58*$B$76 -> 6
A59: Traspile | B59: 0.5 | C59: $ / ton | D59: =Cotizaciones!F36 -> 6.5 | E59: =+D59*B59*$B$76 -> 7.8
A60: Analisis | B60: 0.5 | C60: $ / ton | D60: =Cotizaciones!F5 -> 0 | E60: =+D60*B60*$B$76 -> 0
A61: Flete | B61: 1 | C61: $ / ton | D61: =Cotizaciones!F25 -> 20 | E61: =+D61*B61*$B$76 -> 48
A62: Comisión | B62: 0 | C62: % | D62: =B62%*B82 -> 0 | E62: =D62 -> 0
C63: Total Comercialización | E63: =SUM(E57:E62) -> 61.8 | F63: =E63/E72 -> 0.08285598 | G63: =E63*D1 -> 0
A66: Seguro (Granizo) | B66: 4.2 | C66: % Ing Bruto | D66: =B66%*B86 -> 23.1392 | E66: =D66 -> 23.1392
